Workbook

Sheet Léeme
A1: Hoja de parámetros del generador de datos sintéticos (Objetivo 1)
A2: Modelo predictivo con datos sintéticos para la estimación de tiempos y la asignación de recursos en laboratorios de control de calidad farmacéuticos
A4: Para qué sirve | B4: Reúne los parámetros operativos que reportan las cinco fuentes de calibración del anteproyecto, cada uno con su página, para construir el generador (bloques del 25 al 31 de octubre) y para la tabla de trazabilidad que arma Aldair el jueves 29.
A5: Hojas | B5: Parámetros (lista completa) · Duraciones (tres puntos por técnica y tarea, con media y desviación PERT) · Demanda (mezcla, volumen y escenarios de carga) · Catálogo (12 métodos: complejidad, soluciones, calificación mínima, participación, corrida, reanálisis y tipos de muestra) · Calibración del catálogo (cómo salen esas columnas de las fuentes) · Tipos de muestra (5 tipos: proporción, llegadas, plazo, prioridad, urgentes y probabilidad de cada método) · Calibración de tipos (cómo se reparte cada método entre los tipos sin cambiar la mezcla de técnicas) · Equipos (10 configuraciones: cantidad y compatibilidad con cada método) · Analistas (20 analistas: turno, nivel, área y matriz de calificación) · Calibración de recursos (horas de equipo, cobertura y chequeos) · Turnos (horario de cada código de turno) · Rotación (calendario de 6 semanas por analista) · Mantenimiento (ventanas planificadas y fallas por configuración) · Calibración de turnos (rotación, horas, analistas por franja y fallas) · Diccionario (51 campos del registro: tipo, unidad, valores, cuándo se conoce, papel en el O2, regla que los verifica e indicadores que alimentan) · Indicadores (los 22 indicadores del sistema de variables: cálculo, campos y criterio) · Correlaciones (correlación objetivo entre las tareas de un ensayo y de dónde sale cada una) · Supuestos (lo que no está en las fuentes y deben decidir) · Contraste estructural (para el bloque del 1 de noviembre) · Fuentes (APA 7).
A6: Catálogo | B6: Las decisiones son las celdas amarillas: la complejidad de cada método y las marcas de tipo de muestra (hoja Catálogo), y la regla de complejidad, los multiplicadores de reanálisis y las relaciones de corrida (hoja Calibración del catálogo). Si cambian una complejidad, la participación de los métodos se recalcula para conservar los promedios de Costigliola et al. (2017); revisen la columna «Chequeo» de la calibración. El generador lee la hoja Catálogo con cargar_hoja("Catálogo").
A7: Tipos de muestra | B7: Las decisiones son las celdas amarillas de la hoja Tipos de muestra: la proporción de cada tipo, sus llegadas, su plazo y si puede llegar como urgente. La probabilidad de cada método dentro de cada tipo se recalcula sola (ajuste proporcional iterativo) para conservar la mezcla de técnicas de Costigliola et al. (2017); revisen los chequeos del bloque E de la hoja Calibración de tipos.
A8: Equipos y analistas | B8: Las decisiones son las celdas amarillas: cantidad de equipos y compatibilidad (hoja Equipos), nivel y área de cada analista (hoja Analistas), y configuración principal de cada método, factores de experiencia y áreas (hoja Calibración de recursos). La matriz de calificación se calcula sola: un analista está calificado para un método si su nivel alcanza la calificación mínima del método y si la técnica está en su área. Revisen los chequeos de la hoja Calibración de recursos.
A9: Turnos y mantenimiento | B9: Las decisiones son las celdas amarillas: horario de cada código (hoja Turnos), desfase de rotación y grupo de almuerzo de cada analista (hoja Calibración de turnos), y frecuencia y duración de las ventanas de mantenimiento y verificación (hoja Mantenimiento). La hoja Rotación se calcula sola y se repite cada 42 días (6 semanas).
A10: Registro del dataset | B10: La unidad de análisis (un registro por ejecución de un ensayo sobre una muestra) y los 51 campos del registro están en docs/Diccionario_de_datos.docx, en la hoja Diccionario y en src/generador/registro.py, que verifica cada regla; la hoja Indicadores amarra los campos con el sistema de variables. Sus supuestos son S27 y S28 (hoja Supuestos) y sus datos, el bloque «Estructura del registro» de la hoja Parámetros.
A11: Columna «Tipo» | B11: Dato de la literatura = valor tal como aparece en la fuente. Derivado = cálculo propio a partir de datos de la fuente (la fórmula está en la celda). Supuesto = no aparece en las fuentes revisadas: hay que justificarlo o tratarlo con escenarios.
A12: Colores | B12: Texto azul = valor tomado de la fuente (no editar salvo que encuentren un error). Texto negro = fórmula. Fondo amarillo = supuesto que deben decidir ustedes (son las únicas celdas pensadas para editar).
A13: Páginas | B13: Se cita el número de página de la revista (el que va en APA), no el del PDF. Ejemplo: Costigliola et al. (2017) va de la p. 9014 a la 9019.
A14: Ojo 1 | B14: Costigliola et al. (2017) usa distribuciones triangulares T(mín, moda, máx). El anteproyecto usa BetaPERT con esos mismos tres puntos: declárenlo en la metodología como una adaptación propia.
A15: Ojo 2 | B15: Las cinco fuentes no traen valores para la tasa de reanálisis por OOS, la indisponibilidad de equipos, el porcentaje de urgentes ni los coeficientes de correlación. Están en la hoja Supuestos con una propuesta de escenarios; necesitan fuente o se declaran como supuestos.
... A17: Ojo 4 | B17: Con BetaPERT estándar (λ = 4) las medias quedan por debajo de las de la triangular de la fuente, porque estas distribuciones son asimétricas: en la preparación del análisis, entre 7 % y 22 % según la técnica (hoja Calibración del catálogo, bloque B). Se decide en el bloque de duraciones: usar λ = 1, que conserva la media de la triangular, o declarar la diferencia.
A19: Ejemplo de colores
A20: 70 | B20: ← dato de la fuente (texto azul)
A21: =A20*1.5 -> 105 | B21: ← fórmula (texto negro)
A22: 0.05 | B22: ← supuesto que deben decidir (fondo amarillo)

Sheet Parámetros
A1: Parámetros con fuente y página
A2: Una fila por parámetro. Filtren por Bloque, Tipo o Dimensión con los filtros del encabezado.
A4: ID | B4: Bloque | C4: Parámetro | D4: Valor | E4: Unidad | F4: Tipo | G4: Fuente | H4: Página / ubicación | I4: Uso sugerido en el generador | J4: Dimensión del sistema de variables
A5: P01 | B5: Laboratorio y recursos | C5: Equipos del laboratorio de referencia | D5: 70 | E5: equipos | F5: Dato de la literatura | G5: Costigliola et al. (2017) | H5: p. 9015, §2 | I5: Tamaño de la planta de equipos del escenario base. | J5: Recursos materiales
A6: P02 | B6: Laboratorio y recursos | C6: Tipos de equipo / técnica analítica | D6: 6: HPLC, GC, PSA (tamaño de partícula), titulación Karl Fischer (KF), DSC y XRPD | E6: tipos | F6: Dato de la literatura | G6: Costigliola et al. (2017) | H6: p. 9015, §2 | I6: Catálogo de técnicas del laboratorio de referencia. | J6: Recursos materiales
A7: P03 | B7: Laboratorio y recursos | C7: Analistas | D7: 20 | E7: analistas | F7: Dato de la literatura | G7: Costigliola et al. (2017) | H7: p. 9015, §2 y §2.1 | I7: Tamaño de la plantilla del escenario base. | J7: Recursos humanos
A8: P04 | B8: Laboratorio y recursos | C8: Horario de operación | D8: 24 h, 7 días para control en proceso; estabilidad, desarrollo y validación de lunes a viernes | E8: No aplica | F8: Dato de la literatura | G8: Costigliola et al. (2017) | H8: p. 9015, §2.1 | I8: Calendario de disponibilidad del laboratorio. | J8: Recursos humanos
A9: P05 | B9: Laboratorio y recursos | C9: Turnos (Tabla 1) | D9: Turno 1: 7 días, 8:00–20:00 y 20:00–8:00, 2 analistas por turno · Turno 2: 5 días, 8:00–17:00 y 17:00–24:00, 2 por turno · Turno 3: 5 días, 8:00–17:00, 10 analistas | E9: No aplica | F9: Dato de la literatura | G9: Costigliola et al. (2017) | H9: p. 9015, Tabla 1 | I9: Calendarios de disponibilidad de cada analista. | J9: Recursos humanos
A10: P06 | B10: Laboratorio y recursos | C10: Distribución de la plantilla por turno | D10: 6 analistas en turnos rotativos de 12 h, 4 en dos turnos de 8 h y 10 en turno fijo de 8 h, 5 días a la semana | E10: No aplica | F10: Dato de la literatura | G10: Costigliola et al. (2017) | H10: p. 9015, §2.1 | I10: Asignar turno a cada analista generado. | J10: Recursos humanos
A11: P07 | B11: Laboratorio y recursos | C11: Recursos en instancia diaria realista | D11: 15 máquinas y 5 analistas | E11: No aplica | F11: Dato de la literatura | G11: Cunha et al. (2019) | H11: p. 1425, §4.2 | I11: Escenario reducido (diario) para pruebas rápidas del simulador. | J11: Recursos materiales
A12: P08 | B12: Laboratorio y recursos | C12: Recursos en experimentos de Martins | D12: 7 máquinas (tipos de equipo); 2, 3 o 7 analistas (restringido por analistas, balanceado, restringido por máquinas) | E12: No aplica | F12: Dato de la literatura | G12: Martins et al. (2023) | H12: p. 191, §6.1 | I12: Inspiración para escenarios con distinta relación analistas/equipos. | J12: Recursos humanos
A13: P09 | B13: Estructura de ensayos | C13: Tareas de un análisis (modelo de Costigliola) | D13: Preparación del sistema (soluciones y materiales), montaje del equipo, preparación de la muestra en paralelo con la idoneidad del sistema, análisis y procesamiento de datos | E13: No aplica | F13: Dato de la literatura | G13: Costigliola et al. (2017) | H13: pp. 9015–9016, Fig. 1 | I13: Secuencia de tareas de cada actividad analítica. | J13: Tiempos de ejecución
A14: P10 | B14: Estructura de ensayos | C14: Tareas de un ensayo (modelo de Coito) | D14: Seis tareas en orden: preparación del sistema, idoneidad del sistema, preparación de la muestra, corrida analítica, procesamiento de datos y revisión | E14: No aplica | F14: Dato de la literatura | G14: Coito et al. (2021) | H14: p. 72, §4 | I14: Igual al anterior, más la revisión final. | J14: Tiempos de ejecución
A15: P11 | B15: Estructura de ensayos | C15: Recurso que exige cada tarea | D15: Analista, equipo o ambos; el recurso puede requerirse toda la tarea o solo un porcentaje de ella | E15: No aplica | F15: Dato de la literatura | G15: Coito et al. (2021) | H15: p. 72, §4 | I15: Marcar en cada tarea si ocupa analista, equipo o ambos. | J15: Disponibilidad cruzada de recursos
A16: P12 | B16: Estructura de ensayos | C16: Analista como recurso secundario | D16: El analista es un recurso secundario que solo se requiere en tareas específicas; en la Fig. 3, el equipo queda ocupado desde el inicio de la idoneidad hasta el fin de la corrida | E16: No aplica | F16: Dato de la literatura | G16: Costigliola et al. (2017) | H16: p. 9017, §3.3 | I16: Doble restricción: el equipo se ocupa entero y el analista por tramos. | J16: Disponibilidad cruzada de recursos
A17: P13 | B17: Estructura de ensayos | C17: Unidad de análisis | D17: La pareja muestra/análisis es una entidad y se procesa en un solo equipo | E17: No aplica | F17: Dato de la literatura | G17: Costigliola et al. (2017) | H17: p. 9017, §3.3 (supuesto 1) | I17: Coincide con la unidad de análisis del anteproyecto (§1.4). | J17: Variabilidad y consistencia estructural
A18: P14 | B18: Estructura de ensayos | C18: Ensayos por muestra | D18: 85 % de las muestras con 1 ensayo, ~10 % con 2 y ~5 % con 3 | E18: % de muestras | F18: Dato de la literatura | G18: Cunha et al. (2019) | H18: p. 1425, §4.2 | I18: Número de actividades por muestra (ver hoja Demanda). | J18: Variabilidad y consistencia estructural
A19: P15 | B19: Estructura de ensayos | C19: Tipos de trabajo (Tabla 1) | D19: A: 3 operaciones con precedencia (tiempos 3, 2, 1) · B: 2 operaciones con precedencia (5, 4) · C: 1 operación (1) | E19: unidades de tiempo | F19: Dato de la literatura | G19: Cunha et al. (2019) | H19: p. 1424, Tabla 1 | I19: Plantillas de muestra con precedencias entre ensayos. | J19: Variabilidad y consistencia estructural
... A83: P79 | B83: Estructura del registro | C83: Predecesores de una tarea | D83: Cada tarea puede tener una lista de predecesores directos, solo dentro del mismo proyecto | E83: No aplica | F83: Dato de la literatura | G83: Mischek y Musliu (2021) | H83: p. 539, §3 | I83: No se aplica (S28); en el TLSP la precedencia es opcional. | J83: Variabilidad y consistencia estructural

Sheet Duraciones
A1: Duraciones: tres puntos por técnica y tarea
A2: Costigliola et al. (2017), Tabla 3, p. 9016. Minutos. a = mínimo, m = moda, b = máximo. Media PERT y desviaciones con fórmula: la aproximada de los libros, (b−a)/6, y la exacta de la BetaPERT con λ = 4, que usa src/generador/duraciones.py.
A4: Técnica | B4: Tarea | C4: Distribución original | D4: a (mín) | E4: m (moda) | F4: b (máx) | G4: Media PERT (a+4m+b)/6 | H4: Desv. aproximada (b−a)/6 | I4: Desv. BetaPERT exacta (λ = 4) | J4: Media triangular (a+m+b)/3 | K4: Tipo | L4: Nota
A5: HPLC | B5: Preparación de muestra | C5: T(5, 40, 100) | D5: 5 | E5: 40 | F5: 100 | G5: =IF(COUNT(D5:F5)=3,(D5+4*E5+F5)/6,"") -> 44.166667 | H5: =IF(COUNT(D5:F5)=3,(F5-D5)/6,"") -> 15.833333 | I5: =IF(COUNT(D5:F5)=3,SQRT((G5-D5)*(F5-G5)/7),"") -> 17.674863 | J5: =IF(COUNT(D5:F5)=3,(D5+E5+F5)/3,"") -> 48.333333 | K5: Dato de la literatura
A6: HPLC | B6: Montaje del equipo | C6: T(25, 50, 65) | D6: 25 | E6: 50 | F6: 65 | G6: =IF(COUNT(D6:F6)=3,(D6+4*E6+F6)/6,"") -> 48.333333 | H6: =IF(COUNT(D6:F6)=3,(F6-D6)/6,"") -> 6.6666667 | I6: =IF(COUNT(D6:F6)=3,SQRT((G6-D6)*(F6-G6)/7),"") -> 7.4535599 | J6: =IF(COUNT(D6:F6)=3,(D6+E6+F6)/3,"") -> 46.666667 | K6: Dato de la literatura
A7: HPLC | B7: Corrida | C7: Det. | G7: =IF(COUNT(D7:F7)=3,(D7+4*E7+F7)/6,"") | H7: =IF(COUNT(D7:F7)=3,(F7-D7)/6,"") | I7: =IF(COUNT(D7:F7)=3,SQRT((G7-D7)*(F7-G7)/7),"") | J7: =IF(COUNT(D7:F7)=3,(D7+E7+F7)/3,"") | K7: Dato + supuesto | L7: Determinista en la fuente (sale del informe de cada método, no se publica). La corrida por método está en la hoja Catálogo (supuestos S05 y S14).
A8: HPLC | B8: Procesamiento de datos | C8: T(2, 5, 10) | D8: 2 | E8: 5 | F8: 10 | G8: =IF(COUNT(D8:F8)=3,(D8+4*E8+F8)/6,"") -> 5.3333333 | H8: =IF(COUNT(D8:F8)=3,(F8-D8)/6,"") -> 1.3333333 | I8: =IF(COUNT(D8:F8)=3,SQRT((G8-D8)*(F8-G8)/7),"") -> 1.490712 | J8: =IF(COUNT(D8:F8)=3,(D8+E8+F8)/3,"") -> 5.6666667 | K8: Dato de la literatura
A9: GC | B9: Preparación de muestra | C9: T(5, 10, 35) | D9: 5 | E9: 10 | F9: 35 | G9: =IF(COUNT(D9:F9)=3,(D9+4*E9+F9)/6,"") -> 13.333333 | H9: =IF(COUNT(D9:F9)=3,(F9-D9)/6,"") -> 5 | I9: =IF(COUNT(D9:F9)=3,SQRT((G9-D9)*(F9-G9)/7),"") -> 5.078745 | J9: =IF(COUNT(D9:F9)=3,(D9+E9+F9)/3,"") -> 16.666667 | K9: Dato de la literatura
A10: GC | B10: Montaje del equipo | C10: T(2, 5, 30) | D10: 2 | E10: 5 | F10: 30 | G10: =IF(COUNT(D10:F10)=3,(D10+4*E10+F10)/6,"") -> 8.6666667 | H10: =IF(COUNT(D10:F10)=3,(F10-D10)/6,"") -> 4.6666667 | I10: =IF(COUNT(D10:F10)=3,SQRT((G10-D10)*(F10-G10)/7),"") -> 4.5074894 | J10: =IF(COUNT(D10:F10)=3,(D10+E10+F10)/3,"") -> 12.333333 | K10: Dato de la literatura
A11: GC | B11: Corrida | C11: Det. | G11: =IF(COUNT(D11:F11)=3,(D11+4*E11+F11)/6,"") | H11: =IF(COUNT(D11:F11)=3,(F11-D11)/6,"") | I11: =IF(COUNT(D11:F11)=3,SQRT((G11-D11)*(F11-G11)/7),"") | J11: =IF(COUNT(D11:F11)=3,(D11+E11+F11)/3,"") | K11: Dato + supuesto | L11: Determinista en la fuente (sale del informe de cada método, no se publica). La corrida por método está en la hoja Catálogo (supuestos S05 y S14).
A12: GC | B12: Procesamiento de datos | C12: T(10, 20, 45) | D12: 10 | E12: 20 | F12: 45 | G12: =IF(COUNT(D12:F12)=3,(D12+4*E12+F12)/6,"") -> 22.5 | H12: =IF(COUNT(D12:F12)=3,(F12-D12)/6,"") -> 5.8333333 | I12: =IF(COUNT(D12:F12)=3,SQRT((G12-D12)*(F12-G12)/7),"") -> 6.3386569 | J12: =IF(COUNT(D12:F12)=3,(D12+E12+F12)/3,"") -> 25 | K12: Dato de la literatura
A13: PSA | B13: Preparación de muestra | C13: T(5, 7.5, 21) | D13: 5 | E13: 7.5 | F13: 21 | G13: =IF(COUNT(D13:F13)=3,(D13+4*E13+F13)/6,"") -> 9.3333333 | H13: =IF(COUNT(D13:F13)=3,(F13-D13)/6,"") -> 2.6666667 | I13: =IF(COUNT(D13:F13)=3,SQRT((G13-D13)*(F13-G13)/7),"") -> 2.6874192 | J13: =IF(COUNT(D13:F13)=3,(D13+E13+F13)/3,"") -> 11.166667 | K13: Dato de la literatura
A14: PSA | B14: Montaje del equipo | C14: U(1, 32) | D14: 1 | E14: =(D14+F14)/2 -> 16.5 | F14: 32 | G14: =IF(COUNT(D14:F14)=3,(D14+4*E14+F14)/6,"") -> 16.5 | H14: =IF(COUNT(D14:F14)=3,(F14-D14)/6,"") -> 5.1666667 | I14: =IF(COUNT(D14:F14)=3,SQRT((G14-D14)*(F14-G14)/7),"") -> 5.8584493 | J14: =IF(COUNT(D14:F14)=3,(D14+E14+F14)/3,"") -> 16.5 | K14: Dato + supuesto | L14: La fuente da una uniforme U(mín, máx). Para BetaPERT se propone la moda en el punto medio (supuesto); también pueden dejarla uniforme.
A15: PSA | B15: Corrida | C15: T(5, 10, 30) | D15: 5 | E15: 10 | F15: 30 | G15: =IF(COUNT(D15:F15)=3,(D15+4*E15+F15)/6,"") -> 12.5 | H15: =IF(COUNT(D15:F15)=3,(F15-D15)/6,"") -> 4.1666667 | I15: =IF(COUNT(D15:F15)=3,SQRT((G15-D15)*(F15-G15)/7),"") -> 4.330127 | J15: =IF(COUNT(D15:F15)=3,(D15+E15+F15)/3,"") -> 15 | K15: Dato de la literatura
A16: PSA | B16: Procesamiento de datos | C16: T(2, 6, 10) | D16: 2 | E16: 6 | F16: 10 | G16: =IF(COUNT(D16:F16)=3,(D16+4*E16+F16)/6,"") -> 6 | H16: =IF(COUNT(D16:F16)=3,(F16-D16)/6,"") -> 1.3333333 | I16: =IF(COUNT(D16:F16)=3,SQRT((G16-D16)*(F16-G16)/7),"") -> 1.5118579 | J16: =IF(COUNT(D16:F16)=3,(D16+E16+F16)/3,"") -> 6 | K16: Dato de la literatura
A17: KF | B17: Preparación de muestra | C17: T(1, 6, 25) | D17: 1 | E17: 6 | F17: 25 | G17: =IF(COUNT(D17:F17)=3,(D17+4*E17+F17)/6,"") -> 8.3333333 | H17: =IF(COUNT(D17:F17)=3,(F17-D17)/6,"") -> 4 | I17: =IF(COUNT(D17:F17)=3,SQRT((G17-D17)*(F17-G17)/7),"") -> 4.1785545 | J17: =IF(COUNT(D17:F17)=3,(D17+E17+F17)/3,"") -> 10.666667 | K17: Dato de la literatura
A18: KF | B18: Montaje del equipo | C18: T(4, 8, 16) | D18: 4 | E18: 8 | F18: 16 | G18: =IF(COUNT(D18:F18)=3,(D18+4*E18+F18)/6,"") -> 8.6666667 | H18: =IF(COUNT(D18:F18)=3,(F18-D18)/6,"") -> 2 | I18: =IF(COUNT(D18:F18)=3,SQRT((G18-D18)*(F18-G18)/7),"") -> 2.2110832 | J18: =IF(COUNT(D18:F18)=3,(D18+E18+F18)/3,"") -> 9.3333333 | K18: Dato de la literatura
A19: KF | B19: Corrida | C19: T(2, 5, 56) | D19: 2 | E19: 5 | F19: 56 | G19: =IF(COUNT(D19:F19)=3,(D19+4*E19+F19)/6,"") -> 13 | H19: =IF(COUNT(D19:F19)=3,(F19-D19)/6,"") -> 9 | I19: =IF(COUNT(D19:F19)=3,SQRT((G19-D19)*(F19-G19)/7),"") -> 8.2201842 | J19: =IF(COUNT(D19:F19)=3,(D19+E19+F19)/3,"") -> 21 | K19: Dato de la literatura
A20: KF | B20: Procesamiento de datos | C20: T(10, 20, 30) | D20: 10 | E20: 20 | F20: 30 | G20: =IF(COUNT(D20:F20)=3,(D20+4*E20+F20)/6,"") -> 20 | H20: =IF(COUNT(D20:F20)=3,(F20-D20)/6,"") -> 3.3333333 | I20: =IF(COUNT(D20:F20)=3,SQRT((G20-D20)*(F20-G20)/7),"") -> 3.7796447 | J20: =IF(COUNT(D20:F20)=3,(D20+E20+F20)/3,"") -> 20 | K20: Dato de la literatura
A21: DSC | B21: Preparación de muestra | C21: T(5, 10, 30) | D21: 5 | E21: 10 | F21: 30 | G21: =IF(COUNT(D21:F21)=3,(D21+4*E21+F21)/6,"") -> 12.5 | H21: =IF(COUNT(D21:F21)=3,(F21-D21)/6,"") -> 4.1666667 | I21: =IF(COUNT(D21:F21)=3,SQRT((G21-D21)*(F21-G21)/7),"") -> 4.330127 | J21: =IF(COUNT(D21:F21)=3,(D21+E21+F21)/3,"") -> 15 | K21: Dato de la literatura
A22: DSC | B22: Montaje del equipo | C22: T(1, 3, 12) | D22: 1 | E22: 3 | F22: 12 | G22: =IF(COUNT(D22:F22)=3,(D22+4*E22+F22)/6,"") -> 4.1666667 | H22: =IF(COUNT(D22:F22)=3,(F22-D22)/6,"") -> 1.8333333 | I22: =IF(COUNT(D22:F22)=3,SQRT((G22-D22)*(F22-G22)/7),"") -> 1.8824587 | J22: =IF(COUNT(D22:F22)=3,(D22+E22+F22)/3,"") -> 5.3333333 | K22: Dato de la literatura
A23: DSC | B23: Corrida | C23: U(12, 180) | D23: 12 | E23: =(D23+F23)/2 -> 96 | F23: 180 | G23: =IF(COUNT(D23:F23)=3,(D23+4*E23+F23)/6,"") -> 96 | H23: =IF(COUNT(D23:F23)=3,(F23-D23)/6,"") -> 28 | I23: =IF(COUNT(D23:F23)=3,SQRT((G23-D23)*(F23-G23)/7),"") -> 31.749016 | J23: =IF(COUNT(D23:F23)=3,(D23+E23+F23)/3,"") -> 96 | K23: Dato + supuesto | L23: La fuente da una uniforme U(mín, máx). Para BetaPERT se propone la moda en el punto medio (supuesto); también pueden dejarla uniforme.
A24: DSC | B24: Procesamiento de datos | C24: T(4, 9, 16) | D24: 4 | E24: 9 | F24: 16 | G24: =IF(COUNT(D24:F24)=3,(D24+4*E24+F24)/6,"") -> 9.3333333 | H24: =IF(COUNT(D24:F24)=3,(F24-D24)/6,"") -> 2 | I24: =IF(COUNT(D24:F24)=3,SQRT((G24-D24)*(F24-G24)/7),"") -> 2.2537447 | J24: =IF(COUNT(D24:F24)=3,(D24+E24+F24)/3,"") -> 9.6666667 | K24: Dato de la literatura
A25: XRPD | B25: Preparación de muestra | C25: T(5, 10, 20) | D25: 5 | E25: 10 | F25: 20 | G25: =IF(COUNT(D25:F25)=3,(D25+4*E25+F25)/6,"") -> 10.833333 | H25: =IF(COUNT(D25:F25)=3,(F25-D25)/6,"") -> 2.5 | I25: =IF(COUNT(D25:F25)=3,SQRT((G25-D25)*(F25-G25)/7),"") -> 2.763854 | J25: =IF(COUNT(D25:F25)=3,(D25+E25+F25)/3,"") -> 11.666667 | K25: Dato de la literatura
A26: XRPD | B26: Montaje del equipo | C26: T(1, 5, 20) | D26: 1 | E26: 5 | F26: 20 | G26: =IF(COUNT(D26:F26)=3,(D26+4*E26+F26)/6,"") -> 6.8333333 | H26: =IF(COUNT(D26:F26)=3,(F26-D26)/6,"") -> 3.1666667 | I26: =IF(COUNT(D26:F26)=3,SQRT((G26-D26)*(F26-G26)/7),"") -> 3.3124345 | J26: =IF(COUNT(D26:F26)=3,(D26+E26+F26)/3,"") -> 8.6666667 | K26: Dato de la literatura
A27: XRPD | B27: Corrida | C27: T(11, 25, 203) | D27: 11 | E27: 25 | F27: 203 | G27: =IF(COUNT(D27:F27)=3,(D27+4*E27+F27)/6,"") -> 52.333333 | H27: =IF(COUNT(D27:F27)=3,(F27-D27)/6,"") -> 32 | I27: =IF(COUNT(D27:F27)=3,SQRT((G27-D27)*(F27-G27)/7),"") -> 29.827014 | J27: =IF(COUNT(D27:F27)=3,(D27+E27+F27)/3,"") -> 79.666667 | K27: Dato de la literatura
A28: XRPD | B28: Procesamiento de datos | C28: T(2, 7, 30) | D28: 2 | E28: 7 | F28: 30 | G28: =IF(COUNT(D28:F28)=3,(D28+4*E28+F28)/6,"") -> 10 | H28: =IF(COUNT(D28:F28)=3,(F28-D28)/6,"") -> 4.6666667 | I28: =IF(COUNT(D28:F28)=3,SQRT((G28-D28)*(F28-G28)/7),"") -> 4.7809144 | J28: =IF(COUNT(D28:F28)=3,(D28+E28+F28)/3,"") -> 13 | K28: Dato de la literatura
A29: Fuente: Costigliola et al. (2017), Tabla 3, p. 9016. La conversión de triangular a BetaPERT con los mismos tres puntos es una adaptación propia (declararla en la metodología).
A31: Tiempos promedio por tarea del modelo de Costigliola et al. (2017, Tabla 6, p. 9019) · min · promedio ± desviación (la fuente no explica el ± de esta tabla; en la Tabla 5 es entre corridas, p. 9018)
A32: Técnica | B32: Prep. del sistema | C32: Idoneidad del sistema | D32: Prep. del análisis | E32: Análisis | F32: Proc. de datos
A33: HPLC | B33: 207 ± 14 | C33: 227 ± 11 | D33: 96 ± 3 | E33: 85 ± 1 | F33: 59 ± 2
A34: GC | B34: 67 ± 5 | C34: 152 ± 5 | D34: 48 ± 1 | E34: 62 ± 1 | F34: 39 ± 1
A35: PSA | B35: n.a. | C35: n.a. | D35: 31 ± 1 | E35: 32 ± 1 | F35: 16 ± 1
A36: KF | B36: n.a. | C36: n.a. | D36: 45 ± 3 | E36: 30 ± 2 | F36: 29 ± 2
A37: DSC | B37: n.a. | C37: n.a. | D37: 47 ± 2 | E37: 101 ± 3 | F37: 24 ± 2
A38: XRPD | B38: n.a. | C38: n.a. | D38: 46 ± 1 | E38: 88 ± 3 | F38: 30 ± 1
A39: Uso: referencia de validación para la preparación del análisis y la corrida de HPLC y GC. El procesamiento de datos y la corrida de PSA y KF de esta tabla superan la media (y a veces el máximo) de la Tabla 3, y la fuente no explica por qué. Prep. del sistema/análisis = prep. de muestra × n.º de soluciones (p. 9019).
A41: Tiempos promedio por tarea: estimación de expertos vs. medición (Coito et al., 2021, Tabla 2, p. 74) · min
A42: Tarea | B42: Expertos (sistema anterior) | C42: Medido (sistema propuesto) | D42: Diferencia (fórmula) | E42: Reducción (fórmula) | F42: Reducción reportada
A43: Preparación del sistema | B43: 139 | C43: 93 | D43: =B43-C43 -> 46 | E43: =IF(B43=0,"",D43/B43) -> 0.33093525 | F43: 0.33
A44: Idoneidad del sistema | B44: 159 | C44: 102 | D44: =B44-C44 -> 57 | E44: =IF(B44=0,"",D44/B44) -> 0.35849057 | F44: 0.36
A45: Preparación de muestra | B45: 143 | C45: 117 | D45: =B45-C45 -> 26 | E45: =IF(B45=0,"",D45/B45) -> 0.18181818 | F45: 0.18
A46: Corrida analítica | B46: 221 | C46: 217 | D46: =B46-C46 -> 4 | E46: =IF(B46=0,"",D46/B46) -> 0.018099548 | F46: 0.02
A47: Total (suma) | B47: =SUM(B43:B46) -> 662 | C47: =SUM(C43:C46) -> 529 | D47: =B47-C47 -> 133 | E47: =IF(B47=0,"",D47/B47) -> 0.20090634 | F47: 0.2
A48: La fuente reporta un total de 662 min (expertos) y 529 min (medido); la suma de la tabla debe coincidir. El 90 % de los ensayos queda entre 458 y 786 min (p. 74).

Sheet Demanda
A1: Demanda: mezcla, volumen y escenarios de carga
A2: Datos de Costigliola et al. (2017) y Cunha et al. (2019). Las celdas amarillas son supuestos que pueden cambiar.
A4: Técnica | B4: % de análisis (Tabla 2) | C4: Análisis requeridos al año (Tabla 4) | D4: % según Tabla 4 (fórmula) | E4: Promedio por día calendario (fórmula) | F4: Promedio por día hábil (fórmula)
A5: HPLC | B5: 0.407 | C5: 6099 | D5: =C5/$C$11 -> 0.39802911 | E5: =C5/$B$14 -> 16.709589 | F5: =C5/$B$15 -> 23.457692
A6: GC | B6: 0.257 | C6: 3910 | D6: =C6/$C$11 -> 0.25517196 | E6: =C6/$B$14 -> 10.712329 | F6: =C6/$B$15 -> 15.038462
A7: PSA | B7: 0.188 | C7: 3014 | D7: =C7/$C$11 -> 0.19669777 | E7: =C7/$B$14 -> 8.2575342 | F7: =C7/$B$15 -> 11.592308
A8: KF | B8: 0.071 | C8: 1240 | D8: =C8/$C$11 -> 0.080924101 | E8: =C8/$B$14 -> 3.3972603 | F8: =C8/$B$15 -> 4.7692308
A9: DSC | B9: 0.04 | C9: 581 | D9: =C9/$C$11 -> 0.037916857 | E9: =C9/$B$14 -> 1.5917808 | F9: =C9/$B$15 -> 2.2346154
A10: XRPD | B10: 0.037 | C10: 479 | D10: =C10/$C$11 -> 0.031260197 | E10: =C10/$B$14 -> 1.3123288 | F10: =C10/$B$15 -> 1.8423077
A11: Total | B11: =SUM(B5:B10) -> 1 | C11: =SUM(C5:C10) -> 15323 | D11: =SUM(D5:D10) -> 1 | E11: =SUM(E5:E10) -> 41.980822 | F11: =SUM(F5:F10) -> 58.934615
A12: Fuente: Costigliola et al. (2017), Tabla 2 (p. 9016) y Tabla 4 (p. 9018, año 2015). Las dos tablas no coinciden exactamente (hasta 1 punto porcentual) y la fuente no explica por qué: la Tabla 2 sale de la tabla de llegadas del LIMS (p. 9016) y la Tabla 4, de la validación con el año 2015 (p. 9018); elijan una y declárenlo.
A14: Días calendario al año | B14: 365 | C14: El control en proceso funciona 24/7 (Costigliola et al., 2017, p. 9015).
A15: Días hábiles al año | B15: 260 | C15: Supuesto: 52 semanas × 5 días (estabilidad, desarrollo y validación van de lunes a viernes, p. 9015).
A17: Ensayos por muestra (Cunha et al., 2019, p. 1425)
A18: N.º de ensayos | B18: % de muestras | C18: Aporte (fórmula)
A19: 1 | B19: 0.85 | C19: =A19*B19 -> 0.85
A20: 2 | B20: 0.1 | C20: =A20*B20 -> 0.2
A21: 3 | B21: 0.05 | C21: =A21*B21 -> 0.15
A22: Ensayos promedio por muestra | C22: =SUM(C19:C21) -> 1.2
A23: Chequeo: los % suman | C23: =SUM(B19:B21) -> 1
A25: Escenarios de carga (análisis por día calendario)
A26: Escenario | B26: Multiplicador | C26: Análisis por día (fórmula) | D26: Muestras por día (fórmula) | E26: Origen
A27: Baja | B27: 0.7 | C27: =$E$11*B27 -> 29.386575 | D27: =IF($C$22=0,"",C27/$C$22) -> 24.488813 | E27: Supuesto: −30 % respecto a la base (pueden cambiarlo).
A28: Base | B28: 1 | C28: =$E$11*B28 -> 41.980822 | D28: =IF($C$22=0,"",C28/$C$22) -> 34.984018 | E28: Volumen 2015 de Costigliola et al. (2017), Tabla 4.
A29: Alta | B29: 1.5 | C29: =$E$11*B29 -> 62.971233 | D29: =IF($C$22=0,"",C29/$C$22) -> 52.476027 | E29: +50 %, escenario 2 de Costigliola et al. (2017), p. 9019.
A31: Chequeo con Cunha et al. (2019, pp. 1424–1425): una carga diaria realista tiene 30–40 trabajos y 35–52 operaciones; comparen con la fila Base.

Sheet Catálogo
A1: Catálogo de métodos del laboratorio de referencia
A2: Doce ensayos típicos, dos por técnica. Amarillo = decisión (complejidad y tipos de muestra); el resto se calcula en la hoja Calibración del catálogo.
A3: Fuentes: técnicas y mezcla de Costigliola et al. (2017, pp. 9015–9016); ensayos de ICH Q6A (1999, §3.2.1 y §3.3.1); capítulos generales de la USP–NF. Tipos de muestra: MP materia prima, IN intermedio, GR granel, PT producto terminado, ES estabilidad.
A4: ID | B4: Técnica | C4: Ensayo | D4: Qué mide | E4: Referencia | F4: Equipo requerido | G4: Requiere idoneidad | H4: Complejidad | I4: Soluciones mín | J4: Soluciones máx | K4: Calificación mínima | L4: Participación en la técnica | M4: Participación en la demanda | N4: Corrida: regla | O4: Corrida mín (min) | P4: Corrida moda (min) | Q4: Corrida máx (min) | R4: Cuantil desde | S4: Cuantil hasta | T4: Corrida promedio (min) | U4: Prob. de reanálisis | V4: MP | W4: IN | X4: GR | Y4: PT | Z4: ES | AA4: Por qué esa complejidad
A5: M01 | B5: HPLC | C5: Valoración del principio activo | D5: Contenido del principio activo frente a un estándar de referencia; la identificación por tiempo de retención sale de la misma corrida | E5: USP <621> | F5: HPLC con detector UV | G5: Sí | H5: baja | I5: =INDEX('Calibración del catálogo'!$B$6:$B$8,MATCH(H5,'Calibración del catálogo'!$A$6:$A$8,0)) -> 1 | J5: =INDEX('Calibración del catálogo'!$C$6:$C$8,MATCH(H5,'Calibración del catálogo'!$A$6:$A$8,0)) -> 2 | K5: =INDEX('Calibración del catálogo'!$E$6:$E$8,MATCH(H5,'Calibración del catálogo'!$A$6:$A$8,0)) -> Júnior o superior | L5: =IFERROR(INDEX('Calibración del catálogo'!$L$16:$L$21,MATCH(A5,'Calibración del catálogo'!$H$16:$H$21,0)),INDEX('Calibración del catálogo'!$M$16:$M$21,MATCH(A5,'Calibración del catálogo'!$J$16:$J$21,0))) -> 0.75689655 | M5: =IFERROR(L5*INDEX(Demanda!$B$5:$B$10,MATCH(B5,Demanda!$A$5:$A$10,0)),"revisar") -> 0.3080569 | N5: Triangular alrededor de la moda (S05 y S14) | O5: =IFERROR(P5*(1-'Calibración del catálogo'!$D$25),"revisar") -> 49.829438 | P5: ='Calibración del catálogo'!E25 -> 62.286797 | Q5: =IFERROR(P5*(1+'Calibración del catálogo'!$D$25),"revisar") -> 74.744157 | T5: =P5 -> 62.286797 | U5: =INDEX('Calibración del catálogo'!$H$6:$H$8,MATCH(H5,'Calibración del catálogo'!$A$6:$A$8,0)) -> 0.012466403 | V5: X | W5: X | X5: X | Y5: X | Z5: X | AA5: Muestra por duplicado; los estándares van en la preparación del sistema.
A6: M02 | B6: HPLC | C6: Sustancias relacionadas | D6: Impurezas orgánicas y productos de degradación | E6: USP <621> y <1086> | F6: HPLC con detector UV/DAD y gradiente | G6: Sí | H6: media | I6: =INDEX('Calibración del catálogo'!$B$6:$B$8,MATCH(H6,'Calibración del catálogo'!$A$6:$A$8,0)) -> 3 | J6: =INDEX('Calibración del catálogo'!$C$6:$C$8,MATCH(H6,'Calibración del catálogo'!$A$6:$A$8,0)) -> 4 | K6: =INDEX('Calibración del catálogo'!$E$6:$E$8,MATCH(H6,'Calibración del catálogo'!$A$6:$A$8,0)) -> Intermedio o superior | L6: =IFERROR(INDEX('Calibración del catálogo'!$L$16:$L$21,MATCH(A6,'Calibración del catálogo'!$H$16:$H$21,0)),INDEX('Calibración del catálogo'!$M$16:$M$21,MATCH(A6,'Calibración del catálogo'!$J$16:$J$21,0))) -> 0.24310345 | M6: =IFERROR(L6*INDEX(Demanda!$B$5:$B$10,MATCH(B6,Demanda!$A$5:$A$10,0)),"revisar") -> 0.098943103 | N6: Triangular alrededor de la moda (S05 y S14) | O6: =IFERROR(P6*(1-'Calibración del catálogo'!$D$25),"revisar") -> 124.57359 | P6: ='Calibración del catálogo'!F25 -> 155.71699 | Q6: =IFERROR(P6*(1+'Calibración del catálogo'!$D$25),"revisar") -> 186.86039 | T6: =P6 -> 155.71699 | U6: =INDEX('Calibración del catálogo'!$H$6:$H$8,MATCH(H6,'Calibración del catálogo'!$A$6:$A$8,0)) -> 0.024932807 | V6: X | X6: X | Y6: X | Z6: X | AA6: Muestra por duplicado, muestra adicionada y estándar diluido.
A7: M03 | B7: GC | C7: Pureza de materias primas volátiles | D7: Pureza de solventes y otras materias primas volátiles | E7: USP <621> | F7: GC con inyección líquida y detector FID | G7: Sí | H7: baja | I7: =INDEX('Calibración del catálogo'!$B$6:$B$8,MATCH(H7,'Calibración del catálogo'!$A$6:$A$8,0)) -> 1 | J7: =INDEX('Calibración del catálogo'!$C$6:$C$8,MATCH(H7,'Calibración del catálogo'!$A$6:$A$8,0)) -> 2 | K7: =INDEX('Calibración del catálogo'!$E$6:$E$8,MATCH(H7,'Calibración del catálogo'!$A$6:$A$8,0)) -> Júnior o superior | L7: =IFERROR(INDEX('Calibración del catálogo'!$L$16:$L$21,MATCH(A7,'Calibración del catálogo'!$H$16:$H$21,0)),INDEX('Calibración del catálogo'!$M$16:$M$21,MATCH(A7,'Calibración del catálogo'!$J$16:$J$21,0))) -> 0.31 | M7: =IFERROR(L7*INDEX(Demanda!$B$5:$B$10,MATCH(B7,Demanda!$A$5:$A$10,0)),"revisar") -> 0.07967 | N7: Triangular alrededor de la moda (S05 y S14) | O7: =IFERROR(P7*(1-'Calibración del catálogo'!$D$26),"revisar") -> 36.877323 | P7: ='Calibración del catálogo'!E26 -> 46.096654 | Q7: =IFERROR(P7*(1+'Calibración del catálogo'!$D$26),"revisar") -> 55.315985 | T7: =P7 -> 46.096654 | U7: =INDEX('Calibración del catálogo'!$H$6:$H$8,MATCH(H7,'Calibración del catálogo'!$A$6:$A$8,0)) -> 0.012466403 | V7: X | AA7: Una o dos inyecciones directas del líquido.
A8: M04 | B8: GC | C8: Solventes residuales | D8: Solventes orgánicos que quedan del proceso de fabricación | E8: USP <467> | F8: GC con muestreador de espacio de cabeza y detector FID | G8: Sí | H8: media | I8: =INDEX('Calibración del catálogo'!$B$6:$B$8,MATCH(H8,'Calibración del catálogo'!$A$6:$A$8,0)) -> 3 | J8: =INDEX('Calibración del catálogo'!$C$6:$C$8,MATCH(H8,'Calibración del catálogo'!$A$6:$A$8,0)) -> 4 | K8: =INDEX('Calibración del catálogo'!$E$6:$E$8,MATCH(H8,'Calibración del catálogo'!$A$6:$A$8,0)) -> Intermedio o superior | L8: =IFERROR(INDEX('Calibración del catálogo'!$L$16:$L$21,MATCH(A8,'Calibración del catálogo'!$H$16:$H$21,0)),INDEX('Calibración del catálogo'!$M$16:$M$21,MATCH(A8,'Calibración del catálogo'!$J$16:$J$21,0))) -> 0.69 | M8: =IFERROR(L8*INDEX(Demanda!$B$5:$B$10,MATCH(B8,Demanda!$A$5:$A$10,0)),"revisar") -> 0.17733 | N8: Triangular alrededor de la moda (S05 y S14) | O8: =IFERROR(P8*(1-'Calibración del catálogo'!$D$26),"revisar") -> 55.315985 | P8: ='Calibración del catálogo'!F26 -> 69.144981 | Q8: =IFERROR(P8*(1+'Calibración del catálogo'!$D$26),"revisar") -> 82.973978 | T8: =P8 -> 69.144981 | U8: =INDEX('Calibración del catálogo'!$H$6:$H$8,MATCH(H8,'Calibración del catálogo'!$A$6:$A$8,0)) -> 0.024932807 | V8: X | W8: X | X8: X | Y8: X | AA8: Viales de muestra por duplicado y muestra adicionada.
A9: M05 | B9: PSA | C9: Tamaño de partícula, vía seca | D9: Distribución de tamaño por difracción láser, con la muestra dispersa en aire | E9: USP <429> | F9: Analizador de difracción láser con módulo seco | G9: No | H9: baja | I9: =INDEX('Calibración del catálogo'!$B$6:$B$8,MATCH(H9,'Calibración del catálogo'!$A$6:$A$8,0)) -> 1 | J9: =INDEX('Calibración del catálogo'!$C$6:$C$8,MATCH(H9,'Calibración del catálogo'!$A$6:$A$8,0)) -> 2 | K9: =INDEX('Calibración del catálogo'!$E$6:$E$8,MATCH(H9,'Calibración del catálogo'!$A$6:$A$8,0)) -> Júnior o superior | L9: =IFERROR(INDEX('Calibración del catálogo'!$L$16:$L$21,MATCH(A9,'Calibración del catálogo'!$H$16:$H$21,0)),INDEX('Calibración del catálogo'!$M$16:$M$21,MATCH(A9,'Calibración del catálogo'!$J$16:$J$21,0))) -> 0.3619403 | M9: =IFERROR(L9*INDEX(Demanda!$B$5:$B$10,MATCH(B9,Demanda!$A$5:$A$10,0)),"revisar") -> 0.068044776 | N9: Tramo inferior de la distribución de la Tabla 3 (S15) | O9: ='Calibración del catálogo'!C30 -> 5 | Q9: ='Calibración del catálogo'!G30 -> 12.138593 | R9: 0 | S9: ='Calibración del catálogo'!F30 -> 0.3619403 | T9: ='Calibración del catálogo'!H30 -> 9.5484574 | U9: =INDEX('Calibración del catálogo'!$H$6:$H$8,MATCH(H9,'Calibración del catálogo'!$A$6:$A$8,0)) -> 0.012466403 | V9: X | W9: X | X9: X | AA9: Una o dos alícuotas en seco.
A10: M06 | B10: PSA | C10: Tamaño de partícula, vía húmeda | D10: La misma distribución, con la muestra dispersa en un líquido | E10: USP <429> | F10: Analizador de difracción láser con módulo húmedo | G10: No | H10: media | I10: =INDEX('Calibración del catálogo'!$B$6:$B$8,MATCH(H10,'Calibración del catálogo'!$A$6:$A$8,0)) -> 3 | J10: =INDEX('Calibración del catálogo'!$C$6:$C$8,MATCH(H10,'Calibración del catálogo'!$A$6:$A$8,0)) -> 4 | K10: =INDEX('Calibración del catálogo'!$E$6:$E$8,MATCH(H10,'Calibración del catálogo'!$A$6:$A$8,0)) -> Intermedio o superior | L10: =IFERROR(INDEX('Calibración del catálogo'!$L$16:$L$21,MATCH(A10,'Calibración del catálogo'!$H$16:$H$21,0)),INDEX('Calibración del catálogo'!$M$16:$M$21,MATCH(A10,'Calibración del catálogo'!$J$16:$J$21,0))) -> 0.6380597 | M10: =IFERROR(L10*INDEX(Demanda!$B$5:$B$10,MATCH(B10,Demanda!$A$5:$A$10,0)),"revisar") -> 0.11995522 | N10: Tramo superior de la distribución de la Tabla 3 (S15) | O10: ='Calibración del catálogo'!G30 -> 12.138593 | Q10: ='Calibración del catálogo'!E30 -> 30 | R10: ='Calibración del catálogo'!F30 -> 0.3619403 | S10: 1 | T10: ='Calibración del catálogo'!I30 -> 18.092396 | U10: =INDEX('Calibración del catálogo'!$H$6:$H$8,MATCH(H10,'Calibración del catálogo'!$A$6:$A$8,0)) -> 0.024932807 | V10: X | X10: X | Y10: X | Z10: X | AA10: Dispersante, suspensión de la muestra y réplicas de medición.
A11: M07 | B11: KF | C11: Agua por KF volumétrico | D11: Contenido de agua por titulación directa | E11: USP <921>, método Ia | F11: Titulador Karl Fischer volumétrico | G11: No | H11: media | I11: =INDEX('Calibración del catálogo'!$B$6:$B$8,MATCH(H11,'Calibración del catálogo'!$A$6:$A$8,0)) -> 3 | J11: =INDEX('Calibración del catálogo'!$C$6:$C$8,MATCH(H11,'Calibración del catálogo'!$A$6:$A$8,0)) -> 4 | K11: =INDEX('Calibración del catálogo'!$E$6:$E$8,MATCH(H11,'Calibración del catálogo'!$A$6:$A$8,0)) -> Intermedio o superior | L11: =IFERROR(INDEX('Calibración del catálogo'!$L$16:$L$21,MATCH(A11,'Calibración del catálogo'!$H$16:$H$21,0)),INDEX('Calibración del catálogo'!$M$16:$M$21,MATCH(A11,'Calibración del catálogo'!$J$16:$J$21,0))) -> 0.640625 | M11: =IFERROR(L11*INDEX(Demanda!$B$5:$B$10,MATCH(B11,Demanda!$A$5:$A$10,0)),"revisar") -> 0.045484375 | N11: Tramo inferior de la distribución de la Tabla 3 (S15) | O11: ='Calibración del catálogo'!C31 -> 2 | Q11: ='Calibración del catálogo'!G31 -> 24.540204 | R11: 0 | S11: ='Calibración del catálogo'!F31 -> 0.640625 | T11: ='Calibración del catálogo'!H31 -> 13.131306 | U11: =INDEX('Calibración del catálogo'!$H$6:$H$8,MATCH(H11,'Calibración del catálogo'!$A$6:$A$8,0)) -> 0.024932807 | V11: X | W11: X | X11: X | Y11: X | Z11: X | AA11: Verificación del título y muestra por triplicado.
A12: M08 | B12: KF | C12: Agua por KF coulométrico con horno | D12: Agua en cantidades bajas, liberada en un horno y titulada por coulometría | E12: USP <921>, método Ic | F12: Titulador Karl Fischer coulométrico con horno | G12: No | H12: alta | I12: =INDEX('Calibración del catálogo'!$B$6:$B$8,MATCH(H12,'Calibración del catálogo'!$A$6:$A$8,0)) -> 5 | J12: =INDEX('Calibración del catálogo'!$C$6:$C$8,MATCH(H12,'Calibración del catálogo'!$A$6:$A$8,0)) -> 6 | K12: =INDEX('Calibración del catálogo'!$E$6:$E$8,MATCH(H12,'Calibración del catálogo'!$A$6:$A$8,0)) -> Solo sénior | L12: =IFERROR(INDEX('Calibración del catálogo'!$L$16:$L$21,MATCH(A12,'Calibración del catálogo'!$H$16:$H$21,0)),INDEX('Calibración del catálogo'!$M$16:$M$21,MATCH(A12,'Calibración del catálogo'!$J$16:$J$21,0))) -> 0.359375 | M12: =IFERROR(L12*INDEX(Demanda!$B$5:$B$10,MATCH(B12,Demanda!$A$5:$A$10,0)),"revisar") -> 0.025515625 | N12: Tramo superior de la distribución de la Tabla 3 (S15) | O12: ='Calibración del catálogo'!G31 -> 24.540204 | Q12: ='Calibración del catálogo'!E31 -> 56 | R12: ='Calibración del catálogo'!F31 -> 0.640625 | S12: 1 | T12: ='Calibración del catálogo'!I31 -> 35.026803 | U12: =INDEX('Calibración del catálogo'!$H$6:$H$8,MATCH(H12,'Calibración del catálogo'!$A$6:$A$8,0)) -> 0.049865613 | V12: X | Y12: X | Z12: X | AA12: Viales blanco, estándar de agua y muestra por triplicado.
A13: M09 | B13: DSC | C13: Punto de fusión | D13: Temperatura de fusión, para identificar el material | E13: USP <891> | F13: Calorímetro diferencial de barrido | G13: No | H13: baja | I13: =INDEX('Calibración del catálogo'!$B$6:$B$8,MATCH(H13,'Calibración del catálogo'!$A$6:$A$8,0)) -> 1 | J13: =INDEX('Calibración del catálogo'!$C$6:$C$8,MATCH(H13,'Calibración del catálogo'!$A$6:$A$8,0)) -> 2 | K13: =INDEX('Calibración del catálogo'!$E$6:$E$8,MATCH(H13,'Calibración del catálogo'!$A$6:$A$8,0)) -> Júnior o superior | L13: =IFERROR(INDEX('Calibración del catálogo'!$L$16:$L$21,MATCH(A13,'Calibración del catálogo'!$H$16:$H$21,0)),INDEX('Calibración del catálogo'!$M$16:$M$21,MATCH(A13,'Calibración del catálogo'!$J$16:$J$21,0))) -> 0.18333333 | M13: =IFERROR(L13*INDEX(Demanda!$B$5:$B$10,MATCH(B13,Demanda!$A$5:$A$10,0)),"revisar") -> 0.0073333333 | N13: Tramo inferior de la distribución de la Tabla 3 (S15) | O13: ='Calibración del catálogo'!C32 -> 12 | Q13: ='Calibración del catálogo'!G32 -> 42.8 | R13: 0 | S13: ='Calibración del catálogo'!F32 -> 0.18333333 | T13: ='Calibración del catálogo'!H32 -> 27.4 | U13: =INDEX('Calibración del catálogo'!$H$6:$H$8,MATCH(H13,'Calibración del catálogo'!$A$6:$A$8,0)) -> 0.012466403 | V13: X | W13: X | AA13: Una o dos cápsulas de muestra.
A14: M10 | B14: DSC | C14: Forma polimórfica y pureza | D14: Forma cristalina y pureza a partir del pico de fusión | E14: USP <891> | F14: Calorímetro diferencial de barrido | G14: No | H14: media | I14: =INDEX('Calibración del catálogo'!$B$6:$B$8,MATCH(H14,'Calibración del catálogo'!$A$6:$A$8,0)) -> 3 | J14: =INDEX('Calibración del catálogo'!$C$6:$C$8,MATCH(H14,'Calibración del catálogo'!$A$6:$A$8,0)) -> 4 | K14: =INDEX('Calibración del catálogo'!$E$6:$E$8,MATCH(H14,'Calibración del catálogo'!$A$6:$A$8,0)) -> Intermedio o superior | L14: =IFERROR(INDEX('Calibración del catálogo'!$L$16:$L$21,MATCH(A14,'Calibración del catálogo'!$H$16:$H$21,0)),INDEX('Calibración del catálogo'!$M$16:$M$21,MATCH(A14,'Calibración del catálogo'!$J$16:$J$21,0))) -> 0.81666667 | M14: =IFERROR(L14*INDEX(Demanda!$B$5:$B$10,MATCH(B14,Demanda!$A$5:$A$10,0)),"revisar") -> 0.032666667 | N14: Tramo superior de la distribución de la Tabla 3 (S15) | O14: ='Calibración del catálogo'!G32 -> 42.8 | Q14: ='Calibración del catálogo'!E32 -> 180 | R14: ='Calibración del catálogo'!F32 -> 0.18333333 | S14: 1 | T14: ='Calibración del catálogo'!I32 -> 111.4 | U14: =INDEX('Calibración del catálogo'!$H$6:$H$8,MATCH(H14,'Calibración del catálogo'!$A$6:$A$8,0)) -> 0.024932807 | V14: X | X14: X | Y14: X | Z14: X | AA14: Verificación con indio y muestra por duplicado o triplicado.
A15: M11 | B15: XRPD | C15: Identificación de la forma cristalina | D15: Patrón de difracción para confirmar la forma cristalina | E15: USP <941> | F15: Difractómetro de rayos X de polvo | G15: No | H15: media | I15: =INDEX('Calibración del catálogo'!$B$6:$B$8,MATCH(H15,'Calibración del catálogo'!$A$6:$A$8,0)) -> 3 | J15: =INDEX('Calibración del catálogo'!$C$6:$C$8,MATCH(H15,'Calibración del catálogo'!$A$6:$A$8,0)) -> 4 | K15: =INDEX('Calibración del catálogo'!$E$6:$E$8,MATCH(H15,'Calibración del catálogo'!$A$6:$A$8,0)) -> Intermedio o superior | L15: =IFERROR(INDEX('Calibración del catálogo'!$L$16:$L$21,MATCH(A15,'Calibración del catálogo'!$H$16:$H$21,0)),INDEX('Calibración del catálogo'!$M$16:$M$21,MATCH(A15,'Calibración del catálogo'!$J$16:$J$21,0))) -> 0.77857143 | M15: =IFERROR(L15*INDEX(Demanda!$B$5:$B$10,MATCH(B15,Demanda!$A$5:$A$10,0)),"revisar") -> 0.028807143 | N15: Tramo inferior de la distribución de la Tabla 3 (S15) | O15: ='Calibración del catálogo'!C33 -> 11 | Q15: ='Calibración del catálogo'!G33 -> 116.00837 | R15: 0 | S15: ='Calibración del catálogo'!F33 -> 0.77857143 | T15: ='Calibración del catálogo'!H33 -> 61.084039 | U15: =INDEX('Calibración del catálogo'!$H$6:$H$8,MATCH(H15,'Calibración del catálogo'!$A$6:$A$8,0)) -> 0.024932807 | V15: X | W15: X | Y15: X | AA15: Estándar de la forma y muestra por duplicado.
A16: M12 | B16: XRPD | C16: Cuantificación de fases | D16: Porcentaje de una forma no deseada o de material amorfo, con curva de calibración | E16: USP <941> | F16: Difractómetro de rayos X de polvo | G16: No | H16: alta | I16: =INDEX('Calibración del catálogo'!$B$6:$B$8,MATCH(H16,'Calibración del catálogo'!$A$6:$A$8,0)) -> 5 | J16: =INDEX('Calibración del catálogo'!$C$6:$C$8,MATCH(H16,'Calibración del catálogo'!$A$6:$A$8,0)) -> 6 | K16: =INDEX('Calibración del catálogo'!$E$6:$E$8,MATCH(H16,'Calibración del catálogo'!$A$6:$A$8,0)) -> Solo sénior | L16: =IFERROR(INDEX('Calibración del catálogo'!$L$16:$L$21,MATCH(A16,'Calibración del catálogo'!$H$16:$H$21,0)),INDEX('Calibración del catálogo'!$M$16:$M$21,MATCH(A16,'Calibración del catálogo'!$J$16:$J$21,0))) -> 0.22142857 | M16: =IFERROR(L16*INDEX(Demanda!$B$5:$B$10,MATCH(B16,Demanda!$A$5:$A$10,0)),"revisar") -> 0.0081928571 | N16: Tramo superior de la distribución de la Tabla 3 (S15) | O16: ='Calibración del catálogo'!G33 -> 116.00837 | Q16: ='Calibración del catálogo'!E33 -> 203 | R16: ='Calibración del catálogo'!F33 -> 0.77857143 | S16: 1 | T16: ='Calibración del catálogo'!I33 -> 145.00558 | U16: =INDEX('Calibración del catálogo'!$H$6:$H$8,MATCH(H16,'Calibración del catálogo'!$A$6:$A$8,0)) -> 0.049865613 | X16: X | Y16: X | Z16: X | AA16: Mezclas de calibración y muestras.

Sheet Calibración del catálogo
A1: Calibración del catálogo con las fuentes
A2: Cómo se calculan las columnas de la hoja Catálogo. Azul = dato de la fuente · negro = fórmula · amarillo = supuesto que pueden cambiar.
A4: A. Regla de complejidad (supuestos S11, S12 y S13)
A5: Nivel | B5: Soluciones mín | C5: Soluciones máx | D5: Media de soluciones | E5: Calificación mínima | F5: Multiplicador de reanálisis | G5: Participación en la demanda | H5: Prob. de reanálisis
A6: baja | B6: 1 | C6: 2 | D6: =(B6+C6)/2 -> 1.5 | E6: Júnior o superior | F6: 0.5 | G6: =SUMIFS(Catálogo!$M$5:$M$16,Catálogo!$H$5:$H$16,A6) -> 0.46310501 | H6: =IFERROR($B$11*F6/$B$12,"") -> 0.012466403
A7: media | B7: 3 | C7: 4 | D7: =(B7+C7)/2 -> 3.5 | E7: Intermedio o superior | F7: 1 | G7: =SUMIFS(Catálogo!$M$5:$M$16,Catálogo!$H$5:$H$16,A7) -> 0.50318651 | H7: =IFERROR($B$11*F7/$B$12,"") -> 0.024932807
A8: alta | B8: 5 | C8: 6 | D8: =(B8+C8)/2 -> 5.5 | E8: Solo sénior | F8: 2 | G8: =SUMIFS(Catálogo!$M$5:$M$16,Catálogo!$H$5:$H$16,A8) -> 0.033708482 | H8: =IFERROR($B$11*F8/$B$12,"") -> 0.049865613
A9: Total / promedio ponderado | G9: =SUM(G6:G8) -> 1 | H9: =SUMPRODUCT(G6:G8,H6:H8) -> 0.02
A11: Tasa base de reanálisis (S01) | B11: =Supuestos!$D$5 -> 0.02 | C11: Viene de la hoja Supuestos (S01); se cambia allá.
A12: Factor de normalización | B12: =SUMPRODUCT(F6:F8,G6:G8) -> 0.80215598 | C12: Promedio de los multiplicadores ponderado por la demanda. Con él, el promedio ponderado de la columna H (celda H9) queda igual a S01.
A14: B. Participación de cada método: soluciones promedio implícitas en Costigliola et al. (2017, Tabla 3, p. 9016, y Tabla 6, p. 9019)
A15: Técnica | B15: Prep. del análisis, Tabla 6 (min) | C15: Prep. por solución, Tabla 3: mín | D15: moda | E15: máx | F15: Media triangular por solución (min) | G15: Soluciones promedio implícitas | H15: Método simple | I15: Media de soluciones (simple) | J15: Método exigente | K15: Media de soluciones (exigente) | L15: Participación del simple | M15: Participación del exigente | N15: Prep. reproducida (min) | O15: Diferencia con Tabla 6 | P15: Prep. con BetaPERT estándar (min) | Q15: Diferencia con Tabla 6 | R15: Chequeo
A16: HPLC | B16: 96 | C16: =Duraciones!D5 -> 5 | D16: =Duraciones!E5 -> 40 | E16: =Duraciones!F5 -> 100 | F16: =(C16+D16+E16)/3 -> 48.333333 | G16: =B16/F16 -> 1.9862069 | H16: M01 | I16: =INDEX($D$6:$D$8,MATCH(INDEX(Catálogo!$H$5:$H$16,MATCH(H16,Catálogo!$A$5:$A$16,0)),$A$6:$A$8,0)) -> 1.5 | J16: M02 | K16: =INDEX($D$6:$D$8,MATCH(INDEX(Catálogo!$H$5:$H$16,MATCH(J16,Catálogo!$A$5:$A$16,0)),$A$6:$A$8,0)) -> 3.5 | L16: =IFERROR((K16-G16)/(K16-I16),"revisar") -> 0.75689655 | M16: =IFERROR(1-L16,"revisar") -> 0.24310345 | N16: =IFERROR((L16*I16+M16*K16)*F16,"") -> 96 | O16: =IFERROR(N16/B16-1,"") -> 0 | P16: =G16*(C16+4*D16+E16)/6 -> 87.724138 | Q16: =P16/B16-1 -> -0.086206897 | R16: =IF(ISNUMBER(L16),IF(AND(L16>=0,L16<=1),"OK","Revisar: el promedio no queda entre los dos métodos"),"Revisar: los dos métodos tienen la misma complejidad") -> OK
A17: GC | B17: 48 | C17: =Duraciones!D9 -> 5 | D17: =Duraciones!E9 -> 10 | E17: =Duraciones!F9 -> 35 | F17: =(C17+D17+E17)/3 -> 16.666667 | G17: =B17/F17 -> 2.88 | H17: M03 | I17: =INDEX($D$6:$D$8,MATCH(INDEX(Catálogo!$H$5:$H$16,MATCH(H17,Catálogo!$A$5:$A$16,0)),$A$6:$A$8,0)) -> 1.5 | J17: M04 | K17: =INDEX($D$6:$D$8,MATCH(INDEX(Catálogo!$H$5:$H$16,MATCH(J17,Catálogo!$A$5:$A$16,0)),$A$6:$A$8,0)) -> 3.5 | L17: =IFERROR((K17-G17)/(K17-I17),"revisar") -> 0.31 | M17: =IFERROR(1-L17,"revisar") -> 0.69 | N17: =IFERROR((L17*I17+M17*K17)*F17,"") -> 48 | O17: =IFERROR(N17/B17-1,"") -> 0 | P17: =G17*(C17+4*D17+E17)/6 -> 38.4 | Q17: =P17/B17-1 -> -0.2 | R17: =IF(ISNUMBER(L17),IF(AND(L17>=0,L17<=1),"OK","Revisar: el promedio no queda entre los dos métodos"),"Revisar: los dos métodos tienen la misma complejidad") -> OK
A18: PSA | B18: 31 | C18: =Duraciones!D13 -> 5 | D18: =Duraciones!E13 -> 7.5 | E18: =Duraciones!F13 -> 21 | F18: =(C18+D18+E18)/3 -> 11.166667 | G18: =B18/F18 -> 2.7761194 | H18: M05 | I18: =INDEX($D$6:$D$8,MATCH(INDEX(Catálogo!$H$5:$H$16,MATCH(H18,Catálogo!$A$5:$A$16,0)),$A$6:$A$8,0)) -> 1.5 | J18: M06 | K18: =INDEX($D$6:$D$8,MATCH(INDEX(Catálogo!$H$5:$H$16,MATCH(J18,Catálogo!$A$5:$A$16,0)),$A$6:$A$8,0)) -> 3.5 | L18: =IFERROR((K18-G18)/(K18-I18),"revisar") -> 0.3619403 | M18: =IFERROR(1-L18,"revisar") -> 0.6380597 | N18: =IFERROR((L18*I18+M18*K18)*F18,"") -> 31 | O18: =IFERROR(N18/B18-1,"") -> 0 | P18: =G18*(C18+4*D18+E18)/6 -> 25.910448 | Q18: =P18/B18-1 -> -0.1641791 | R18: =IF(ISNUMBER(L18),IF(AND(L18>=0,L18<=1),"OK","Revisar: el promedio no queda entre los dos métodos"),"Revisar: los dos métodos tienen la misma complejidad") -> OK
A19: KF | B19: 45 | C19: =Duraciones!D17 -> 1 | D19: =Duraciones!E17 -> 6 | E19: =Duraciones!F17 -> 25 | F19: =(C19+D19+E19)/3 -> 10.666667 | G19: =B19/F19 -> 4.21875 | H19: M07 | I19: =INDEX($D$6:$D$8,MATCH(INDEX(Catálogo!$H$5:$H$16,MATCH(H19,Catálogo!$A$5:$A$16,0)),$A$6:$A$8,0)) -> 3.5 | J19: M08 | K19: =INDEX($D$6:$D$8,MATCH(INDEX(Catálogo!$H$5:$H$16,MATCH(J19,Catálogo!$A$5:$A$16,0)),$A$6:$A$8,0)) -> 5.5 | L19: =IFERROR((K19-G19)/(K19-I19),"revisar") -> 0.640625 | M19: =IFERROR(1-L19,"revisar") -> 0.359375 | N19: =IFERROR((L19*I19+M19*K19)*F19,"") -> 45 | O19: =IFERROR(N19/B19-1,"") -> 0 | P19: =G19*(C19+4*D19+E19)/6 -> 35.15625 | Q19: =P19/B19-1 -> -0.21875 | R19: =IF(ISNUMBER(L19),IF(AND(L19>=0,L19<=1),"OK","Revisar: el promedio no queda entre los dos métodos"),"Revisar: los dos métodos tienen la misma complejidad") -> OK
A20: DSC | B20: 47 | C20: =Duraciones!D21 -> 5 | D20: =Duraciones!E21 -> 10 | E20: =Duraciones!F21 -> 30 | F20: =(C20+D20+E20)/3 -> 15 | G20: =B20/F20 -> 3.1333333 | H20: M09 | I20: =INDEX($D$6:$D$8,MATCH(INDEX(Catálogo!$H$5:$H$16,MATCH(H20,Catálogo!$A$5:$A$16,0)),$A$6:$A$8,0)) -> 1.5 | J20: M10 | K20: =INDEX($D$6:$D$8,MATCH(INDEX(Catálogo!$H$5:$H$16,MATCH(J20,Catálogo!$A$5:$A$16,0)),$A$6:$A$8,0)) -> 3.5 | L20: =IFERROR((K20-G20)/(K20-I20),"revisar") -> 0.18333333 | M20: =IFERROR(1-L20,"revisar") -> 0.81666667 | N20: =IFERROR((L20*I20+M20*K20)*F20,"") -> 47 | O20: =IFERROR(N20/B20-1,"") -> 0 | P20: =G20*(C20+4*D20+E20)/6 -> 39.166667 | Q20: =P20/B20-1 -> -0.16666667 | R20: =IF(ISNUMBER(L20),IF(AND(L20>=0,L20<=1),"OK","Revisar: el promedio no queda entre los dos métodos"),"Revisar: los dos métodos tienen la misma complejidad") -> OK
A21: XRPD | B21: 46 | C21: =Duraciones!D25 -> 5 | D21: =Duraciones!E25 -> 10 | E21: =Duraciones!F25 -> 20 | F21: =(C21+D21+E21)/3 -> 11.666667 | G21: =B21/F21 -> 3.9428571 | H21: M11 | I21: =INDEX($D$6:$D$8,MATCH(INDEX(Catálogo!$H$5:$H$16,MATCH(H21,Catálogo!$A$5:$A$16,0)),$A$6:$A$8,0)) -> 3.5 | J21: M12 | K21: =INDEX($D$6:$D$8,MATCH(INDEX(Catálogo!$H$5:$H$16,MATCH(J21,Catálogo!$A$5:$A$16,0)),$A$6:$A$8,0)) -> 5.5 | L21: =IFERROR((K21-G21)/(K21-I21),"revisar") -> 0.77857143 | M21: =IFERROR(1-L21,"revisar") -> 0.22142857 | N21: =IFERROR((L21*I21+M21*K21)*F21,"") -> 46 | O21: =IFERROR(N21/B21-1,"") -> 0 | P21: =G21*(C21+4*D21+E21)/6 -> 42.714286 | Q21: =P21/B21-1 -> -0.071428571 | R21: =IF(ISNUMBER(L21),IF(AND(L21>=0,L21<=1),"OK","Revisar: el promedio no queda entre los dos métodos"),"Revisar: los dos métodos tienen la misma complejidad") -> OK
A22: Soluciones promedio implícitas = prep. del análisis (Tabla 6) ÷ media triangular de la prep. por solución (Tabla 3), porque la fuente multiplica una por la otra (p. 9019). La participación del simple sale de igualar el promedio ponderado de los dos métodos a ese valor.
A23: C. Corrida de HPLC y GC: fija por método en la fuente y no publicada; se reparte el promedio de la Tabla 6 (supuestos S05 y S14)
A24: Técnica | B24: Corrida promedio, Tabla 6 (min) | C24: Relación exigente / simple | D24: Margen ± (S05) | E24: Moda del simple (min) | F24: Moda del exigente (min) | G24: Promedio ponderado (min) | H24: Diferencia con Tabla 6
A25: HPLC | B25: 85 | C25: 2.5 | D25: 0.2 | E25: =IFERROR(B25/(L16+M16*C25),"revisar") -> 62.286797 | F25: =IFERROR(C25*E25,"revisar") -> 155.71699 | G25: =IFERROR(L16*E25+M16*F25,"revisar") -> 85 | H25: =IFERROR(G25/B25-1,"revisar") -> 0
A26: GC | B26: 62 | C26: 1.5 | D26: =D25 -> 0.2 | E26: =IFERROR(B26/(L17+M17*C26),"revisar") -> 46.096654 | F26: =IFERROR(C26*E26,"revisar") -> 69.144981 | G26: =IFERROR(L17*E26+M17*F26,"revisar") -> 62 | H26: =IFERROR(G26/B26-1,"revisar") -> 0
A28: D. Corrida de PSA, KF, DSC y XRPD: la distribución de la Tabla 3 se reparte en dos tramos según la participación de cada método (supuesto S15)
A29: Técnica | B29: Distribución (Tabla 3) | C29: mín | D29: moda | E29: máx | F29: Participación del simple (cuantil de corte) | G29: Corte (min) | H29: Media del tramo simple (min) | I29: Media del tramo exigente (min) | J29: Promedio ponderado (min) | K29: Media de la distribución (min) | L29: Diferencia | M29: Auxiliar: G(moda) | N29: Auxiliar: G(corte) | O29: Auxiliar: G(máx)
A30: PSA | B30: T | C30: =Duraciones!D15 -> 5 | D30: =Duraciones!E15 -> 10 | E30: =Duraciones!F15 -> 30 | F30: =L18 -> 0.3619403 | G30: =IFERROR(IF(B30="U",C30+F30*(E30-C30),IF(F30<=(D30-C30)/(E30-C30),C30+SQRT(F30*(E30-C30)*(D30-C30)),E30-SQRT((1-F30)*(E30-C30)*(E30-D30)))),"revisar") -> 12.138593 | H30: =IFERROR(IF(B30="U",(C30+G30)/2,N30/F30),"revisar") -> 9.5484574 | I30: =IFERROR(IF(B30="U",(G30+E30)/2,(O30-N30)/(1-F30)),"revisar") -> 18.092396 | J30: =IFERROR(F30*H30+(1-F30)*I30,"revisar") -> 15 | K30: =IFERROR(IF(B30="U",(C30+E30)/2,(C30+D30+E30)/3),"revisar") -> 15 | L30: =IFERROR(J30/K30-1,"revisar") -> 0 | M30: =IFERROR(IF(B30="U","",2/((E30-C30)*(D30-C30))*(D30^3/3-C30*D30^2/2+C30^3/6)),"revisar") -> 1.6666667 | N30: =IFERROR(IF(B30="U","",IF(G30<=D30,2/((E30-C30)*(D30-C30))*(G30^3/3-C30*G30^2/2+C30^3/6),M30+2/((E30-C30)*(E30-D30))*(E30*G30^2/2-G30^3/3-E30*D30^2/2+D30^3/3))),"revisar") -> 3.4559715 | O30: =IFERROR(IF(B30="U","",M30+2/((E30-C30)*(E30-D30))*(E30^3/2-E30^3/3-E30*D30^2/2+D30^3/3)),"revisar") -> 15
A31: KF | B31: T | C31: =Duraciones!D19 -> 2 | D31: =Duraciones!E19 -> 5 | E31: =Duraciones!F19 -> 56 | F31: =L19 -> 0.640625 | G31: =IFERROR(IF(B31="U",C31+F31*(E31-C31),IF(F31<=(D31-C31)/(E31-C31),C31+SQRT(F31*(E31-C31)*(D31-C31)),E31-SQRT((1-F31)*(E31-C31)*(E31-D31)))),"revisar") -> 24.540204 | H31: =IFERROR(IF(B31="U",(C31+G31)/2,N31/F31),"revisar") -> 13.131306 | I31: =IFERROR(IF(B31="U",(G31+E31)/2,(O31-N31)/(1-F31)),"revisar") -> 35.026803 | J31: =IFERROR(F31*H31+(1-F31)*I31,"revisar") -> 21 | K31: =IFERROR(IF(B31="U",(C31+E31)/2,(C31+D31+E31)/3),"revisar") -> 21 | L31: =IFERROR(J31/K31-1,"revisar") -> 0 | M31: =IFERROR(IF(B31="U","",2/((E31-C31)*(D31-C31))*(D31^3/3-C31*D31^2/2+C31^3/6)),"revisar") -> 0.22222222 | N31: =IFERROR(IF(B31="U","",IF(G31<=D31,2/((E31-C31)*(D31-C31))*(G31^3/3-C31*G31^2/2+C31^3/6),M31+2/((E31-C31)*(E31-D31))*(E31*G31^2/2-G31^3/3-E31*D31^2/2+D31^3/3))),"revisar") -> 8.4122427 | O31: =IFERROR(IF(B31="U","",M31+2/((E31-C31)*(E31-D31))*(E31^3/2-E31^3/3-E31*D31^2/2+D31^3/3)),"revisar") -> 21
A32: DSC | B32: U | C32: =Duraciones!D23 -> 12 | D32: =Duraciones!E23 -> 96 | E32: =Duraciones!F23 -> 180 | F32: =L20 -> 0.18333333 | G32: =IFERROR(IF(B32="U",C32+F32*(E32-C32),IF(F32<=(D32-C32)/(E32-C32),C32+SQRT(F32*(E32-C32)*(D32-C32)),E32-SQRT((1-F32)*(E32-C32)*(E32-D32)))),"revisar") -> 42.8 | H32: =IFERROR(IF(B32="U",(C32+G32)/2,N32/F32),"revisar") -> 27.4 | I32: =IFERROR(IF(B32="U",(G32+E32)/2,(O32-N32)/(1-F32)),"revisar") -> 111.4 | J32: =IFERROR(F32*H32+(1-F32)*I32,"revisar") -> 96 | K32: =IFERROR(IF(B32="U",(C32+E32)/2,(C32+D32+E32)/3),"revisar") -> 96 | L32: =IFERROR(J32/K32-1,"revisar") -> 0 | M32: =IFERROR(IF(B32="U","",2/((E32-C32)*(D32-C32))*(D32^3/3-C32*D32^2/2+C32^3/6)),"revisar") | N32: =IFERROR(IF(B32="U","",IF(G32<=D32,2/((E32-C32)*(D32-C32))*(G32^3/3-C32*G32^2/2+C32^3/6),M32+2/((E32-C32)*(E32-D32))*(E32*G32^2/2-G32^3/3-E32*D32^2/2+D32^3/3))),"revisar") | O32: =IFERROR(IF(B32="U","",M32+2/((E32-C32)*(E32-D32))*(E32^3/2-E32^3/3-E32*D32^2/2+D32^3/3)),"revisar")
A33: XRPD | B33: T | C33: =Duraciones!D27 -> 11 | D33: =Duraciones!E27 -> 25 | E33: =Duraciones!F27 -> 203 | F33: =L21 -> 0.77857143 | G33: =IFERROR(IF(B33="U",C33+F33*(E33-C33),IF(F33<=(D33-C33)/(E33-C33),C33+SQRT(F33*(E33-C33)*(D33-C33)),E33-SQRT((1-F33)*(E33-C33)*(E33-D33)))),"revisar") -> 116.00837 | H33: =IFERROR(IF(B33="U",(C33+G33)/2,N33/F33),"revisar") -> 61.084039 | I33: =IFERROR(IF(B33="U",(G33+E33)/2,(O33-N33)/(1-F33)),"revisar") -> 145.00558 | J33: =IFERROR(F33*H33+(1-F33)*I33,"revisar") -> 79.666667 | K33: =IFERROR(IF(B33="U",(C33+E33)/2,(C33+D33+E33)/3),"revisar") -> 79.666667 | L33: =IFERROR(J33/K33-1,"revisar") -> 0 | M33: =IFERROR(IF(B33="U","",2/((E33-C33)*(D33-C33))*(D33^3/3-C33*D33^2/2+C33^3/6)),"revisar") -> 1.4826389 | N33: =IFERROR(IF(B33="U","",IF(G33<=D33,2/((E33-C33)*(D33-C33))*(G33^3/3-C33*G33^2/2+C33^3/6),M33+2/((E33-C33)*(E33-D33))*(E33*G33^2/2-G33^3/3-E33*D33^2/2+D33^3/3))),"revisar") -> 47.558288 | O33: =IFERROR(IF(B33="U","",M33+2/((E33-C33)*(E33-D33))*(E33^3/2-E33^3/3-E33*D33^2/2+D33^3/3)),"revisar") -> 79.666667
A35: G(x) es el momento parcial de la triangular entre el mínimo y x (integral de t·f(t)); la media de cada tramo es la diferencia de G entre sus extremos dividida por la probabilidad del tramo. En la uniforme (DSC) la media del tramo es su punto medio.
A36: Los cortes en minutos usan la distribución de la fuente (triangular o uniforme). Si el generador usa BetaPERT, se aplica el mismo cuantil sobre la BetaPERT.
A37: «Prep. con BetaPERT estándar» (bloque B) muestra cuánto bajaría la preparación promedio si el generador usa BetaPERT con λ = 4 en lugar de la triangular de la fuente (Léeme, Ojo 4).

Sheet Tipos de muestra
A1: Tipos de muestra del laboratorio de referencia
A2: Una fila por tipo. Amarillo = decisión (proporción, llegadas, plazos y urgentes); la probabilidad de cada método dentro del tipo (columnas M01 a M12) se calcula en la hoja Calibración de tipos.
A3: Definiciones: WHO (2014, glosario, pp. 82–85). Llegadas: Costigliola et al. (2017, p. 9015) y supuesto S10. Plazos: Costigliola et al. (2017, p. 9018) y supuesto S06. Volumen: Tabla 4 de Costigliola et al. (2017) y ensayos por muestra de Cunha et al. (2019), en la hoja Demanda.
A4: Código | B4: Tipo de muestra | C4: Definición | D4: Proporción de muestras | E4: Días de llegada por semana | F4: Llegada desde (h) | G4: Llegada hasta (h) | H4: Forma de llegada | I4: Plazo | J4: Unidad del plazo | K4: Plazo en horas (aprox.) | L4: Prioridad | M4: Puede ser urgente | N4: Muestras al año | O4: Muestras por día de llegada | P4: M01 | Q4: M02 | R4: M03 | S4: M04 | T4: M05 | U4: M06 | V4: M07 | W4: M08 | X4: M09 | Y4: M10 | Z4: M11 | AA4: M12 | AB4: Fuente o supuesto
A5: MP | B5: Materia prima | C5: Sustancia de calidad definida que se usa en la producción de un producto farmacéutico, excepto los materiales de empaque. | D5: 0.25 | E5: 5 | F5: 8 | G5: 17 | H5: Poisson | I5: 5 | J5: días hábiles | K5: =IF(J5="h",I5,I5*24) -> 120 | L5: =RANK(K5,$K$5:$K$9,1) -> 4 | M5: Sí | N5: =D5*Demanda!$C$11/Demanda!$C$22 -> 3192.2917 | O5: =N5/IF(E5=7,Demanda!$B$14,Demanda!$B$15) -> 12.278045 | P5: ='Calibración de tipos'!C58 -> 0.17395194 | Q5: ='Calibración de tipos'!D58 -> 0.095116665 | R5: ='Calibración de tipos'!E58 -> 0.31868 | S5: ='Calibración de tipos'!F58 -> 0.12154841 | T5: ='Calibración de tipos'!G58 -> 0.059759521 | U5: ='Calibración de tipos'!H58 -> 0.11531618 | V5: ='Calibración de tipos'!I58 -> 0.025683876 | W5: ='Calibración de tipos'!J58 -> 0.028919842 | ... AA5: ='Calibración de tipos'!N58 -> 0 | AB5: Definición: WHO (2014, p. 85). Baja prioridad: puede procesarse incluso después de una semana (Costigliola et al., 2017, p. 9018).
A6: IN | B6: Intermedio (control en proceso) | C6: Producto parcialmente procesado que debe pasar por más etapas antes de ser granel; sus muestras son controles hechos durante la producción para vigilar y ajustar el proceso. | D6: 0.3 | E6: 7 | F6: 0 | G6: 24 | H6: Poisson | I6: 4 | J6: h | K6: =IF(J6="h",I6,I6*24) -> 4 | L6: =RANK(K6,$K$5:$K$9,1) -> 1 | M6: No | N6: =D6*Demanda!$C$11/Demanda!$C$22 -> 3830.75 | O6: =N6/IF(E6=7,Demanda!$B$14,Demanda!$B$15) -> 10.495205 | P6: ='Calibración de tipos'!C59 -> 0.42369022 | Q6: ='Calibración de tipos'!D59 -> 0 | R6: ='Calibración de tipos'!E59 -> 0 | S6: ='Calibración de tipos'!F59 -> 0.29605232 | T6: ='Calibración de tipos'!G59 -> 0.14555472 | U6: ='Calibración de tipos'!H59 -> 0 | V6: ='Calibración de tipos'!I59 -> 0.06255755 | W6: ='Calibración de tipos'!J59 -> 0 | ... AA6: ='Calibración de tipos'!N59 -> 0 | AB6: Definiciones: WHO (2014, pp. 82–83). Se atiende las 24 h, los 7 días, y pasa unas 2 h en el sistema (Costigliola et al., 2017, pp. 9015 y 9018).
A7: GR | B7: Granel | C7: Producto que completó todas las etapas de procesamiento, sin incluir el empaque final. | D7: 0.1 | E7: 5 | F7: 8 | G7: 17 | H7: Poisson | I7: 1 | J7: días hábiles | K7: =IF(J7="h",I7,I7*24) -> 24 | L7: =RANK(K7,$K$5:$K$9,1) -> 2 | M7: Sí | N7: =D7*Demanda!$C$11/Demanda!$C$22 -> 1276.9167 | O7: =N7/IF(E7=7,Demanda!$B$14,Demanda!$B$15) -> 4.9112179 | P7: ='Calibración de tipos'!C60 -> 0.27474151 | Q7: ='Calibración de tipos'!D60 -> 0.15022825 | R7: ='Calibración de tipos'!E60 -> 0 | S7: ='Calibración de tipos'!F60 -> 0.19197484 | T7: ='Calibración de tipos'!G60 -> 0.094384813 | U7: ='Calibración de tipos'!H60 -> 0.18213158 | V7: ='Calibración de tipos'!I60 -> 0.040565382 | W7: ='Calibración de tipos'!J60 -> 0 | ... AA7: ='Calibración de tipos'!N60 -> 0.016374856 | AB7: Definición: WHO (2014, p. 82). Plazo: supuesto S06.
A8: PT | B8: Producto terminado | C8: Forma farmacéutica que pasó por todas las etapas de fabricación, incluidos el empaque en su envase final y el etiquetado. | D8: 0.2 | E8: 5 | F8: 8 | G8: 17 | H8: Poisson | I8: 2 | J8: días hábiles | K8: =IF(J8="h",I8,I8*24) -> 48 | L8: =RANK(K8,$K$5:$K$9,1) -> 3 | M8: Sí | N8: =D8*Demanda!$C$11/Demanda!$C$22 -> 2553.8333 | O8: =N8/IF(E8=7,Demanda!$B$14,Demanda!$B$15) -> 9.8224359 | P8: ='Calibración de tipos'!C61 -> 0.278568 | Q8: ='Calibración de tipos'!D61 -> 0.15232057 | R8: ='Calibración de tipos'!E61 -> 0 | S8: ='Calibración de tipos'!F61 -> 0.19464858 | T8: ='Calibración de tipos'!G61 -> 0 | U8: ='Calibración de tipos'!H61 -> 0.18466824 | V8: ='Calibración de tipos'!I61 -> 0.04113036 | W8: ='Calibración de tipos'!J61 -> 0.046312461 | ... AA8: ='Calibración de tipos'!N61 -> 0.016602918 | AB8: Definición: WHO (2014, p. 82). Unas 31 h en el sistema en HPLC, que según la fuente pueden representar una muestra de prioridad media (Costigliola et al., 2017, Tabla 5, p. 9018).
A9: ES | B9: Estabilidad | C9: Muestras de lotes en estudio de estabilidad, retiradas de las cámaras en las fechas del protocolo. | D9: 0.15 | E9: 5 | F9: 8 | G9: 8 | H9: Programada (lote al inicio de la jornada) | I9: 10 | J9: días hábiles | K9: =IF(J9="h",I9,I9*24) -> 240 | L9: =RANK(K9,$K$5:$K$9,1) -> 5 | M9: No | N9: =D9*Demanda!$C$11/Demanda!$C$22 -> 1915.375 | O9: =N9/IF(E9=7,Demanda!$B$14,Demanda!$B$15) -> 7.3668269 | P9: ='Calibración de tipos'!C62 -> 0.36182732 | Q9: ='Calibración de tipos'!D62 -> 0.19784665 | R9: ='Calibración de tipos'!E62 -> 0 | S9: ='Calibración de tipos'!F62 -> 0 | T9: ='Calibración de tipos'!G62 -> 0 | U9: ='Calibración de tipos'!H62 -> 0.23986249 | V9: ='Calibración de tipos'!I62 -> 0.053423538 | W9: ='Calibración de tipos'!J62 -> 0.060154482 | ... AA9: ='Calibración de tipos'!N62 -> 0.021565253 | AB9: Retiro cada 3 meses el primer año, cada 6 meses el segundo y luego cada año (WHO, 2018, §2.1.6 y §2.2.6); se analiza de lunes a viernes (Costigliola et al., 2017, p. 9015).

Sheet Calibración de tipos
A1: Calibración de los tipos de muestra
A2: Cómo se reparte cada método entre los tipos de muestra sin cambiar la mezcla de técnicas de Costigliola et al. (2017). Azul = dato · negro = fórmula · amarillo = supuesto.
A4: A. Datos de entrada: proporción objetivo de cada tipo (hoja Tipos de muestra) y métodos que aplican (hoja Catálogo, columnas MP a ES)
A5: Tipo / método | B5: Proporción objetivo | C5: M01 | D5: M02 | E5: M03 | F5: M04 | G5: M05 | H5: M06 | I5: M07 | J5: M08 | K5: M09 | L5: M10 | M5: M11 | N5: M12
A6: Técnica | C6: =Catálogo!B5 -> HPLC | D6: =Catálogo!B6 -> HPLC | E6: =Catálogo!B7 -> GC | F6: =Catálogo!B8 -> GC | G6: =Catálogo!B9 -> PSA | H6: =Catálogo!B10 -> PSA | I6: =Catálogo!B11 -> KF | J6: =Catálogo!B12 -> KF | K6: =Catálogo!B13 -> DSC | L6: =Catálogo!B14 -> DSC | M6: =Catálogo!B15 -> XRPD | N6: =Catálogo!B16 -> XRPD
A7: Participación en la demanda | C7: =Catálogo!M5 -> 0.3080569 | D7: =Catálogo!M6 -> 0.098943103 | E7: =Catálogo!M7 -> 0.07967 | F7: =Catálogo!M8 -> 0.17733 | G7: =Catálogo!M9 -> 0.068044776 | H7: =Catálogo!M10 -> 0.11995522 | I7: =Catálogo!M11 -> 0.045484375 | J7: =Catálogo!M12 -> 0.025515625 | K7: =Catálogo!M13 -> 0.0073333333 | L7: =Catálogo!M14 -> 0.032666667 | M7: =Catálogo!M15 -> 0.028807143 | N7: =Catálogo!M16 -> 0.0081928571
A8: MP | B8: ='Tipos de muestra'!D5 -> 0.25 | C8: =IF(INDEX(Catálogo!$V$5:$Z$16,MATCH(C$5,Catálogo!$A$5:$A$16,0),MATCH($A8,Catálogo!$V$4:$Z$4,0))="X",1,0) -> 1 | D8: =IF(INDEX(Catálogo!$V$5:$Z$16,MATCH(D$5,Catálogo!$A$5:$A$16,0),MATCH($A8,Catálogo!$V$4:$Z$4,0))="X",1,0) -> 1 | E8: =IF(INDEX(Catálogo!$V$5:$Z$16,MATCH(E$5,Catálogo!$A$5:$A$16,0),MATCH($A8,Catálogo!$V$4:$Z$4,0))="X",1,0) -> 1 | F8: =IF(INDEX(Catálogo!$V$5:$Z$16,MATCH(F$5,Catálogo!$A$5:$A$16,0),MATCH($A8,Catálogo!$V$4:$Z$4,0))="X",1,0) -> 1 | G8: =IF(INDEX(Catálogo!$V$5:$Z$16,MATCH(G$5,Catálogo!$A$5:$A$16,0),MATCH($A8,Catálogo!$V$4:$Z$4,0))="X",1,0) -> 1 | H8: =IF(INDEX(Catálogo!$V$5:$Z$16,MATCH(H$5,Catálogo!$A$5:$A$16,0),MATCH($A8,Catálogo!$V$4:$Z$4,0))="X",1,0) -> 1 | I8: =IF(INDEX(Catálogo!$V$5:$Z$16,MATCH(I$5,Catálogo!$A$5:$A$16,0),MATCH($A8,Catálogo!$V$4:$Z$4,0))="X",1,0) -> 1 | J8: =IF(INDEX(Catálogo!$V$5:$Z$16,MATCH(J$5,Catálogo!$A$5:$A$16,0),MATCH($A8,Catálogo!$V$4:$Z$4,0))="X",1,0) -> 1 | ... N8: =IF(INDEX(Catálogo!$V$5:$Z$16,MATCH(N$5,Catálogo!$A$5:$A$16,0),MATCH($A8,Catálogo!$V$4:$Z$4,0))="X",1,0) -> 0
A9: IN | B9: ='Tipos de muestra'!D6 -> 0.3 | C9: =IF(INDEX(Catálogo!$V$5:$Z$16,MATCH(C$5,Catálogo!$A$5:$A$16,0),MATCH($A9,Catálogo!$V$4:$Z$4,0))="X",1,0) -> 1 | D9: =IF(INDEX(Catálogo!$V$5:$Z$16,MATCH(D$5,Catálogo!$A$5:$A$16,0),MATCH($A9,Catálogo!$V$4:$Z$4,0))="X",1,0) -> 0 | E9: =IF(INDEX(Catálogo!$V$5:$Z$16,MATCH(E$5,Catálogo!$A$5:$A$16,0),MATCH($A9,Catálogo!$V$4:$Z$4,0))="X",1,0) -> 0 | F9: =IF(INDEX(Catálogo!$V$5:$Z$16,MATCH(F$5,Catálogo!$A$5:$A$16,0),MATCH($A9,Catálogo!$V$4:$Z$4,0))="X",1,0) -> 1 | G9: =IF(INDEX(Catálogo!$V$5:$Z$16,MATCH(G$5,Catálogo!$A$5:$A$16,0),MATCH($A9,Catálogo!$V$4:$Z$4,0))="X",1,0) -> 1 | H9: =IF(INDEX(Catálogo!$V$5:$Z$16,MATCH(H$5,Catálogo!$A$5:$A$16,0),MATCH($A9,Catálogo!$V$4:$Z$4,0))="X",1,0) -> 0 | I9: =IF(INDEX(Catálogo!$V$5:$Z$16,MATCH(I$5,Catálogo!$A$5:$A$16,0),MATCH($A9,Catálogo!$V$4:$Z$4,0))="X",1,0) -> 1 | J9: =IF(INDEX(Catálogo!$V$5:$Z$16,MATCH(J$5,Catálogo!$A$5:$A$16,0),MATCH($A9,Catálogo!$V$4:$Z$4,0))="X",1,0) -> 0 | ... N9: =IF(INDEX(Catálogo!$V$5:$Z$16,MATCH(N$5,Catálogo!$A$5:$A$16,0),MATCH($A9,Catálogo!$V$4:$Z$4,0))="X",1,0) -> 0
A10: GR | B10: ='Tipos de muestra'!D7 -> 0.1 | C10: =IF(INDEX(Catálogo!$V$5:$Z$16,MATCH(C$5,Catálogo!$A$5:$A$16,0),MATCH($A10,Catálogo!$V$4:$Z$4,0))="X",1,0) -> 1 | D10: =IF(INDEX(Catálogo!$V$5:$Z$16,MATCH(D$5,Catálogo!$A$5:$A$16,0),MATCH($A10,Catálogo!$V$4:$Z$4,0))="X",1,0) -> 1 | E10: =IF(INDEX(Catálogo!$V$5:$Z$16,MATCH(E$5,Catálogo!$A$5:$A$16,0),MATCH($A10,Catálogo!$V$4:$Z$4,0))="X",1,0) -> 0 | F10: =IF(INDEX(Catálogo!$V$5:$Z$16,MATCH(F$5,Catálogo!$A$5:$A$16,0),MATCH($A10,Catálogo!$V$4:$Z$4,0))="X",1,0) -> 1 | G10: =IF(INDEX(Catálogo!$V$5:$Z$16,MATCH(G$5,Catálogo!$A$5:$A$16,0),MATCH($A10,Catálogo!$V$4:$Z$4,0))="X",1,0) -> 1 | H10: =IF(INDEX(Catálogo!$V$5:$Z$16,MATCH(H$5,Catálogo!$A$5:$A$16,0),MATCH($A10,Catálogo!$V$4:$Z$4,0))="X",1,0) -> 1 | I10: =IF(INDEX(Catálogo!$V$5:$Z$16,MATCH(I$5,Catálogo!$A$5:$A$16,0),MATCH($A10,Catálogo!$V$4:$Z$4,0))="X",1,0) -> 1 | J10: =IF(INDEX(Catálogo!$V$5:$Z$16,MATCH(J$5,Catálogo!$A$5:$A$16,0),MATCH($A10,Catálogo!$V$4:$Z$4,0))="X",1,0) -> 0 | ... N10: =IF(INDEX(Catálogo!$V$5:$Z$16,MATCH(N$5,Catálogo!$A$5:$A$16,0),MATCH($A10,Catálogo!$V$4:$Z$4,0))="X",1,0) -> 1
A11: PT | B11: ='Tipos de muestra'!D8 -> 0.2 | C11: =IF(INDEX(Catálogo!$V$5:$Z$16,MATCH(C$5,Catálogo!$A$5:$A$16,0),MATCH($A11,Catálogo!$V$4:$Z$4,0))="X",1,0) -> 1 | D11: =IF(INDEX(Catálogo!$V$5:$Z$16,MATCH(D$5,Catálogo!$A$5:$A$16,0),MATCH($A11,Catálogo!$V$4:$Z$4,0))="X",1,0) -> 1 | E11: =IF(INDEX(Catálogo!$V$5:$Z$16,MATCH(E$5,Catálogo!$A$5:$A$16,0),MATCH($A11,Catálogo!$V$4:$Z$4,0))="X",1,0) -> 0 | F11: =IF(INDEX(Catálogo!$V$5:$Z$16,MATCH(F$5,Catálogo!$A$5:$A$16,0),MATCH($A11,Catálogo!$V$4:$Z$4,0))="X",1,0) -> 1 | G11: =IF(INDEX(Catálogo!$V$5:$Z$16,MATCH(G$5,Catálogo!$A$5:$A$16,0),MATCH($A11,Catálogo!$V$4:$Z$4,0))="X",1,0) -> 0 | H11: =IF(INDEX(Catálogo!$V$5:$Z$16,MATCH(H$5,Catálogo!$A$5:$A$16,0),MATCH($A11,Catálogo!$V$4:$Z$4,0))="X",1,0) -> 1 | I11: =IF(INDEX(Catálogo!$V$5:$Z$16,MATCH(I$5,Catálogo!$A$5:$A$16,0),MATCH($A11,Catálogo!$V$4:$Z$4,0))="X",1,0) -> 1 | J11: =IF(INDEX(Catálogo!$V$5:$Z$16,MATCH(J$5,Catálogo!$A$5:$A$16,0),MATCH($A11,Catálogo!$V$4:$Z$4,0))="X",1,0) -> 1 | ... N11: =IF(INDEX(Catálogo!$V$5:$Z$16,MATCH(N$5,Catálogo!$A$5:$A$16,0),MATCH($A11,Catálogo!$V$4:$Z$4,0))="X",1,0) -> 1
A12: ES | B12: ='Tipos de muestra'!D9 -> 0.15 | C12: =IF(INDEX(Catálogo!$V$5:$Z$16,MATCH(C$5,Catálogo!$A$5:$A$16,0),MATCH($A12,Catálogo!$V$4:$Z$4,0))="X",1,0) -> 1 | D12: =IF(INDEX(Catálogo!$V$5:$Z$16,MATCH(D$5,Catálogo!$A$5:$A$16,0),MATCH($A12,Catálogo!$V$4:$Z$4,0))="X",1,0) -> 1 | E12: =IF(INDEX(Catálogo!$V$5:$Z$16,MATCH(E$5,Catálogo!$A$5:$A$16,0),MATCH($A12,Catálogo!$V$4:$Z$4,0))="X",1,0) -> 0 | F12: =IF(INDEX(Catálogo!$V$5:$Z$16,MATCH(F$5,Catálogo!$A$5:$A$16,0),MATCH($A12,Catálogo!$V$4:$Z$4,0))="X",1,0) -> 0 | G12: =IF(INDEX(Catálogo!$V$5:$Z$16,MATCH(G$5,Catálogo!$A$5:$A$16,0),MATCH($A12,Catálogo!$V$4:$Z$4,0))="X",1,0) -> 0 | H12: =IF(INDEX(Catálogo!$V$5:$Z$16,MATCH(H$5,Catálogo!$A$5:$A$16,0),MATCH($A12,Catálogo!$V$4:$Z$4,0))="X",1,0) -> 1 | I12: =IF(INDEX(Catálogo!$V$5:$Z$16,MATCH(I$5,Catálogo!$A$5:$A$16,0),MATCH($A12,Catálogo!$V$4:$Z$4,0))="X",1,0) -> 1 | J12: =IF(INDEX(Catálogo!$V$5:$Z$16,MATCH(J$5,Catálogo!$A$5:$A$16,0),MATCH($A12,Catálogo!$V$4:$Z$4,0))="X",1,0) -> 1 | ... N12: =IF(INDEX(Catálogo!$V$5:$Z$16,MATCH(N$5,Catálogo!$A$5:$A$16,0),MATCH($A12,Catálogo!$V$4:$Z$4,0))="X",1,0) -> 1
A13: Tipos en que aplica el método | C13: =SUM(C8:C12) -> 5 | D13: =SUM(D8:D12) -> 4 | E13: =SUM(E8:E12) -> 1 | F13: =SUM(F8:F12) -> 4 | G13: =SUM(G8:G12) -> 3 | H13: =SUM(H8:H12) -> 4 | I13: =SUM(I8:I12) -> 5 | J13: =SUM(J8:J12) -> 3 | ... N13: =SUM(N8:N12) -> 3
A15: B. Ajuste proporcional iterativo (Deming y Stephan, 1940): w = peso de cada tipo; b = participación del método ÷ suma de los pesos de los tipos en que aplica; s = proporción que resulta para cada tipo
A16: Iteración | B16: w MP | C16: w IN | D16: w GR | E16: w PT | F16: w ES | G16: b M01 | H16: b M02 | I16: b M03 | J16: b M04 | K16: b M05 | L16: b M06 | M16: b M07 | N16: b M08 | O16: b M09 | P16: b M10 | Q16: b M11 | R16: b M12 | S16: s MP | T16: s IN | U16: s GR | V16: s PT | W16: s ES | X16: Error (suma de diferencias)
A17: 0 | B17: =$B$8 -> 0.25 | C17: =$B$9 -> 0.3 | D17: =$B$10 -> 0.1 | E17: =$B$11 -> 0.2 | F17: =$B$12 -> 0.15 | G17: =IFERROR(C$7/($B17*C$8+$C17*C$9+$D17*C$10+$E17*C$11+$F17*C$12),0) -> 0.3080569 | H17: =IFERROR(D$7/($B17*D$8+$C17*D$9+$D17*D$10+$E17*D$11+$F17*D$12),0) -> 0.14134729 | I17: =IFERROR(E$7/($B17*E$8+$C17*E$9+$D17*E$10+$E17*E$11+$F17*E$12),0) -> 0.31868 | J17: =IFERROR(F$7/($B17*F$8+$C17*F$9+$D17*F$10+$E17*F$11+$F17*F$12),0) -> 0.20862353 | K17: =IFERROR(G$7/($B17*G$8+$C17*G$9+$D17*G$10+$E17*G$11+$F17*G$12),0) -> 0.10468427 | L17: =IFERROR(H$7/($B17*H$8+$C17*H$9+$D17*H$10+$E17*H$11+$F17*H$12),0) -> 0.17136461 | M17: =IFERROR(I$7/($B17*I$8+$C17*I$9+$D17*I$10+$E17*I$11+$F17*I$12),0) -> 0.045484375 | N17: =IFERROR(J$7/($B17*J$8+$C17*J$9+$D17*J$10+$E17*J$11+$F17*J$12),0) -> 0.042526042 | ... R17: =IFERROR(N$7/($B17*N$8+$C17*N$9+$D17*N$10+$E17*N$11+$F17*N$12),0) -> 0.018206349 | S17: =B17*SUMPRODUCT($C$8:$N$8,$G17:$R17) -> 0.35979413 | T17: =C17*SUMPRODUCT($C$9:$N$9,$G17:$R17) -> 0.21557758 | U17: =D17*SUMPRODUCT($C$10:$N$10,$G17:$R17) -> 0.1044434 | V17: =E17*SUMPRODUCT($C$11:$N$11,$G17:$R17) -> 0.20413706 | W17: =F17*SUMPRODUCT($C$12:$N$12,$G17:$R17) -> 0.11604783 | X17: =ABS(S17-$B$8)+ABS(T17-$B$9)+ABS(U17-$B$10)+ABS(V17-$B$11)+ABS(W17-$B$12) -> 0.23674917
A18: 1 | B18: =IFERROR(B17*$B$8/S17,0) -> 0.17371045 | C18: =IFERROR(C17*$B$9/T17,0) -> 0.41748312 | D18: =IFERROR(D17*$B$10/U17,0) -> 0.09574564 | E18: =IFERROR(E17*$B$11/V17,0) -> 0.19594679 | F18: =IFERROR(F17*$B$12/W17,0) -> 0.19388557 | G18: =IFERROR(C$7/($B18*C$8+$C18*C$9+$D18*C$10+$E18*C$11+$F18*C$12),0) -> 0.28609308 | H18: =IFERROR(D$7/($B18*D$8+$C18*D$9+$D18*D$10+$E18*D$11+$F18*D$12),0) -> 0.15007559 | I18: =IFERROR(E$7/($B18*E$8+$C18*E$9+$D18*E$10+$E18*E$11+$F18*E$12),0) -> 0.45863678 | J18: =IFERROR(F$7/($B18*F$8+$C18*F$9+$D18*F$10+$E18*F$11+$F18*F$12),0) -> 0.20085266 | K18: =IFERROR(G$7/($B18*G$8+$C18*G$9+$D18*G$10+$E18*G$11+$F18*G$12),0) -> 0.099055019 | L18: =IFERROR(H$7/($B18*H$8+$C18*H$9+$D18*H$10+$E18*H$11+$F18*H$12),0) -> 0.1819465 | M18: =IFERROR(I$7/($B18*I$8+$C18*I$9+$D18*I$10+$E18*I$11+$F18*I$12),0) -> 0.042241434 | N18: =IFERROR(J$7/($B18*J$8+$C18*J$9+$D18*J$10+$E18*J$11+$F18*J$12),0) -> 0.045277173 | ... R18: =IFERROR(N$7/($B18*N$8+$C18*N$9+$D18*N$10+$E18*N$11+$F18*N$12),0) -> 0.016872382 | S18: =B18*SUMPRODUCT($C$8:$N$8,$G18:$R18) -> 0.2714622 | T18: =C18*SUMPRODUCT($C$9:$N$9,$G18:$R18) -> 0.28273781 | U18: =D18*SUMPRODUCT($C$10:$N$10,$G18:$R18) -> 0.098300616 | V18: =E18*SUMPRODUCT($C$11:$N$11,$G18:$R18) -> 0.19780914 | W18: =F18*SUMPRODUCT($C$12:$N$12,$G18:$R18) -> 0.14969023 | X18: =ABS(S18-$B$8)+ABS(T18-$B$9)+ABS(U18-$B$10)+ABS(V18-$B$11)+ABS(W18-$B$12) -> 0.042924398
A19: 2 | B19: =IFERROR(B18*$B$8/S18,0) -> 0.15997665 | C19: =IFERROR(C18*$B$9/T18,0) -> 0.44297201 | D19: =IFERROR(D18*$B$10/U18,0) -> 0.097400854 | E19: =IFERROR(E18*$B$11/V18,0) -> 0.19811702 | F19: =IFERROR(F18*$B$12/W18,0) -> 0.19428679 | G19: =IFERROR(C$7/($B19*C$8+$C19*C$9+$D19*C$10+$E19*C$11+$F19*C$12),0) -> 0.28190891 | H19: =IFERROR(D$7/($B19*D$8+$C19*D$9+$D19*D$10+$E19*D$11+$F19*D$12),0) -> 0.15227139 | I19: =IFERROR(E$7/($B19*E$8+$C19*E$9+$D19*E$10+$E19*E$11+$F19*E$12),0) -> 0.49801019 | J19: =IFERROR(F$7/($B19*F$8+$C19*F$9+$D19*F$10+$E19*F$11+$F19*F$12),0) -> 0.19736962 | K19: =IFERROR(G$7/($B19*G$8+$C19*G$9+$D19*G$10+$E19*G$11+$F19*G$12),0) -> 0.097158312 | L19: =IFERROR(H$7/($B19*H$8+$C19*H$9+$D19*H$10+$E19*H$11+$F19*H$12),0) -> 0.18460861 | M19: =IFERROR(I$7/($B19*I$8+$C19*I$9+$D19*I$10+$E19*I$11+$F19*I$12),0) -> 0.041623644 | N19: =IFERROR(J$7/($B19*J$8+$C19*J$9+$D19*J$10+$E19*J$11+$F19*J$12),0) -> 0.046192121 | ... R19: =IFERROR(N$7/($B19*N$8+$C19*N$9+$D19*N$10+$E19*N$11+$F19*N$12),0) -> 0.016726785 | S19: =B19*SUMPRODUCT($C$8:$N$8,$G19:$R19) -> 0.25556903 | T19: =C19*SUMPRODUCT($C$9:$N$9,$G19:$R19) -> 0.29510085 | U19: =D19*SUMPRODUCT($C$10:$N$10,$G19:$R19) -> 0.099537887 | V19: =E19*SUMPRODUCT($C$11:$N$11,$G19:$R19) -> 0.19949104 | W19: =F19*SUMPRODUCT($C$12:$N$12,$G19:$R19) -> 0.15030119 | X19: =ABS(S19-$B$8)+ABS(T19-$B$9)+ABS(U19-$B$10)+ABS(V19-$B$11)+ABS(W19-$B$12) -> 0.01174044
A20: 3 | B20: =IFERROR(B19*$B$8/S19,0) -> 0.15649064 | C20: =IFERROR(C19*$B$9/T19,0) -> 0.45032606 | D20: =IFERROR(D19*$B$10/U19,0) -> 0.097853046 | E20: =IFERROR(E19*$B$11/V19,0) -> 0.19862247 | F20: =IFERROR(F19*$B$12/W19,0) -> 0.19389746 | G20: =IFERROR(C$7/($B20*C$8+$C20*C$9+$D20*C$10+$E20*C$11+$F20*C$12),0) -> 0.28076905 | H20: =IFERROR(D$7/($B20*D$8+$C20*D$9+$D20*D$10+$E20*D$11+$F20*D$12),0) -> 0.15295822 | I20: =IFERROR(E$7/($B20*E$8+$C20*E$9+$D20*E$10+$E20*E$11+$F20*E$12),0) -> 0.50910392 | J20: =IFERROR(F$7/($B20*F$8+$C20*F$9+$D20*F$10+$E20*F$11+$F20*F$12),0) -> 0.19631521 | K20: =IFERROR(G$7/($B20*G$8+$C20*G$9+$D20*G$10+$E20*G$11+$F20*G$12),0) -> 0.096562647 | L20: =IFERROR(H$7/($B20*H$8+$C20*H$9+$D20*H$10+$E20*H$11+$F20*H$12),0) -> 0.18544129 | M20: =IFERROR(I$7/($B20*I$8+$C20*I$9+$D20*I$10+$E20*I$11+$F20*I$12),0) -> 0.041455344 | N20: =IFERROR(J$7/($B20*J$8+$C20*J$9+$D20*J$10+$E20*J$11+$F20*J$12),0) -> 0.046475654 | ... R20: =IFERROR(N$7/($B20*N$8+$C20*N$9+$D20*N$10+$E20*N$11+$F20*N$12),0) -> 0.0167074 | S20: =B20*SUMPRODUCT($C$8:$N$8,$G20:$R20) -> 0.25154808 | T20: =C20*SUMPRODUCT($C$9:$N$9,$G20:$R20) -> 0.29854498 | U20: =D20*SUMPRODUCT($C$10:$N$10,$G20:$R20) -> 0.099879507 | V20: =E20*SUMPRODUCT($C$11:$N$11,$G20:$R20) -> 0.19989127 | W20: =F20*SUMPRODUCT($C$12:$N$12,$G20:$R20) -> 0.15013616 | X20: =ABS(S20-$B$8)+ABS(T20-$B$9)+ABS(U20-$B$10)+ABS(V20-$B$11)+ABS(W20-$B$12) -> 0.0033684922
A21: 4 | B21: =IFERROR(B20*$B$8/S20,0) -> 0.15552757 | C21: =IFERROR(C20*$B$9/T20,0) -> 0.45252082 | D21: =IFERROR(D20*$B$10/U20,0) -> 0.097971094 | E21: =IFERROR(E20*$B$11/V20,0) -> 0.19873051 | F21: =IFERROR(F20*$B$12/W20,0) -> 0.1937216 | G21: =IFERROR(C$7/($B21*C$8+$C21*C$9+$D21*C$10+$E21*C$11+$F21*C$12),0) -> 0.28044139 | H21: =IFERROR(D$7/($B21*D$8+$C21*D$9+$D21*D$10+$E21*D$11+$F21*D$12),0) -> 0.15317437 | I21: =IFERROR(E$7/($B21*E$8+$C21*E$9+$D21*E$10+$E21*E$11+$F21*E$12),0) -> 0.51225646 | J21: =IFERROR(F$7/($B21*F$8+$C21*F$9+$D21*F$10+$E21*F$11+$F21*F$12),0) -> 0.1959989 | K21: =IFERROR(G$7/($B21*G$8+$C21*G$9+$D21*G$10+$E21*G$11+$F21*G$12),0) -> 0.096378044 | L21: =IFERROR(H$7/($B21*H$8+$C21*H$9+$D21*H$10+$E21*H$11+$F21*H$12),0) -> 0.18570335 | M21: =IFERROR(I$7/($B21*I$8+$C21*I$9+$D21*I$10+$E21*I$11+$F21*I$12),0) -> 0.041406965 | N21: =IFERROR(J$7/($B21*J$8+$C21*J$9+$D21*J$10+$E21*J$11+$F21*J$12),0) -> 0.046563086 | ... R21: =IFERROR(N$7/($B21*N$8+$C21*N$9+$D21*N$10+$E21*N$11+$F21*N$12),0) -> 0.016705688 | S21: =B21*SUMPRODUCT($C$8:$N$8,$G21:$R21) -> 0.25043995 | T21: =C21*SUMPRODUCT($C$9:$N$9,$G21:$R21) -> 0.29956521 | U21: =D21*SUMPRODUCT($C$10:$N$10,$G21:$R21) -> 0.09996776 | V21: =E21*SUMPRODUCT($C$11:$N$11,$G21:$R21) -> 0.19997686 | W21: =F21*SUMPRODUCT($C$12:$N$12,$G21:$R21) -> 0.15005023 | X21: =ABS(S21-$B$8)+ABS(T21-$B$9)+ABS(U21-$B$10)+ABS(V21-$B$11)+ABS(W21-$B$12) -> 0.00098034279
A22: 5 | B22: =IFERROR(B21*$B$8/S21,0) -> 0.15525435 | C22: =IFERROR(C21*$B$9/T21,0) -> 0.45317761 | D22: =IFERROR(D21*$B$10/U21,0) -> 0.09800269 | E22: =IFERROR(E21*$B$11/V21,0) -> 0.1987535 | F22: =IFERROR(F21*$B$12/W21,0) -> 0.19365676 | G22: =IFERROR(C$7/($B22*C$8+$C22*C$9+$D22*C$10+$E22*C$11+$F22*C$12),0) -> 0.28034611 | H22: =IFERROR(D$7/($B22*D$8+$C22*D$9+$D22*D$10+$E22*D$11+$F22*D$12),0) -> 0.15324162 | I22: =IFERROR(E$7/($B22*E$8+$C22*E$9+$D22*E$10+$E22*E$11+$F22*E$12),0) -> 0.51315792 | J22: =IFERROR(F$7/($B22*F$8+$C22*F$9+$D22*F$10+$E22*F$11+$F22*F$12),0) -> 0.19590402 | K22: =IFERROR(G$7/($B22*G$8+$C22*G$9+$D22*G$10+$E22*G$11+$F22*G$12),0) -> 0.096321402 | L22: =IFERROR(H$7/($B22*H$8+$C22*H$9+$D22*H$10+$E22*H$11+$F22*H$12),0) -> 0.18578488 | M22: =IFERROR(I$7/($B22*I$8+$C22*I$9+$D22*I$10+$E22*I$11+$F22*I$12),0) -> 0.041392898 | N22: =IFERROR(J$7/($B22*J$8+$C22*J$9+$D22*J$10+$E22*J$11+$F22*J$12),0) -> 0.046589873 | ... R22: =IFERROR(N$7/($B22*N$8+$C22*N$9+$D22*N$10+$E22*N$11+$F22*N$12),0) -> 0.016706037 | S22: =B22*SUMPRODUCT($C$8:$N$8,$G22:$R22) -> 0.25012619 | T22: =C22*SUMPRODUCT($C$9:$N$9,$G22:$R22) -> 0.29987019 | U22: =D22*SUMPRODUCT($C$10:$N$10,$G22:$R22) -> 0.099991225 | V22: =E22*SUMPRODUCT($C$11:$N$11,$G22:$R22) -> 0.19999521 | W22: =F22*SUMPRODUCT($C$12:$N$12,$G22:$R22) -> 0.15001719 | X22: =ABS(S22-$B$8)+ABS(T22-$B$9)+ABS(U22-$B$10)+ABS(V22-$B$11)+ABS(W22-$B$12) -> 0.00028675463
A23: 6 | B23: =IFERROR(B22*$B$8/S22,0) -> 0.15517603 | C23: =IFERROR(C22*$B$9/T22,0) -> 0.45337379 | D23: =IFERROR(D22*$B$10/U22,0) -> 0.09801129 | E23: =IFERROR(E22*$B$11/V22,0) -> 0.19875826 | F23: =IFERROR(F22*$B$12/W22,0) -> 0.19363457 | G23: =IFERROR(C$7/($B23*C$8+$C23*C$9+$D23*C$10+$E23*C$11+$F23*C$12),0) -> 0.2803183 | H23: =IFERROR(D$7/($B23*D$8+$C23*D$9+$D23*D$10+$E23*D$11+$F23*D$12),0) -> 0.15326231 | I23: =IFERROR(E$7/($B23*E$8+$C23*E$9+$D23*E$10+$E23*E$11+$F23*E$12),0) -> 0.51341693 | J23: =IFERROR(F$7/($B23*F$8+$C23*F$9+$D23*F$10+$E23*F$11+$F23*F$12),0) -> 0.19587563 | K23: =IFERROR(G$7/($B23*G$8+$C23*G$9+$D23*G$10+$E23*G$11+$F23*G$12),0) -> 0.096304163 | L23: =IFERROR(H$7/($B23*H$8+$C23*H$9+$D23*H$10+$E23*H$11+$F23*H$12),0) -> 0.18580996 | M23: =IFERROR(I$7/($B23*I$8+$C23*I$9+$D23*I$10+$E23*I$11+$F23*I$12),0) -> 0.041388791 | N23: =IFERROR(J$7/($B23*J$8+$C23*J$9+$D23*J$10+$E23*J$11+$F23*J$12),0) -> 0.046598021 | ... R23: =IFERROR(N$7/($B23*N$8+$C23*N$9+$D23*N$10+$E23*N$11+$F23*N$12),0) -> 0.016706338 | S23: =B23*SUMPRODUCT($C$8:$N$8,$G23:$R23) -> 0.25003638 | T23: =C23*SUMPRODUCT($C$9:$N$9,$G23:$R23) -> 0.29996132 | U23: =D23*SUMPRODUCT($C$10:$N$10,$G23:$R23) -> 0.099997584 | V23: =E23*SUMPRODUCT($C$11:$N$11,$G23:$R23) -> 0.19999907 | W23: =F23*SUMPRODUCT($C$12:$N$12,$G23:$R23) -> 0.15000564 | X23: =ABS(S23-$B$8)+ABS(T23-$B$9)+ABS(U23-$B$10)+ABS(V23-$B$11)+ABS(W23-$B$12) -> 8.4045407e-05
A24: 7 | B24: =IFERROR(B23*$B$8/S23,0) -> 0.15515345 | C24: =IFERROR(C23*$B$9/T23,0) -> 0.45343225 | D24: =IFERROR(D23*$B$10/U23,0) -> 0.098013658 | E24: =IFERROR(E23*$B$11/V23,0) -> 0.19875919 | F24: =IFERROR(F23*$B$12/W23,0) -> 0.19362729 | G24: =IFERROR(C$7/($B24*C$8+$C24*C$9+$D24*C$10+$E24*C$11+$F24*C$12),0) -> 0.28031016 | H24: =IFERROR(D$7/($B24*D$8+$C24*D$9+$D24*D$10+$E24*D$11+$F24*D$12),0) -> 0.15326862 | I24: =IFERROR(E$7/($B24*E$8+$C24*E$9+$D24*E$10+$E24*E$11+$F24*E$12),0) -> 0.51349165 | J24: =IFERROR(F$7/($B24*F$8+$C24*F$9+$D24*F$10+$E24*F$11+$F24*F$12),0) -> 0.19586715 | K24: =IFERROR(G$7/($B24*G$8+$C24*G$9+$D24*G$10+$E24*G$11+$F24*G$12),0) -> 0.096298951 | L24: =IFERROR(H$7/($B24*H$8+$C24*H$9+$D24*H$10+$E24*H$11+$F24*H$12),0) -> 0.18581761 | M24: =IFERROR(I$7/($B24*I$8+$C24*I$9+$D24*I$10+$E24*I$11+$F24*I$12),0) -> 0.04138759 | N24: =IFERROR(J$7/($B24*J$8+$C24*J$9+$D24*J$10+$E24*J$11+$F24*J$12),0) -> 0.046600483 | ... R24: =IFERROR(N$7/($B24*N$8+$C24*N$9+$D24*N$10+$E24*N$11+$F24*N$12),0) -> 0.016706474 | S24: =B24*SUMPRODUCT($C$8:$N$8,$G24:$R24) -> 0.25001053 | T24: =C24*SUMPRODUCT($C$9:$N$9,$G24:$R24) -> 0.2999885 | U24: =D24*SUMPRODUCT($C$10:$N$10,$G24:$R24) -> 0.099999329 | V24: =E24*SUMPRODUCT($C$11:$N$11,$G24:$R24) -> 0.19999984 | W24: =F24*SUMPRODUCT($C$12:$N$12,$G24:$R24) -> 0.1500018 | X24: =ABS(S24-$B$8)+ABS(T24-$B$9)+ABS(U24-$B$10)+ABS(V24-$B$11)+ABS(W24-$B$12) -> 2.4658035e-05
A25: 8 | B25: =IFERROR(B24*$B$8/S24,0) -> 0.15514691 | C25: =IFERROR(C24*$B$9/T24,0) -> 0.45344963 | D25: =IFERROR(D24*$B$10/U24,0) -> 0.098014316 | E25: =IFERROR(E24*$B$11/V24,0) -> 0.19875935 | F25: =IFERROR(F24*$B$12/W24,0) -> 0.19362496 | G25: =IFERROR(C$7/($B25*C$8+$C25*C$9+$D25*C$10+$E25*C$11+$F25*C$12),0) -> 0.28030778 | H25: =IFERROR(D$7/($B25*D$8+$C25*D$9+$D25*D$10+$E25*D$11+$F25*D$12),0) -> 0.15327052 | I25: =IFERROR(E$7/($B25*E$8+$C25*E$9+$D25*E$10+$E25*E$11+$F25*E$12),0) -> 0.51351328 | J25: =IFERROR(F$7/($B25*F$8+$C25*F$9+$D25*F$10+$E25*F$11+$F25*F$12),0) -> 0.19586463 | K25: =IFERROR(G$7/($B25*G$8+$C25*G$9+$D25*G$10+$E25*G$11+$F25*G$12),0) -> 0.096297383 | L25: =IFERROR(H$7/($B25*H$8+$C25*H$9+$D25*H$10+$E25*H$11+$F25*H$12),0) -> 0.18581993 | M25: =IFERROR(I$7/($B25*I$8+$C25*I$9+$D25*I$10+$E25*I$11+$F25*I$12),0) -> 0.041387238 | N25: =IFERROR(J$7/($B25*J$8+$C25*J$9+$D25*J$10+$E25*J$11+$F25*J$12),0) -> 0.046601224 | ... R25: =IFERROR(N$7/($B25*N$8+$C25*N$9+$D25*N$10+$E25*N$11+$F25*N$12),0) -> 0.016706526 | S25: =B25*SUMPRODUCT($C$8:$N$8,$G25:$R25) -> 0.25000306 | T25: =C25*SUMPRODUCT($C$9:$N$9,$G25:$R25) -> 0.29999659 | U25: =D25*SUMPRODUCT($C$10:$N$10,$G25:$R25) -> 0.099999812 | V25: =E25*SUMPRODUCT($C$11:$N$11,$G25:$R25) -> 0.19999998 | W25: =F25*SUMPRODUCT($C$12:$N$12,$G25:$R25) -> 0.15000056 | X25: =ABS(S25-$B$8)+ABS(T25-$B$9)+ABS(U25-$B$10)+ABS(V25-$B$11)+ABS(W25-$B$12) -> 7.2391139e-06
A26: 9 | B26: =IFERROR(B25*$B$8/S25,0) -> 0.15514502 | C26: =IFERROR(C25*$B$9/T25,0) -> 0.45345478 | D26: =IFERROR(D25*$B$10/U25,0) -> 0.0980145 | E26: =IFERROR(E25*$B$11/V25,0) -> 0.19875937 | F26: =IFERROR(F25*$B$12/W25,0) -> 0.19362423 | G26: =IFERROR(C$7/($B26*C$8+$C26*C$9+$D26*C$10+$E26*C$11+$F26*C$12),0) -> 0.28030708 | H26: =IFERROR(D$7/($B26*D$8+$C26*D$9+$D26*D$10+$E26*D$11+$F26*D$12),0) -> 0.1532711 | I26: =IFERROR(E$7/($B26*E$8+$C26*E$9+$D26*E$10+$E26*E$11+$F26*E$12),0) -> 0.51351955 | J26: =IFERROR(F$7/($B26*F$8+$C26*F$9+$D26*F$10+$E26*F$11+$F26*F$12),0) -> 0.19586388 | K26: =IFERROR(G$7/($B26*G$8+$C26*G$9+$D26*G$10+$E26*G$11+$F26*G$12),0) -> 0.096296913 | L26: =IFERROR(H$7/($B26*H$8+$C26*H$9+$D26*H$10+$E26*H$11+$F26*H$12),0) -> 0.18582062 | M26: =IFERROR(I$7/($B26*I$8+$C26*I$9+$D26*I$10+$E26*I$11+$F26*I$12),0) -> 0.041387135 | N26: =IFERROR(J$7/($B26*J$8+$C26*J$9+$D26*J$10+$E26*J$11+$F26*J$12),0) -> 0.046601445 | ... R26: =IFERROR(N$7/($B26*N$8+$C26*N$9+$D26*N$10+$E26*N$11+$F26*N$12),0) -> 0.016706543 | S26: =B26*SUMPRODUCT($C$8:$N$8,$G26:$R26) -> 0.25000089 | T26: =C26*SUMPRODUCT($C$9:$N$9,$G26:$R26) -> 0.29999899 | U26: =D26*SUMPRODUCT($C$10:$N$10,$G26:$R26) -> 0.099999947 | V26: =E26*SUMPRODUCT($C$11:$N$11,$G26:$R26) -> 0.2 | W26: =F26*SUMPRODUCT($C$12:$N$12,$G26:$R26) -> 0.15000017 | X26: =ABS(S26-$B$8)+ABS(T26-$B$9)+ABS(U26-$B$10)+ABS(V26-$B$11)+ABS(W26-$B$12) -> 2.1284047e-06
A27: 10 | B27: =IFERROR(B26*$B$8/S26,0) -> 0.15514447 | C27: =IFERROR(C26*$B$9/T26,0) -> 0.45345631 | D27: =IFERROR(D26*$B$10/U26,0) -> 0.098014552 | E27: =IFERROR(E26*$B$11/V26,0) -> 0.19875936 | F27: =IFERROR(F26*$B$12/W26,0) -> 0.19362401 | G27: =IFERROR(C$7/($B27*C$8+$C27*C$9+$D27*C$10+$E27*C$11+$F27*C$12),0) -> 0.28030688 | H27: =IFERROR(D$7/($B27*D$8+$C27*D$9+$D27*D$10+$E27*D$11+$F27*D$12),0) -> 0.15327127 | I27: =IFERROR(E$7/($B27*E$8+$C27*E$9+$D27*E$10+$E27*E$11+$F27*E$12),0) -> 0.51352138 | J27: =IFERROR(F$7/($B27*F$8+$C27*F$9+$D27*F$10+$E27*F$11+$F27*F$12),0) -> 0.19586366 | K27: =IFERROR(G$7/($B27*G$8+$C27*G$9+$D27*G$10+$E27*G$11+$F27*G$12),0) -> 0.096296773 | L27: =IFERROR(H$7/($B27*H$8+$C27*H$9+$D27*H$10+$E27*H$11+$F27*H$12),0) -> 0.18582083 | M27: =IFERROR(I$7/($B27*I$8+$C27*I$9+$D27*I$10+$E27*I$11+$F27*I$12),0) -> 0.041387105 | N27: =IFERROR(J$7/($B27*J$8+$C27*J$9+$D27*J$10+$E27*J$11+$F27*J$12),0) -> 0.046601512 | ... R27: =IFERROR(N$7/($B27*N$8+$C27*N$9+$D27*N$10+$E27*N$11+$F27*N$12),0) -> 0.016706549 | S27: =B27*SUMPRODUCT($C$8:$N$8,$G27:$R27) -> 0.25000026 | T27: =C27*SUMPRODUCT($C$9:$N$9,$G27:$R27) -> 0.2999997 | U27: =D27*SUMPRODUCT($C$10:$N$10,$G27:$R27) -> 0.099999985 | V27: =E27*SUMPRODUCT($C$11:$N$11,$G27:$R27) -> 0.2 | W27: =F27*SUMPRODUCT($C$12:$N$12,$G27:$R27) -> 0.15000005 | X27: =ABS(S27-$B$8)+ABS(T27-$B$9)+ABS(U27-$B$10)+ABS(V27-$B$11)+ABS(W27-$B$12) -> 6.2863718e-07
A28: 11 | B28: =IFERROR(B27*$B$8/S27,0) -> 0.15514431 | C28: =IFERROR(C27*$B$9/T27,0) -> 0.45345677 | D28: =IFERROR(D27*$B$10/U27,0) -> 0.098014567 | E28: =IFERROR(E27*$B$11/V27,0) -> 0.19875936 | F28: =IFERROR(F27*$B$12/W27,0) -> 0.19362394 | G28: =IFERROR(C$7/($B28*C$8+$C28*C$9+$D28*C$10+$E28*C$11+$F28*C$12),0) -> 0.28030682 | H28: =IFERROR(D$7/($B28*D$8+$C28*D$9+$D28*D$10+$E28*D$11+$F28*D$12),0) -> 0.15327132 | I28: =IFERROR(E$7/($B28*E$8+$C28*E$9+$D28*E$10+$E28*E$11+$F28*E$12),0) -> 0.51352191 | J28: =IFERROR(F$7/($B28*F$8+$C28*F$9+$D28*F$10+$E28*F$11+$F28*F$12),0) -> 0.19586359 | K28: =IFERROR(G$7/($B28*G$8+$C28*G$9+$D28*G$10+$E28*G$11+$F28*G$12),0) -> 0.096296731 | L28: =IFERROR(H$7/($B28*H$8+$C28*H$9+$D28*H$10+$E28*H$11+$F28*H$12),0) -> 0.18582089 | M28: =IFERROR(I$7/($B28*I$8+$C28*I$9+$D28*I$10+$E28*I$11+$F28*I$12),0) -> 0.041387096 | N28: =IFERROR(J$7/($B28*J$8+$C28*J$9+$D28*J$10+$E28*J$11+$F28*J$12),0) -> 0.046601531 | ... R28: =IFERROR(N$7/($B28*N$8+$C28*N$9+$D28*N$10+$E28*N$11+$F28*N$12),0) -> 0.016706551 | S28: =B28*SUMPRODUCT($C$8:$N$8,$G28:$R28) -> 0.25000008 | T28: =C28*SUMPRODUCT($C$9:$N$9,$G28:$R28) -> 0.29999991 | U28: =D28*SUMPRODUCT($C$10:$N$10,$G28:$R28) -> 0.099999996 | V28: =E28*SUMPRODUCT($C$11:$N$11,$G28:$R28) -> 0.2 | W28: =F28*SUMPRODUCT($C$12:$N$12,$G28:$R28) -> 0.15000002 | X28: =ABS(S28-$B$8)+ABS(T28-$B$9)+ABS(U28-$B$10)+ABS(V28-$B$11)+ABS(W28-$B$12) -> 1.8555719e-07
A29: 12 | B29: =IFERROR(B28*$B$8/S28,0) -> 0.15514426 | C29: =IFERROR(C28*$B$9/T28,0) -> 0.4534569 | D29: =IFERROR(D28*$B$10/U28,0) -> 0.098014571 | E29: =IFERROR(E28*$B$11/V28,0) -> 0.19875936 | F29: =IFERROR(F28*$B$12/W28,0) -> 0.19362392 | G29: =IFERROR(C$7/($B29*C$8+$C29*C$9+$D29*C$10+$E29*C$11+$F29*C$12),0) -> 0.2803068 | H29: =IFERROR(D$7/($B29*D$8+$C29*D$9+$D29*D$10+$E29*D$11+$F29*D$12),0) -> 0.15327134 | I29: =IFERROR(E$7/($B29*E$8+$C29*E$9+$D29*E$10+$E29*E$11+$F29*E$12),0) -> 0.51352207 | J29: =IFERROR(F$7/($B29*F$8+$C29*F$9+$D29*F$10+$E29*F$11+$F29*F$12),0) -> 0.19586357 | K29: =IFERROR(G$7/($B29*G$8+$C29*G$9+$D29*G$10+$E29*G$11+$F29*G$12),0) -> 0.096296719 | L29: =IFERROR(H$7/($B29*H$8+$C29*H$9+$D29*H$10+$E29*H$11+$F29*H$12),0) -> 0.18582091 | M29: =IFERROR(I$7/($B29*I$8+$C29*I$9+$D29*I$10+$E29*I$11+$F29*I$12),0) -> 0.041387094 | N29: =IFERROR(J$7/($B29*J$8+$C29*J$9+$D29*J$10+$E29*J$11+$F29*J$12),0) -> 0.046601537 | ... R29: =IFERROR(N$7/($B29*N$8+$C29*N$9+$D29*N$10+$E29*N$11+$F29*N$12),0) -> 0.016706552 | S29: =B29*SUMPRODUCT($C$8:$N$8,$G29:$R29) -> 0.25000002 | T29: =C29*SUMPRODUCT($C$9:$N$9,$G29:$R29) -> 0.29999997 | U29: =D29*SUMPRODUCT($C$10:$N$10,$G29:$R29) -> 0.099999999 | V29: =E29*SUMPRODUCT($C$11:$N$11,$G29:$R29) -> 0.2 | W29: =F29*SUMPRODUCT($C$12:$N$12,$G29:$R29) -> 0.15 | X29: =ABS(S29-$B$8)+ABS(T29-$B$9)+ABS(U29-$B$10)+ABS(V29-$B$11)+ABS(W29-$B$12) -> 5.4743928e-08
... A42: 25 | B42: =IFERROR(B41*$B$8/S41,0) -> 0.15514424 | C42: =IFERROR(C41*$B$9/T41,0) -> 0.45345696 | D42: =IFERROR(D41*$B$10/U41,0) -> 0.098014573 | E42: =IFERROR(E41*$B$11/V41,0) -> 0.19875936 | F42: =IFERROR(F41*$B$12/W41,0) -> 0.19362391 | G42: =IFERROR(C$7/($B42*C$8+$C42*C$9+$D42*C$10+$E42*C$11+$F42*C$12),0) -> 0.28030679 | H42: =IFERROR(D$7/($B42*D$8+$C42*D$9+$D42*D$10+$E42*D$11+$F42*D$12),0) -> 0.15327134 | I42: =IFERROR(E$7/($B42*E$8+$C42*E$9+$D42*E$10+$E42*E$11+$F42*E$12),0) -> 0.51352213 | J42: =IFERROR(F$7/($B42*F$8+$C42*F$9+$D42*F$10+$E42*F$11+$F42*F$12),0) -> 0.19586356 | K42: =IFERROR(G$7/($B42*G$8+$C42*G$9+$D42*G$10+$E42*G$11+$F42*G$12),0) -> 0.096296714 | L42: =IFERROR(H$7/($B42*H$8+$C42*H$9+$D42*H$10+$E42*H$11+$F42*H$12),0) -> 0.18582092 | M42: =IFERROR(I$7/($B42*I$8+$C42*I$9+$D42*I$10+$E42*I$11+$F42*I$12),0) -> 0.041387093 | N42: =IFERROR(J$7/($B42*J$8+$C42*J$9+$D42*J$10+$E42*J$11+$F42*J$12),0) -> 0.04660154 | ... R42: =IFERROR(N$7/($B42*N$8+$C42*N$9+$D42*N$10+$E42*N$11+$F42*N$12),0) -> 0.016706552 | S42: =B42*SUMPRODUCT($C$8:$N$8,$G42:$R42) -> 0.25 | T42: =C42*SUMPRODUCT($C$9:$N$9,$G42:$R42) -> 0.3 | U42: =D42*SUMPRODUCT($C$10:$N$10,$G42:$R42) -> 0.1 | V42: =E42*SUMPRODUCT($C$11:$N$11,$G42:$R42) -> 0.2 | W42: =F42*SUMPRODUCT($C$12:$N$12,$G42:$R42) -> 0.15 | X42: =ABS(S42-$B$8)+ABS(T42-$B$9)+ABS(U42-$B$10)+ABS(V42-$B$11)+ABS(W42-$B$12) -> 6.6613381e-15
A43: El ajuste parte de la matriz de aplicación (dentro de un método, todos los tipos en que aplica pesan igual) y alterna dos correcciones: que cada método conserve su participación y que cada tipo llegue a su proporción objetivo. Converge en unas 10 iteraciones; se calculan 25.
A45: C. Mezcla resultante: proporción del total de ensayos que corresponde a cada par tipo–método (última iteración)
A46: Tipo | B46: Proporción lograda | C46: M01 | D46: M02 | E46: M03 | F46: M04 | G46: M05 | H46: M06 | I46: M07 | J46: M08 | K46: M09 | L46: M10 | M46: M11 | N46: M12 | O46: Objetivo | P46: Diferencia
A47: MP | B47: =SUM(C47:N47) -> 0.25 | C47: =$B$42*C8*G$42 -> 0.043487984 | D47: =$B$42*D8*H$42 -> 0.023779166 | E47: =$B$42*E8*I$42 -> 0.07967 | F47: =$B$42*F8*J$42 -> 0.030387104 | G47: =$B$42*G8*K$42 -> 0.01493988 | H47: =$B$42*H8*L$42 -> 0.028829045 | I47: =$B$42*I8*M$42 -> 0.006420969 | J47: =$B$42*J8*N$42 -> 0.0072299604 | ... N47: =$B$42*N8*R$42 -> 0 | O47: =B8 -> 0.25 | P47: =ABS(B47-O47) -> 2.6645353e-15
A48: IN | B48: =SUM(C48:N48) -> 0.3 | C48: =$C$42*C9*G$42 -> 0.12710707 | D48: =$C$42*D9*H$42 -> 0 | E48: =$C$42*E9*I$42 -> 0 | F48: =$C$42*F9*J$42 -> 0.088815696 | G48: =$C$42*G9*K$42 -> 0.043666415 | H48: =$C$42*H9*L$42 -> 0 | I48: =$C$42*I9*M$42 -> 0.018767265 | J48: =$C$42*J9*N$42 -> 0 | ... N48: =$C$42*N9*R$42 -> 0 | O48: =B9 -> 0.3 | P48: =ABS(B48-O48) -> 3.3306691e-15
A49: GR | B49: =SUM(C49:N49) -> 0.1 | C49: =$D$42*C10*G$42 -> 0.027474151 | D49: =$D$42*D10*H$42 -> 0.015022825 | E49: =$D$42*E10*I$42 -> 0 | F49: =$D$42*F10*J$42 -> 0.019197484 | G49: =$D$42*G10*K$42 -> 0.0094384813 | H49: =$D$42*H10*L$42 -> 0.018213158 | I49: =$D$42*I10*M$42 -> 0.0040565382 | J49: =$D$42*J10*N$42 -> 0 | ... N49: =$D$42*N10*R$42 -> 0.0016374856 | O49: =B10 -> 0.1 | P49: =ABS(B49-O49) -> 0
A50: PT | B50: =SUM(C50:N50) -> 0.2 | C50: =$E$42*C11*G$42 -> 0.055713599 | D50: =$E$42*D11*H$42 -> 0.030464115 | E50: =$E$42*E11*I$42 -> 0 | F50: =$E$42*F11*J$42 -> 0.038929717 | G50: =$E$42*G11*K$42 -> 0 | H50: =$E$42*H11*L$42 -> 0.036933647 | I50: =$E$42*I11*M$42 -> 0.0082260721 | J50: =$E$42*J11*N$42 -> 0.0092624922 | ... N50: =$E$42*N11*R$42 -> 0.0033205836 | O50: =B11 -> 0.2 | P50: =ABS(B50-O50) -> 0
A51: ES | B51: =SUM(C51:N51) -> 0.15 | C51: =$F$42*C12*G$42 -> 0.054274098 | D51: =$F$42*D12*H$42 -> 0.029676997 | E51: =$F$42*E12*I$42 -> 0 | F51: =$F$42*F12*J$42 -> 0 | G51: =$F$42*G12*K$42 -> 0 | H51: =$F$42*H12*L$42 -> 0.035979373 | I51: =$F$42*I12*M$42 -> 0.0080135307 | J51: =$F$42*J12*N$42 -> 0.0090231724 | ... N51: =$F$42*N12*R$42 -> 0.003234788 | O51: =B12 -> 0.15 | P51: =ABS(B51-O51) -> 6.6613381e-16
A52: Suma por método | C52: =SUM(C47:C51) -> 0.3080569 | D52: =SUM(D47:D51) -> 0.098943103 | E52: =SUM(E47:E51) -> 0.07967 | F52: =SUM(F47:F51) -> 0.17733 | G52: =SUM(G47:G51) -> 0.068044776 | H52: =SUM(H47:H51) -> 0.11995522 | I52: =SUM(I47:I51) -> 0.045484375 | J52: =SUM(J47:J51) -> 0.025515625 | ... N52: =SUM(N47:N51) -> 0.0081928571
A53: Participación en el catálogo | C53: =C$7 -> 0.3080569 | D53: =D$7 -> 0.098943103 | E53: =E$7 -> 0.07967 | F53: =F$7 -> 0.17733 | G53: =G$7 -> 0.068044776 | H53: =H$7 -> 0.11995522 | I53: =I$7 -> 0.045484375 | J53: =J$7 -> 0.025515625 | ... N53: =N$7 -> 0.0081928571
A54: Diferencia | C54: =ABS(C52-C53) -> 0 | D54: =ABS(D52-D53) -> 0 | E54: =ABS(E52-E53) -> 0 | F54: =ABS(F52-F53) -> 0 | G54: =ABS(G52-G53) -> 0 | H54: =ABS(H52-H53) -> 0 | I54: =ABS(I52-I53) -> 0 | J54: =ABS(J52-J53) -> 0 | ... N54: =ABS(N52-N53) -> 0
A56: Probabilidad de cada método dentro de cada tipo de muestra (la usa el generador; pasa a las columnas M01 a M12 de la hoja Tipos de muestra)
A57: Tipo | B57: Suma | C57: M01 | D57: M02 | E57: M03 | F57: M04 | G57: M05 | H57: M06 | I57: M07 | J57: M08 | K57: M09 | L57: M10 | M57: M11 | N57: M12
A58: MP | B58: =SUM(C58:N58) -> 1 | C58: =IFERROR(C47/$B47,0) -> 0.17395194 | D58: =IFERROR(D47/$B47,0) -> 0.095116665 | E58: =IFERROR(E47/$B47,0) -> 0.31868 | F58: =IFERROR(F47/$B47,0) -> 0.12154841 | G58: =IFERROR(G47/$B47,0) -> 0.059759521 | H58: =IFERROR(H47/$B47,0) -> 0.11531618 | I58: =IFERROR(I47/$B47,0) -> 0.025683876 | J58: =IFERROR(J47/$B47,0) -> 0.028919842 | ... N58: =IFERROR(N47/$B47,0) -> 0
A59: IN | B59: =SUM(C59:N59) -> 1 | C59: =IFERROR(C48/$B48,0) -> 0.42369022 | D59: =IFERROR(D48/$B48,0) -> 0 | E59: =IFERROR(E48/$B48,0) -> 0 | F59: =IFERROR(F48/$B48,0) -> 0.29605232 | G59: =IFERROR(G48/$B48,0) -> 0.14555472 | H59: =IFERROR(H48/$B48,0) -> 0 | I59: =IFERROR(I48/$B48,0) -> 0.06255755 | J59: =IFERROR(J48/$B48,0) -> 0 | ... N59: =IFERROR(N48/$B48,0) -> 0
A60: GR | B60: =SUM(C60:N60) -> 1 | C60: =IFERROR(C49/$B49,0) -> 0.27474151 | D60: =IFERROR(D49/$B49,0) -> 0.15022825 | E60: =IFERROR(E49/$B49,0) -> 0 | F60: =IFERROR(F49/$B49,0) -> 0.19197484 | G60: =IFERROR(G49/$B49,0) -> 0.094384813 | H60: =IFERROR(H49/$B49,0) -> 0.18213158 | I60: =IFERROR(I49/$B49,0) -> 0.040565382 | J60: =IFERROR(J49/$B49,0) -> 0 | ... N60: =IFERROR(N49/$B49,0) -> 0.016374856
A61: PT | B61: =SUM(C61:N61) -> 1 | C61: =IFERROR(C50/$B50,0) -> 0.278568 | D61: =IFERROR(D50/$B50,0) -> 0.15232057 | E61: =IFERROR(E50/$B50,0) -> 0 | F61: =IFERROR(F50/$B50,0) -> 0.19464858 | G61: =IFERROR(G50/$B50,0) -> 0 | H61: =IFERROR(H50/$B50,0) -> 0.18466824 | I61: =IFERROR(I50/$B50,0) -> 0.04113036 | J61: =IFERROR(J50/$B50,0) -> 0.046312461 | ... N61: =IFERROR(N50/$B50,0) -> 0.016602918
A62: ES | B62: =SUM(C62:N62) -> 1 | C62: =IFERROR(C51/$B51,0) -> 0.36182732 | D62: =IFERROR(D51/$B51,0) -> 0.19784665 | E62: =IFERROR(E51/$B51,0) -> 0 | F62: =IFERROR(F51/$B51,0) -> 0 | G62: =IFERROR(G51/$B51,0) -> 0 | H62: =IFERROR(H51/$B51,0) -> 0.23986249 | I62: =IFERROR(I51/$B51,0) -> 0.053423538 | J62: =IFERROR(J51/$B51,0) -> 0.060154482 | ... N62: =IFERROR(N51/$B51,0) -> 0.021565253
A64: D. Mezcla de técnicas dentro de cada tipo de muestra
A65: Tipo | B65: HPLC | C65: GC | D65: PSA | E65: KF | F65: DSC | G65: XRPD
A66: MP | B66: =SUMIF($C$6:$N$6,B$65,$C58:$N58) -> 0.2690686 | C66: =SUMIF($C$6:$N$6,C$65,$C58:$N58) -> 0.44022841 | D66: =SUMIF($C$6:$N$6,D$65,$C58:$N58) -> 0.1750757 | E66: =SUMIF($C$6:$N$6,E$65,$C58:$N58) -> 0.054603718 | F66: =SUMIF($C$6:$N$6,F$65,$C58:$N58) -> 0.03888098 | G66: =SUMIF($C$6:$N$6,G$65,$C58:$N58) -> 0.022142584
A67: IN | B67: =SUMIF($C$6:$N$6,B$65,$C59:$N59) -> 0.42369022 | C67: =SUMIF($C$6:$N$6,C$65,$C59:$N59) -> 0.29605232 | D67: =SUMIF($C$6:$N$6,D$65,$C59:$N59) -> 0.14555472 | E67: =SUMIF($C$6:$N$6,E$65,$C59:$N59) -> 0.06255755 | F67: =SUMIF($C$6:$N$6,F$65,$C59:$N59) -> 0.018213082 | G67: =SUMIF($C$6:$N$6,G$65,$C59:$N59) -> 0.053932117
A68: GR | B68: =SUMIF($C$6:$N$6,B$65,$C60:$N60) -> 0.42496976 | C68: =SUMIF($C$6:$N$6,C$65,$C60:$N60) -> 0.19197484 | D68: =SUMIF($C$6:$N$6,D$65,$C60:$N60) -> 0.27651639 | E68: =SUMIF($C$6:$N$6,E$65,$C60:$N60) -> 0.040565382 | F68: =SUMIF($C$6:$N$6,F$65,$C60:$N60) -> 0.049598771 | G68: =SUMIF($C$6:$N$6,G$65,$C60:$N60) -> 0.016374856
A69: PT | B69: =SUMIF($C$6:$N$6,B$65,$C61:$N61) -> 0.43088857 | C69: =SUMIF($C$6:$N$6,C$65,$C61:$N61) -> 0.19464858 | D69: =SUMIF($C$6:$N$6,D$65,$C61:$N61) -> 0.18466824 | E69: =SUMIF($C$6:$N$6,E$65,$C61:$N61) -> 0.087442822 | F69: =SUMIF($C$6:$N$6,F$65,$C61:$N61) -> 0.050289562 | G69: =SUMIF($C$6:$N$6,G$65,$C61:$N61) -> 0.052062226
A70: ES | B70: =SUMIF($C$6:$N$6,B$65,$C62:$N62) -> 0.55967397 | C70: =SUMIF($C$6:$N$6,C$65,$C62:$N62) -> 0 | D70: =SUMIF($C$6:$N$6,D$65,$C62:$N62) -> 0.23986249 | E70: =SUMIF($C$6:$N$6,E$65,$C62:$N62) -> 0.11357802 | F70: =SUMIF($C$6:$N$6,F$65,$C62:$N62) -> 0.065320273 | G70: =SUMIF($C$6:$N$6,G$65,$C62:$N62) -> 0.021565253
A72: E. Chequeos
A73: Suma de las proporciones objetivo | B73: =SUM(B8:B12) -> 1 | C73: =IF(ABS(B73-1)<0.0001,"OK","Revisar: las proporciones deben sumar 100 %") -> OK
A74: Error del ajuste en la iteración 25 | B74: =X42 -> 6.6613381e-15 | C74: =IF(B74<0.000001,"OK","Revisar: la proporción de tipos no es compatible con la matriz de aplicación") -> OK
A75: Mayor diferencia en la participación de un método | B75: =MAX(C54:N54) -> 0 | C75: =IF(B75<0.000001,"OK","Revisar") -> OK
A76: Métodos que no aplican a ningún tipo | B76: =COUNTIF(C13:N13,0) -> 0 | C76: =IF(B76=0,"OK","Revisar: hay métodos sin tipo de muestra en la hoja Catálogo") -> OK
A77: Muestras por día hábil (escenario base) | B77: =SUM('Tipos de muestra'!O5:O9) -> 44.873731 | C77: ="Referencia: 30 a 40 trabajos por día (Cunha et al., 2019, pp. 1424–1425)" -> Referencia: 30 a 40 trabajos por día (Cunha et al., 2019, pp. 1424–1425)
A78: Ensayos por día hábil (escenario base) | B78: =B77*Demanda!$C$22 -> 53.848477 | C78: ="Referencia: 35 a 52 operaciones por día (Cunha et al., 2019, pp. 1424–1425)" -> Referencia: 35 a 52 operaciones por día (Cunha et al., 2019, pp. 1424–1425)
A79: Muestras por día de fin de semana (solo control en proceso) | B79: ='Tipos de muestra'!O6 -> 10.495205 | C79: =""

Sheet Equipos
A1: Equipos del laboratorio de referencia
A2: Una fila por configuración. Amarillo = decisión (cantidad y métodos que corre cada configuración); las horas, la sugerencia proporcional y la utilización se calculan.
A3: Total de 70 equipos de 6 tipos (Costigliola et al., 2017, p. 9015); al menos 22 HPLC (Fig. 5, p. 9018). Reparto: supuesto S21. Compatibilidad: supuesto S22. Utilización = horas de montaje y corrida ÷ horas del año (24 h × 365 días), sin la idoneidad del sistema.
A4: Código | B4: Técnica | C4: Configuración | D4: Equipos | E4: M01 | F4: M02 | G4: M03 | H4: M04 | I4: M05 | J4: M06 | K4: M07 | L4: M08 | M4: M09 | N4: M10 | O4: M11 | P4: M12 | Q4: Horas de equipo al año (base) | R4: Proporcional (sin mínimo) | S4: Sugerencia (mínimo 2) | T4: Diferencia con la sugerencia | U4: Utilización (base) | V4: Utilización (carga alta) | W4: Fuente o supuesto
A5: HPLC-G | B5: HPLC | C5: HPLC con gradiente y detector UV/DAD | D5: 15 | E5: X | F5: X | Q5: =SUMIF('Calibración de recursos'!$C$6:$C$17,A5,'Calibración de recursos'!$H$6:$H$17) -> 5113.9152 | R5: ='Calibración de recursos'!$B$22*Q5/SUM($Q$5:$Q$14) -> 15.9124 | S5: =IF(R5<2,2,('Calibración de recursos'!$B$22-2*COUNTIF($R$5:$R$14,"<2"))*Q5/(SUM($Q$5:$Q$14)-SUMIF($R$5:$R$14,"<2",$Q$5:$Q$14))) -> 15.227152 | T5: =D5-S5 -> -0.22715193 | U5: =IFERROR(Q5/(D5*24*Demanda!$B$14),"") -> 0.038918685 | V5: =IFERROR(U5*Demanda!$B$29,"") -> 0.058378028 | W5: Costigliola et al. (2017, p. 9015); reparto S21; compatibilidad S22.
A6: HPLC-I | B6: HPLC | C6: HPLC isocrático con detector UV | D6: 26 | E6: X | Q6: =SUMIF('Calibración de recursos'!$C$6:$C$17,A6,'Calibración de recursos'!$H$6:$H$17) -> 8571.652 | R6: ='Calibración de recursos'!$B$22*Q6/SUM($Q$5:$Q$14) -> 26.671454 | S6: =IF(R6<2,2,('Calibración de recursos'!$B$22-2*COUNTIF($R$5:$R$14,"<2"))*Q6/(SUM($Q$5:$Q$14)-SUMIF($R$5:$R$14,"<2",$Q$5:$Q$14))) -> 25.52288 | T6: =D6-S6 -> 0.4771196 | U6: =IFERROR(Q6/(D6*24*Demanda!$B$14),"") -> 0.03763458 | V6: =IFERROR(U6*Demanda!$B$29,"") -> 0.05645187 | W6: Costigliola et al. (2017, p. 9015); reparto S21; compatibilidad S22.
A7: GC-L | B7: GC | C7: GC con inyección líquida y FID | D7: 4 | G7: X | Q7: =SUMIF('Calibración de recursos'!$C$6:$C$17,A7,'Calibración de recursos'!$H$6:$H$17) -> 1188.8393 | R7: ='Calibración de recursos'!$B$22*Q7/SUM($Q$5:$Q$14) -> 3.6991788 | S7: =IF(R7<2,2,('Calibración de recursos'!$B$22-2*COUNTIF($R$5:$R$14,"<2"))*Q7/(SUM($Q$5:$Q$14)-SUMIF($R$5:$R$14,"<2",$Q$5:$Q$14))) -> 3.5398782 | T7: =D7-S7 -> 0.4601218 | U7: =IFERROR(Q7/(D7*24*Demanda!$B$14),"") -> 0.033928063 | V7: =IFERROR(U7*Demanda!$B$29,"") -> 0.050892094 | W7: Costigliola et al. (2017, p. 9015); reparto S21; compatibilidad S22.
A8: GC-H | B8: GC | C8: GC con espacio de cabeza y FID | D8: 11 | H8: X | Q8: =SUMIF('Calibración de recursos'!$C$6:$C$17,A8,'Calibración de recursos'!$H$6:$H$17) -> 3689.9187 | R8: ='Calibración de recursos'!$B$22*Q8/SUM($Q$5:$Q$14) -> 11.481509 | S8: =IF(R8<2,2,('Calibración de recursos'!$B$22-2*COUNTIF($R$5:$R$14,"<2"))*Q8/(SUM($Q$5:$Q$14)-SUMIF($R$5:$R$14,"<2",$Q$5:$Q$14))) -> 10.987072 | T8: =D8-S8 -> 0.012928285 | U8: =IFERROR(Q8/(D8*24*Demanda!$B$14),"") -> 0.038293055 | V8: =IFERROR(U8*Demanda!$B$29,"") -> 0.057439582 | W8: Costigliola et al. (2017, p. 9015); reparto S21; compatibilidad S22.
A9: PSA-S | B9: PSA | C9: Difracción láser, módulo seco | D9: 2 | I9: X | Q9: =SUMIF('Calibración de recursos'!$C$6:$C$17,A9,'Calibración de recursos'!$H$6:$H$17) -> 452.65711 | R9: ='Calibración de recursos'!$B$22*Q9/SUM($Q$5:$Q$14) -> 1.4084827 | S9: =IF(R9<2,2,('Calibración de recursos'!$B$22-2*COUNTIF($R$5:$R$14,"<2"))*Q9/(SUM($Q$5:$Q$14)-SUMIF($R$5:$R$14,"<2",$Q$5:$Q$14))) -> 2 | T9: =D9-S9 -> 0 | U9: =IFERROR(Q9/(D9*24*Demanda!$B$14),"") -> 0.025836593 | V9: =IFERROR(U9*Demanda!$B$29,"") -> 0.03875489 | W9: Costigliola et al. (2017, p. 9015); reparto S21; compatibilidad S22.
A10: PSA-H | B10: PSA | C10: Difracción láser, módulo húmedo | D10: 3 | J10: X | Q10: =SUMIF('Calibración de recursos'!$C$6:$C$17,A10,'Calibración de recursos'!$H$6:$H$17) -> 1059.723 | R10: ='Calibración de recursos'!$B$22*Q10/SUM($Q$5:$Q$14) -> 3.2974219 | S10: =IF(R10<2,2,('Calibración de recursos'!$B$22-2*COUNTIF($R$5:$R$14,"<2"))*Q10/(SUM($Q$5:$Q$14)-SUMIF($R$5:$R$14,"<2",$Q$5:$Q$14))) -> 3.1554224 | T10: =D10-S10 -> -0.15542245 | U10: =IFERROR(Q10/(D10*24*Demanda!$B$14),"") -> 0.040324315 | V10: =IFERROR(U10*Demanda!$B$29,"") -> 0.060486472 | W10: Costigliola et al. (2017, p. 9015); reparto S21; compatibilidad S22.
A11: KF-V | B11: KF | C11: Titulador KF volumétrico | D11: 2 | K11: X | Q11: =SUMIF('Calibración de recursos'!$C$6:$C$17,A11,'Calibración de recursos'!$H$6:$H$17) -> 260.94815 | R11: ='Calibración de recursos'!$B$22*Q11/SUM($Q$5:$Q$14) -> 0.81196329 | S11: =IF(R11<2,2,('Calibración de recursos'!$B$22-2*COUNTIF($R$5:$R$14,"<2"))*Q11/(SUM($Q$5:$Q$14)-SUMIF($R$5:$R$14,"<2",$Q$5:$Q$14))) -> 2 | T11: =D11-S11 -> 0 | U11: =IFERROR(Q11/(D11*24*Demanda!$B$14),"") -> 0.014894301 | V11: =IFERROR(U11*Demanda!$B$29,"") -> 0.022341451 | W11: Costigliola et al. (2017, p. 9015); reparto S21; compatibilidad S22.
A12: KF-C | B12: KF | C12: Titulador KF coulométrico con horno | D12: 2 | L12: X | Q12: =SUMIF('Calibración de recursos'!$C$6:$C$17,A12,'Calibración de recursos'!$H$6:$H$17) -> 289.06242 | R12: ='Calibración de recursos'!$B$22*Q12/SUM($Q$5:$Q$14) -> 0.89944331 | S12: =IF(R12<2,2,('Calibración de recursos'!$B$22-2*COUNTIF($R$5:$R$14,"<2"))*Q12/(SUM($Q$5:$Q$14)-SUMIF($R$5:$R$14,"<2",$Q$5:$Q$14))) -> 2 | T12: =D12-S12 -> 0 | U12: =IFERROR(Q12/(D12*24*Demanda!$B$14),"") -> 0.016498997 | V12: =IFERROR(U12*Demanda!$B$29,"") -> 0.024748495 | W12: Costigliola et al. (2017, p. 9015); reparto S21; compatibilidad S22.
A13: DSC | B13: DSC | C13: Calorímetro diferencial de barrido | D13: 3 | M13: X | N13: X | Q13: =SUMIF('Calibración de recursos'!$C$6:$C$17,A13,'Calibración de recursos'!$H$6:$H$17) -> 1035.1538 | R13: ='Calibración de recursos'!$B$22*Q13/SUM($Q$5:$Q$14) -> 3.2209726 | S13: =IF(R13<2,2,('Calibración de recursos'!$B$22-2*COUNTIF($R$5:$R$14,"<2"))*Q13/(SUM($Q$5:$Q$14)-SUMIF($R$5:$R$14,"<2",$Q$5:$Q$14))) -> 3.0822654 | T13: =D13-S13 -> -0.082265376 | U13: =IFERROR(Q13/(D13*24*Demanda!$B$14),"") -> 0.039389413 | V13: =IFERROR(U13*Demanda!$B$29,"") -> 0.05908412 | W13: Costigliola et al. (2017, p. 9015); reparto S21; compatibilidad S22.
A14: XRPD | B14: XRPD | C14: Difractómetro de rayos X de polvo | D14: 2 | O14: X | P14: X | Q14: =SUMIF('Calibración de recursos'!$C$6:$C$17,A14,'Calibración de recursos'!$H$6:$H$17) -> 834.67786 | R14: ='Calibración de recursos'!$B$22*Q14/SUM($Q$5:$Q$14) -> 2.5971741 | S14: =IF(R14<2,2,('Calibración de recursos'!$B$22-2*COUNTIF($R$5:$R$14,"<2"))*Q14/(SUM($Q$5:$Q$14)-SUMIF($R$5:$R$14,"<2",$Q$5:$Q$14))) -> 2.4853299 | T14: =D14-S14 -> -0.48532993 | U14: =IFERROR(Q14/(D14*24*Demanda!$B$14),"") -> 0.04764143 | V14: =IFERROR(U14*Demanda!$B$29,"") -> 0.071462146 | W14: Costigliola et al. (2017, p. 9015); reparto S21; compatibilidad S22.

Sheet Analistas
A1: Analistas del laboratorio de referencia
A2: Una fila por analista. Amarillo = decisión (nivel y área); la matriz de calificación (columnas M01 a M12, 1 = calificado) se calcula con la regla de la hoja Calibración de recursos.
A3: 20 analistas en 3 turnos: 6 en el turno 1, 4 en el turno 2 y 10 en el turno 3 (Costigliola et al., 2017, Tabla 1, p. 9015). Nivel: supuesto S19. Área: supuesto S20. Calificado = nivel ≥ nivel mínimo del método (S12) y técnica dentro del área del analista.
A4: ID | B4: Turno | C4: Nivel | D4: Área | E4: Factor de duración | F4: M01 | G4: M02 | H4: M03 | I4: M04 | J4: M05 | K4: M06 | L4: M07 | M4: M08 | N4: M09 | O4: M10 | P4: M11 | Q4: M12 | R4: Métodos calificados | S4: Fuente o supuesto
A5: A01 | B5: T1 | C5: sénior | D5: Todas | E5: =INDEX('Calibración de recursos'!$C$31:$C$33,MATCH(C5,'Calibración de recursos'!$A$31:$A$33,0)) -> 0.9 | F5: =IF(AND(MATCH($C5,'Calibración de recursos'!$A$31:$A$33,0)>='Calibración de recursos'!B$44,INDEX('Calibración de recursos'!$B$37:$G$39,MATCH($D5,'Calibración de recursos'!$A$37:$A$39,0),MATCH('Calibración de recursos'!B$43,'Calibración de recursos'!$B$36:$G$36,0))=1),1,0) -> 1 | G5: =IF(AND(MATCH($C5,'Calibración de recursos'!$A$31:$A$33,0)>='Calibración de recursos'!C$44,INDEX('Calibración de recursos'!$B$37:$G$39,MATCH($D5,'Calibración de recursos'!$A$37:$A$39,0),MATCH('Calibración de recursos'!C$43,'Calibración de recursos'!$B$36:$G$36,0))=1),1,0) -> 1 | H5: =IF(AND(MATCH($C5,'Calibración de recursos'!$A$31:$A$33,0)>='Calibración de recursos'!D$44,INDEX('Calibración de recursos'!$B$37:$G$39,MATCH($D5,'Calibración de recursos'!$A$37:$A$39,0),MATCH('Calibración de recursos'!D$43,'Calibración de recursos'!$B$36:$G$36,0))=1),1,0) -> 1 | I5: =IF(AND(MATCH($C5,'Calibración de recursos'!$A$31:$A$33,0)>='Calibración de recursos'!E$44,INDEX('Calibración de recursos'!$B$37:$G$39,MATCH($D5,'Calibración de recursos'!$A$37:$A$39,0),MATCH('Calibración de recursos'!E$43,'Calibración de recursos'!$B$36:$G$36,0))=1),1,0) -> 1 | J5: =IF(AND(MATCH($C5,'Calibración de recursos'!$A$31:$A$33,0)>='Calibración de recursos'!F$44,INDEX('Calibración de recursos'!$B$37:$G$39,MATCH($D5,'Calibración de recursos'!$A$37:$A$39,0),MATCH('Calibración de recursos'!F$43,'Calibración de recursos'!$B$36:$G$36,0))=1),1,0) -> 1 | K5: =IF(AND(MATCH($C5,'Calibración de recursos'!$A$31:$A$33,0)>='Calibración de recursos'!G$44,INDEX('Calibración de recursos'!$B$37:$G$39,MATCH($D5,'Calibración de recursos'!$A$37:$A$39,0),MATCH('Calibración de recursos'!G$43,'Calibración de recursos'!$B$36:$G$36,0))=1),1,0) -> 1 | L5: =IF(AND(MATCH($C5,'Calibración de recursos'!$A$31:$A$33,0)>='Calibración de recursos'!H$44,INDEX('Calibración de recursos'!$B$37:$G$39,MATCH($D5,'Calibración de recursos'!$A$37:$A$39,0),MATCH('Calibración de recursos'!H$43,'Calibración de recursos'!$B$36:$G$36,0))=1),1,0) -> 1 | M5: =IF(AND(MATCH($C5,'Calibración de recursos'!$A$31:$A$33,0)>='Calibración de recursos'!I$44,INDEX('Calibración de recursos'!$B$37:$G$39,MATCH($D5,'Calibración de recursos'!$A$37:$A$39,0),MATCH('Calibración de recursos'!I$43,'Calibración de recursos'!$B$36:$G$36,0))=1),1,0) -> 1 | ... Q5: =IF(AND(MATCH($C5,'Calibración de recursos'!$A$31:$A$33,0)>='Calibración de recursos'!M$44,INDEX('Calibración de recursos'!$B$37:$G$39,MATCH($D5,'Calibración de recursos'!$A$37:$A$39,0),MATCH('Calibración de recursos'!M$43,'Calibración de recursos'!$B$36:$G$36,0))=1),1,0) -> 1 | R5: =SUM(F5:Q5) -> 12 | S5: Turno: Tabla 1 de Costigliola et al. (2017). Nivel: S19. Área: S20.
A6: A02 | B6: T1 | C6: sénior | D6: Todas | E6: =INDEX('Calibración de recursos'!$C$31:$C$33,MATCH(C6,'Calibración de recursos'!$A$31:$A$33,0)) -> 0.9 | F6: =IF(AND(MATCH($C6,'Calibración de recursos'!$A$31:$A$33,0)>='Calibración de recursos'!B$44,INDEX('Calibración de recursos'!$B$37:$G$39,MATCH($D6,'Calibración de recursos'!$A$37:$A$39,0),MATCH('Calibración de recursos'!B$43,'Calibración de recursos'!$B$36:$G$36,0))=1),1,0) -> 1 | G6: =IF(AND(MATCH($C6,'Calibración de recursos'!$A$31:$A$33,0)>='Calibración de recursos'!C$44,INDEX('Calibración de recursos'!$B$37:$G$39,MATCH($D6,'Calibración de recursos'!$A$37:$A$39,0),MATCH('Calibración de recursos'!C$43,'Calibración de recursos'!$B$36:$G$36,0))=1),1,0) -> 1 | H6: =IF(AND(MATCH($C6,'Calibración de recursos'!$A$31:$A$33,0)>='Calibración de recursos'!D$44,INDEX('Calibración de recursos'!$B$37:$G$39,MATCH($D6,'Calibración de recursos'!$A$37:$A$39,0),MATCH('Calibración de recursos'!D$43,'Calibración de recursos'!$B$36:$G$36,0))=1),1,0) -> 1 | I6: =IF(AND(MATCH($C6,'Calibración de recursos'!$A$31:$A$33,0)>='Calibración de recursos'!E$44,INDEX('Calibración de recursos'!$B$37:$G$39,MATCH($D6,'Calibración de recursos'!$A$37:$A$39,0),MATCH('Calibración de recursos'!E$43,'Calibración de recursos'!$B$36:$G$36,0))=1),1,0) -> 1 | J6: =IF(AND(MATCH($C6,'Calibración de recursos'!$A$31:$A$33,0)>='Calibración de recursos'!F$44,INDEX('Calibración de recursos'!$B$37:$G$39,MATCH($D6,'Calibración de recursos'!$A$37:$A$39,0),MATCH('Calibración de recursos'!F$43,'Calibración de recursos'!$B$36:$G$36,0))=1),1,0) -> 1 | K6: =IF(AND(MATCH($C6,'Calibración de recursos'!$A$31:$A$33,0)>='Calibración de recursos'!G$44,INDEX('Calibración de recursos'!$B$37:$G$39,MATCH($D6,'Calibración de recursos'!$A$37:$A$39,0),MATCH('Calibración de recursos'!G$43,'Calibración de recursos'!$B$36:$G$36,0))=1),1,0) -> 1 | L6: =IF(AND(MATCH($C6,'Calibración de recursos'!$A$31:$A$33,0)>='Calibración de recursos'!H$44,INDEX('Calibración de recursos'!$B$37:$G$39,MATCH($D6,'Calibración de recursos'!$A$37:$A$39,0),MATCH('Calibración de recursos'!H$43,'Calibración de recursos'!$B$36:$G$36,0))=1),1,0) -> 1 | M6: =IF(AND(MATCH($C6,'Calibración de recursos'!$A$31:$A$33,0)>='Calibración de recursos'!I$44,INDEX('Calibración de recursos'!$B$37:$G$39,MATCH($D6,'Calibración de recursos'!$A$37:$A$39,0),MATCH('Calibración de recursos'!I$43,'Calibración de recursos'!$B$36:$G$36,0))=1),1,0) -> 1 | ... Q6: =IF(AND(MATCH($C6,'Calibración de recursos'!$A$31:$A$33,0)>='Calibración de recursos'!M$44,INDEX('Calibración de recursos'!$B$37:$G$39,MATCH($D6,'Calibración de recursos'!$A$37:$A$39,0),MATCH('Calibración de recursos'!M$43,'Calibración de recursos'!$B$36:$G$36,0))=1),1,0) -> 1 | R6: =SUM(F6:Q6) -> 12 | S6: Turno: Tabla 1 de Costigliola et al. (2017). Nivel: S19. Área: S20.
A7: A03 | B7: T1 | C7: intermedio | D7: Todas | E7: =INDEX('Calibración de recursos'!$C$31:$C$33,MATCH(C7,'Calibración de recursos'!$A$31:$A$33,0)) -> 1 | F7: =IF(AND(MATCH($C7,'Calibración de recursos'!$A$31:$A$33,0)>='Calibración de recursos'!B$44,INDEX('Calibración de recursos'!$B$37:$G$39,MATCH($D7,'Calibración de recursos'!$A$37:$A$39,0),MATCH('Calibración de recursos'!B$43,'Calibración de recursos'!$B$36:$G$36,0))=1),1,0) -> 1 | G7: =IF(AND(MATCH($C7,'Calibración de recursos'!$A$31:$A$33,0)>='Calibración de recursos'!C$44,INDEX('Calibración de recursos'!$B$37:$G$39,MATCH($D7,'Calibración de recursos'!$A$37:$A$39,0),MATCH('Calibración de recursos'!C$43,'Calibración de recursos'!$B$36:$G$36,0))=1),1,0) -> 1 | H7: =IF(AND(MATCH($C7,'Calibración de recursos'!$A$31:$A$33,0)>='Calibración de recursos'!D$44,INDEX('Calibración de recursos'!$B$37:$G$39,MATCH($D7,'Calibración de recursos'!$A$37:$A$39,0),MATCH('Calibración de recursos'!D$43,'Calibración de recursos'!$B$36:$G$36,0))=1),1,0) -> 1 | I7: =IF(AND(MATCH($C7,'Calibración de recursos'!$A$31:$A$33,0)>='Calibración de recursos'!E$44,INDEX('Calibración de recursos'!$B$37:$G$39,MATCH($D7,'Calibración de recursos'!$A$37:$A$39,0),MATCH('Calibración de recursos'!E$43,'Calibración de recursos'!$B$36:$G$36,0))=1),1,0) -> 1 | J7: =IF(AND(MATCH($C7,'Calibración de recursos'!$A$31:$A$33,0)>='Calibración de recursos'!F$44,INDEX('Calibración de recursos'!$B$37:$G$39,MATCH($D7,'Calibración de recursos'!$A$37:$A$39,0),MATCH('Calibración de recursos'!F$43,'Calibración de recursos'!$B$36:$G$36,0))=1),1,0) -> 1 | K7: =IF(AND(MATCH($C7,'Calibración de recursos'!$A$31:$A$33,0)>='Calibración de recursos'!G$44,INDEX('Calibración de recursos'!$B$37:$G$39,MATCH($D7,'Calibración de recursos'!$A$37:$A$39,0),MATCH('Calibración de recursos'!G$43,'Calibración de recursos'!$B$36:$G$36,0))=1),1,0) -> 1 | L7: =IF(AND(MATCH($C7,'Calibración de recursos'!$A$31:$A$33,0)>='Calibración de recursos'!H$44,INDEX('Calibración de recursos'!$B$37:$G$39,MATCH($D7,'Calibración de recursos'!$A$37:$A$39,0),MATCH('Calibración de recursos'!H$43,'Calibración de recursos'!$B$36:$G$36,0))=1),1,0) -> 1 | M7: =IF(AND(MATCH($C7,'Calibración de recursos'!$A$31:$A$33,0)>='Calibración de recursos'!I$44,INDEX('Calibración de recursos'!$B$37:$G$39,MATCH($D7,'Calibración de recursos'!$A$37:$A$39,0),MATCH('Calibración de recursos'!I$43,'Calibración de recursos'!$B$36:$G$36,0))=1),1,0) -> 0 | ... Q7: =IF(AND(MATCH($C7,'Calibración de recursos'!$A$31:$A$33,0)>='Calibración de recursos'!M$44,INDEX('Calibración de recursos'!$B$37:$G$39,MATCH($D7,'Calibración de recursos'!$A$37:$A$39,0),MATCH('Calibración de recursos'!M$43,'Calibración de recursos'!$B$36:$G$36,0))=1),1,0) -> 0 | R7: =SUM(F7:Q7) -> 10 | S7: Turno: Tabla 1 de Costigliola et al. (2017). Nivel: S19. Área: S20.
A8: A04 | B8: T1 | C8: intermedio | D8: Todas | E8: =INDEX('Calibración de recursos'!$C$31:$C$33,MATCH(C8,'Calibración de recursos'!$A$31:$A$33,0)) -> 1 | F8: =IF(AND(MATCH($C8,'Calibración de recursos'!$A$31:$A$33,0)>='Calibración de recursos'!B$44,INDEX('Calibración de recursos'!$B$37:$G$39,MATCH($D8,'Calibración de recursos'!$A$37:$A$39,0),MATCH('Calibración de recursos'!B$43,'Calibración de recursos'!$B$36:$G$36,0))=1),1,0) -> 1 | G8: =IF(AND(MATCH($C8,'Calibración de recursos'!$A$31:$A$33,0)>='Calibración de recursos'!C$44,INDEX('Calibración de recursos'!$B$37:$G$39,MATCH($D8,'Calibración de recursos'!$A$37:$A$39,0),MATCH('Calibración de recursos'!C$43,'Calibración de recursos'!$B$36:$G$36,0))=1),1,0) -> 1 | H8: =IF(AND(MATCH($C8,'Calibración de recursos'!$A$31:$A$33,0)>='Calibración de recursos'!D$44,INDEX('Calibración de recursos'!$B$37:$G$39,MATCH($D8,'Calibración de recursos'!$A$37:$A$39,0),MATCH('Calibración de recursos'!D$43,'Calibración de recursos'!$B$36:$G$36,0))=1),1,0) -> 1 | I8: =IF(AND(MATCH($C8,'Calibración de recursos'!$A$31:$A$33,0)>='Calibración de recursos'!E$44,INDEX('Calibración de recursos'!$B$37:$G$39,MATCH($D8,'Calibración de recursos'!$A$37:$A$39,0),MATCH('Calibración de recursos'!E$43,'Calibración de recursos'!$B$36:$G$36,0))=1),1,0) -> 1 | J8: =IF(AND(MATCH($C8,'Calibración de recursos'!$A$31:$A$33,0)>='Calibración de recursos'!F$44,INDEX('Calibración de recursos'!$B$37:$G$39,MATCH($D8,'Calibración de recursos'!$A$37:$A$39,0),MATCH('Calibración de recursos'!F$43,'Calibración de recursos'!$B$36:$G$36,0))=1),1,0) -> 1 | K8: =IF(AND(MATCH($C8,'Calibración de recursos'!$A$31:$A$33,0)>='Calibración de recursos'!G$44,INDEX('Calibración de recursos'!$B$37:$G$39,MATCH($D8,'Calibración de recursos'!$A$37:$A$39,0),MATCH('Calibración de recursos'!G$43,'Calibración de recursos'!$B$36:$G$36,0))=1),1,0) -> 1 | L8: =IF(AND(MATCH($C8,'Calibración de recursos'!$A$31:$A$33,0)>='Calibración de recursos'!H$44,INDEX('Calibración de recursos'!$B$37:$G$39,MATCH($D8,'Calibración de recursos'!$A$37:$A$39,0),MATCH('Calibración de recursos'!H$43,'Calibración de recursos'!$B$36:$G$36,0))=1),1,0) -> 1 | M8: =IF(AND(MATCH($C8,'Calibración de recursos'!$A$31:$A$33,0)>='Calibración de recursos'!I$44,INDEX('Calibración de recursos'!$B$37:$G$39,MATCH($D8,'Calibración de recursos'!$A$37:$A$39,0),MATCH('Calibración de recursos'!I$43,'Calibración de recursos'!$B$36:$G$36,0))=1),1,0) -> 0 | ... Q8: =IF(AND(MATCH($C8,'Calibración de recursos'!$A$31:$A$33,0)>='Calibración de recursos'!M$44,INDEX('Calibración de recursos'!$B$37:$G$39,MATCH($D8,'Calibración de recursos'!$A$37:$A$39,0),MATCH('Calibración de recursos'!M$43,'Calibración de recursos'!$B$36:$G$36,0))=1),1,0) -> 0 | R8: =SUM(F8:Q8) -> 10 | S8: Turno: Tabla 1 de Costigliola et al. (2017). Nivel: S19. Área: S20.
A9: A05 | B9: T1 | C9: intermedio | D9: Todas | E9: =INDEX('Calibración de recursos'!$C$31:$C$33,MATCH(C9,'Calibración de recursos'!$A$31:$A$33,0)) -> 1 | F9: =IF(AND(MATCH($C9,'Calibración de recursos'!$A$31:$A$33,0)>='Calibración de recursos'!B$44,INDEX('Calibración de recursos'!$B$37:$G$39,MATCH($D9,'Calibración de recursos'!$A$37:$A$39,0),MATCH('Calibración de recursos'!B$43,'Calibración de recursos'!$B$36:$G$36,0))=1),1,0) -> 1 | G9: =IF(AND(MATCH($C9,'Calibración de recursos'!$A$31:$A$33,0)>='Calibración de recursos'!C$44,INDEX('Calibración de recursos'!$B$37:$G$39,MATCH($D9,'Calibración de recursos'!$A$37:$A$39,0),MATCH('Calibración de recursos'!C$43,'Calibración de recursos'!$B$36:$G$36,0))=1),1,0) -> 1 | H9: =IF(AND(MATCH($C9,'Calibración de recursos'!$A$31:$A$33,0)>='Calibración de recursos'!D$44,INDEX('Calibración de recursos'!$B$37:$G$39,MATCH($D9,'Calibración de recursos'!$A$37:$A$39,0),MATCH('Calibración de recursos'!D$43,'Calibración de recursos'!$B$36:$G$36,0))=1),1,0) -> 1 | I9: =IF(AND(MATCH($C9,'Calibración de recursos'!$A$31:$A$33,0)>='Calibración de recursos'!E$44,INDEX('Calibración de recursos'!$B$37:$G$39,MATCH($D9,'Calibración de recursos'!$A$37:$A$39,0),MATCH('Calibración de recursos'!E$43,'Calibración de recursos'!$B$36:$G$36,0))=1),1,0) -> 1 | J9: =IF(AND(MATCH($C9,'Calibración de recursos'!$A$31:$A$33,0)>='Calibración de recursos'!F$44,INDEX('Calibración de recursos'!$B$37:$G$39,MATCH($D9,'Calibración de recursos'!$A$37:$A$39,0),MATCH('Calibración de recursos'!F$43,'Calibración de recursos'!$B$36:$G$36,0))=1),1,0) -> 1 | K9: =IF(AND(MATCH($C9,'Calibración de recursos'!$A$31:$A$33,0)>='Calibración de recursos'!G$44,INDEX('Calibración de recursos'!$B$37:$G$39,MATCH($D9,'Calibración de recursos'!$A$37:$A$39,0),MATCH('Calibración de recursos'!G$43,'Calibración de recursos'!$B$36:$G$36,0))=1),1,0) -> 1 | L9: =IF(AND(MATCH($C9,'Calibración de recursos'!$A$31:$A$33,0)>='Calibración de recursos'!H$44,INDEX('Calibración de recursos'!$B$37:$G$39,MATCH($D9,'Calibración de recursos'!$A$37:$A$39,0),MATCH('Calibración de recursos'!H$43,'Calibración de recursos'!$B$36:$G$36,0))=1),1,0) -> 1 | M9: =IF(AND(MATCH($C9,'Calibración de recursos'!$A$31:$A$33,0)>='Calibración de recursos'!I$44,INDEX('Calibración de recursos'!$B$37:$G$39,MATCH($D9,'Calibración de recursos'!$A$37:$A$39,0),MATCH('Calibración de recursos'!I$43,'Calibración de recursos'!$B$36:$G$36,0))=1),1,0) -> 0 | ... Q9: =IF(AND(MATCH($C9,'Calibración de recursos'!$A$31:$A$33,0)>='Calibración de recursos'!M$44,INDEX('Calibración de recursos'!$B$37:$G$39,MATCH($D9,'Calibración de recursos'!$A$37:$A$39,0),MATCH('Calibración de recursos'!M$43,'Calibración de recursos'!$B$36:$G$36,0))=1),1,0) -> 0 | R9: =SUM(F9:Q9) -> 10 | S9: Turno: Tabla 1 de Costigliola et al. (2017). Nivel: S19. Área: S20.
A10: A06 | B10: T1 | C10: intermedio | D10: Todas | E10: =INDEX('Calibración de recursos'!$C$31:$C$33,MATCH(C10,'Calibración de recursos'!$A$31:$A$33,0)) -> 1 | F10: =IF(AND(MATCH($C10,'Calibración de recursos'!$A$31:$A$33,0)>='Calibración de recursos'!B$44,INDEX('Calibración de recursos'!$B$37:$G$39,MATCH($D10,'Calibración de recursos'!$A$37:$A$39,0),MATCH('Calibración de recursos'!B$43,'Calibración de recursos'!$B$36:$G$36,0))=1),1,0) -> 1 | G10: =IF(AND(MATCH($C10,'Calibración de recursos'!$A$31:$A$33,0)>='Calibración de recursos'!C$44,INDEX('Calibración de recursos'!$B$37:$G$39,MATCH($D10,'Calibración de recursos'!$A$37:$A$39,0),MATCH('Calibración de recursos'!C$43,'Calibración de recursos'!$B$36:$G$36,0))=1),1,0) -> 1 | H10: =IF(AND(MATCH($C10,'Calibración de recursos'!$A$31:$A$33,0)>='Calibración de recursos'!D$44,INDEX('Calibración de recursos'!$B$37:$G$39,MATCH($D10,'Calibración de recursos'!$A$37:$A$39,0),MATCH('Calibración de recursos'!D$43,'Calibración de recursos'!$B$36:$G$36,0))=1),1,0) -> 1 | I10: =IF(AND(MATCH($C10,'Calibración de recursos'!$A$31:$A$33,0)>='Calibración de recursos'!E$44,INDEX('Calibración de recursos'!$B$37:$G$39,MATCH($D10,'Calibración de recursos'!$A$37:$A$39,0),MATCH('Calibración de recursos'!E$43,'Calibración de recursos'!$B$36:$G$36,0))=1),1,0) -> 1 | J10: =IF(AND(MATCH($C10,'Calibración de recursos'!$A$31:$A$33,0)>='Calibración de recursos'!F$44,INDEX('Calibración de recursos'!$B$37:$G$39,MATCH($D10,'Calibración de recursos'!$A$37:$A$39,0),MATCH('Calibración de recursos'!F$43,'Calibración de recursos'!$B$36:$G$36,0))=1),1,0) -> 1 | K10: =IF(AND(MATCH($C10,'Calibración de recursos'!$A$31:$A$33,0)>='Calibración de recursos'!G$44,INDEX('Calibración de recursos'!$B$37:$G$39,MATCH($D10,'Calibración de recursos'!$A$37:$A$39,0),MATCH('Calibración de recursos'!G$43,'Calibración de recursos'!$B$36:$G$36,0))=1),1,0) -> 1 | L10: =IF(AND(MATCH($C10,'Calibración de recursos'!$A$31:$A$33,0)>='Calibración de recursos'!H$44,INDEX('Calibración de recursos'!$B$37:$G$39,MATCH($D10,'Calibración de recursos'!$A$37:$A$39,0),MATCH('Calibración de recursos'!H$43,'Calibración de recursos'!$B$36:$G$36,0))=1),1,0) -> 1 | M10: =IF(AND(MATCH($C10,'Calibración de recursos'!$A$31:$A$33,0)>='Calibración de recursos'!I$44,INDEX('Calibración de recursos'!$B$37:$G$39,MATCH($D10,'Calibración de recursos'!$A$37:$A$39,0),MATCH('Calibración de recursos'!I$43,'Calibración de recursos'!$B$36:$G$36,0))=1),1,0) -> 0 | ... Q10: =IF(AND(MATCH($C10,'Calibración de recursos'!$A$31:$A$33,0)>='Calibración de recursos'!M$44,INDEX('Calibración de recursos'!$B$37:$G$39,MATCH($D10,'Calibración de recursos'!$A$37:$A$39,0),MATCH('Calibración de recursos'!M$43,'Calibración de recursos'!$B$36:$G$36,0))=1),1,0) -> 0 | R10: =SUM(F10:Q10) -> 10 | S10: Turno: Tabla 1 de Costigliola et al. (2017). Nivel: S19. Área: S20.
A11: A07 | B11: T2 | C11: sénior | D11: Cromatografía | E11: =INDEX('Calibración de recursos'!$C$31:$C$33,MATCH(C11,'Calibración de recursos'!$A$31:$A$33,0)) -> 0.9 | F11: =IF(AND(MATCH($C11,'Calibración de recursos'!$A$31:$A$33,0)>='Calibración de recursos'!B$44,INDEX('Calibración de recursos'!$B$37:$G$39,MATCH($D11,'Calibración de recursos'!$A$37:$A$39,0),MATCH('Calibración de recursos'!B$43,'Calibración de recursos'!$B$36:$G$36,0))=1),1,0) -> 1 | G11: =IF(AND(MATCH($C11,'Calibración de recursos'!$A$31:$A$33,0)>='Calibración de recursos'!C$44,INDEX('Calibración de recursos'!$B$37:$G$39,MATCH($D11,'Calibración de recursos'!$A$37:$A$39,0),MATCH('Calibración de recursos'!C$43,'Calibración de recursos'!$B$36:$G$36,0))=1),1,0) -> 1 | H11: =IF(AND(MATCH($C11,'Calibración de recursos'!$A$31:$A$33,0)>='Calibración de recursos'!D$44,INDEX('Calibración de recursos'!$B$37:$G$39,MATCH($D11,'Calibración de recursos'!$A$37:$A$39,0),MATCH('Calibración de recursos'!D$43,'Calibración de recursos'!$B$36:$G$36,0))=1),1,0) -> 1 | I11: =IF(AND(MATCH($C11,'Calibración de recursos'!$A$31:$A$33,0)>='Calibración de recursos'!E$44,INDEX('Calibración de recursos'!$B$37:$G$39,MATCH($D11,'Calibración de recursos'!$A$37:$A$39,0),MATCH('Calibración de recursos'!E$43,'Calibración de recursos'!$B$36:$G$36,0))=1),1,0) -> 1 | J11: =IF(AND(MATCH($C11,'Calibración de recursos'!$A$31:$A$33,0)>='Calibración de recursos'!F$44,INDEX('Calibración de recursos'!$B$37:$G$39,MATCH($D11,'Calibración de recursos'!$A$37:$A$39,0),MATCH('Calibración de recursos'!F$43,'Calibración de recursos'!$B$36:$G$36,0))=1),1,0) -> 0 | K11: =IF(AND(MATCH($C11,'Calibración de recursos'!$A$31:$A$33,0)>='Calibración de recursos'!G$44,INDEX('Calibración de recursos'!$B$37:$G$39,MATCH($D11,'Calibración de recursos'!$A$37:$A$39,0),MATCH('Calibración de recursos'!G$43,'Calibración de recursos'!$B$36:$G$36,0))=1),1,0) -> 0 | L11: =IF(AND(MATCH($C11,'Calibración de recursos'!$A$31:$A$33,0)>='Calibración de recursos'!H$44,INDEX('Calibración de recursos'!$B$37:$G$39,MATCH($D11,'Calibración de recursos'!$A$37:$A$39,0),MATCH('Calibración de recursos'!H$43,'Calibración de recursos'!$B$36:$G$36,0))=1),1,0) -> 0 | M11: =IF(AND(MATCH($C11,'Calibración de recursos'!$A$31:$A$33,0)>='Calibración de recursos'!I$44,INDEX('Calibración de recursos'!$B$37:$G$39,MATCH($D11,'Calibración de recursos'!$A$37:$A$39,0),MATCH('Calibración de recursos'!I$43,'Calibración de recursos'!$B$36:$G$36,0))=1),1,0) -> 0 | ... Q11: =IF(AND(MATCH($C11,'Calibración de recursos'!$A$31:$A$33,0)>='Calibración de recursos'!M$44,INDEX('Calibración de recursos'!$B$37:$G$39,MATCH($D11,'Calibración de recursos'!$A$37:$A$39,0),MATCH('Calibración de recursos'!M$43,'Calibración de recursos'!$B$36:$G$36,0))=1),1,0) -> 0 | R11: =SUM(F11:Q11) -> 4 | S11: Turno: Tabla 1 de Costigliola et al. (2017). Nivel: S19. Área: S20.
A12: A08 | B12: T2 | C12: intermedio | D12: Cromatografía | E12: =INDEX('Calibración de recursos'!$C$31:$C$33,MATCH(C12,'Calibración de recursos'!$A$31:$A$33,0)) -> 1 | F12: =IF(AND(MATCH($C12,'Calibración de recursos'!$A$31:$A$33,0)>='Calibración de recursos'!B$44,INDEX('Calibración de recursos'!$B$37:$G$39,MATCH($D12,'Calibración de recursos'!$A$37:$A$39,0),MATCH('Calibración de recursos'!B$43,'Calibración de recursos'!$B$36:$G$36,0))=1),1,0) -> 1 | G12: =IF(AND(MATCH($C12,'Calibración de recursos'!$A$31:$A$33,0)>='Calibración de recursos'!C$44,INDEX('Calibración de recursos'!$B$37:$G$39,MATCH($D12,'Calibración de recursos'!$A$37:$A$39,0),MATCH('Calibración de recursos'!C$43,'Calibración de recursos'!$B$36:$G$36,0))=1),1,0) -> 1 | H12: =IF(AND(MATCH($C12,'Calibración de recursos'!$A$31:$A$33,0)>='Calibración de recursos'!D$44,INDEX('Calibración de recursos'!$B$37:$G$39,MATCH($D12,'Calibración de recursos'!$A$37:$A$39,0),MATCH('Calibración de recursos'!D$43,'Calibración de recursos'!$B$36:$G$36,0))=1),1,0) -> 1 | I12: =IF(AND(MATCH($C12,'Calibración de recursos'!$A$31:$A$33,0)>='Calibración de recursos'!E$44,INDEX('Calibración de recursos'!$B$37:$G$39,MATCH($D12,'Calibración de recursos'!$A$37:$A$39,0),MATCH('Calibración de recursos'!E$43,'Calibración de recursos'!$B$36:$G$36,0))=1),1,0) -> 1 | J12: =IF(AND(MATCH($C12,'Calibración de recursos'!$A$31:$A$33,0)>='Calibración de recursos'!F$44,INDEX('Calibración de recursos'!$B$37:$G$39,MATCH($D12,'Calibración de recursos'!$A$37:$A$39,0),MATCH('Calibración de recursos'!F$43,'Calibración de recursos'!$B$36:$G$36,0))=1),1,0) -> 0 | K12: =IF(AND(MATCH($C12,'Calibración de recursos'!$A$31:$A$33,0)>='Calibración de recursos'!G$44,INDEX('Calibración de recursos'!$B$37:$G$39,MATCH($D12,'Calibración de recursos'!$A$37:$A$39,0),MATCH('Calibración de recursos'!G$43,'Calibración de recursos'!$B$36:$G$36,0))=1),1,0) -> 0 | L12: =IF(AND(MATCH($C12,'Calibración de recursos'!$A$31:$A$33,0)>='Calibración de recursos'!H$44,INDEX('Calibración de recursos'!$B$37:$G$39,MATCH($D12,'Calibración de recursos'!$A$37:$A$39,0),MATCH('Calibración de recursos'!H$43,'Calibración de recursos'!$B$36:$G$36,0))=1),1,0) -> 0 | M12: =IF(AND(MATCH($C12,'Calibración de recursos'!$A$31:$A$33,0)>='Calibración de recursos'!I$44,INDEX('Calibración de recursos'!$B$37:$G$39,MATCH($D12,'Calibración de recursos'!$A$37:$A$39,0),MATCH('Calibración de recursos'!I$43,'Calibración de recursos'!$B$36:$G$36,0))=1),1,0) -> 0 | ... Q12: =IF(AND(MATCH($C12,'Calibración de recursos'!$A$31:$A$33,0)>='Calibración de recursos'!M$44,INDEX('Calibración de recursos'!$B$37:$G$39,MATCH($D12,'Calibración de recursos'!$A$37:$A$39,0),MATCH('Calibración de recursos'!M$43,'Calibración de recursos'!$B$36:$G$36,0))=1),1,0) -> 0 | R12: =SUM(F12:Q12) -> 4 | S12: Turno: Tabla 1 de Costigliola et al. (2017). Nivel: S19. Área: S20.
A13: A09 | B13: T2 | C13: intermedio | D13: Fisicoquímica | E13: =INDEX('Calibración de recursos'!$C$31:$C$33,MATCH(C13,'Calibración de recursos'!$A$31:$A$33,0)) -> 1 | F13: =IF(AND(MATCH($C13,'Calibración de recursos'!$A$31:$A$33,0)>='Calibración de recursos'!B$44,INDEX('Calibración de recursos'!$B$37:$G$39,MATCH($D13,'Calibración de recursos'!$A$37:$A$39,0),MATCH('Calibración de recursos'!B$43,'Calibración de recursos'!$B$36:$G$36,0))=1),1,0) -> 0 | G13: =IF(AND(MATCH($C13,'Calibración de recursos'!$A$31:$A$33,0)>='Calibración de recursos'!C$44,INDEX('Calibración de recursos'!$B$37:$G$39,MATCH($D13,'Calibración de recursos'!$A$37:$A$39,0),MATCH('Calibración de recursos'!C$43,'Calibración de recursos'!$B$36:$G$36,0))=1),1,0) -> 0 | H13: =IF(AND(MATCH($C13,'Calibración de recursos'!$A$31:$A$33,0)>='Calibración de recursos'!D$44,INDEX('Calibración de recursos'!$B$37:$G$39,MATCH($D13,'Calibración de recursos'!$A$37:$A$39,0),MATCH('Calibración de recursos'!D$43,'Calibración de recursos'!$B$36:$G$36,0))=1),1,0) -> 0 | I13: =IF(AND(MATCH($C13,'Calibración de recursos'!$A$31:$A$33,0)>='Calibración de recursos'!E$44,INDEX('Calibración de recursos'!$B$37:$G$39,MATCH($D13,'Calibración de recursos'!$A$37:$A$39,0),MATCH('Calibración de recursos'!E$43,'Calibración de recursos'!$B$36:$G$36,0))=1),1,0) -> 0 | J13: =IF(AND(MATCH($C13,'Calibración de recursos'!$A$31:$A$33,0)>='Calibración de recursos'!F$44,INDEX('Calibración de recursos'!$B$37:$G$39,MATCH($D13,'Calibración de recursos'!$A$37:$A$39,0),MATCH('Calibración de recursos'!F$43,'Calibración de recursos'!$B$36:$G$36,0))=1),1,0) -> 1 | K13: =IF(AND(MATCH($C13,'Calibración de recursos'!$A$31:$A$33,0)>='Calibración de recursos'!G$44,INDEX('Calibración de recursos'!$B$37:$G$39,MATCH($D13,'Calibración de recursos'!$A$37:$A$39,0),MATCH('Calibración de recursos'!G$43,'Calibración de recursos'!$B$36:$G$36,0))=1),1,0) -> 1 | L13: =IF(AND(MATCH($C13,'Calibración de recursos'!$A$31:$A$33,0)>='Calibración de recursos'!H$44,INDEX('Calibración de recursos'!$B$37:$G$39,MATCH($D13,'Calibración de recursos'!$A$37:$A$39,0),MATCH('Calibración de recursos'!H$43,'Calibración de recursos'!$B$36:$G$36,0))=1),1,0) -> 1 | M13: =IF(AND(MATCH($C13,'Calibración de recursos'!$A$31:$A$33,0)>='Calibración de recursos'!I$44,INDEX('Calibración de recursos'!$B$37:$G$39,MATCH($D13,'Calibración de recursos'!$A$37:$A$39,0),MATCH('Calibración de recursos'!I$43,'Calibración de recursos'!$B$36:$G$36,0))=1),1,0) -> 0 | ... Q13: =IF(AND(MATCH($C13,'Calibración de recursos'!$A$31:$A$33,0)>='Calibración de recursos'!M$44,INDEX('Calibración de recursos'!$B$37:$G$39,MATCH($D13,'Calibración de recursos'!$A$37:$A$39,0),MATCH('Calibración de recursos'!M$43,'Calibración de recursos'!$B$36:$G$36,0))=1),1,0) -> 0 | R13: =SUM(F13:Q13) -> 6 | S13: Turno: Tabla 1 de Costigliola et al. (2017). Nivel: S19. Área: S20.
A14: A10 | B14: T2 | C14: júnior | D14: Cromatografía | E14: =INDEX('Calibración de recursos'!$C$31:$C$33,MATCH(C14,'Calibración de recursos'!$A$31:$A$33,0)) -> 1.15 | F14: =IF(AND(MATCH($C14,'Calibración de recursos'!$A$31:$A$33,0)>='Calibración de recursos'!B$44,INDEX('Calibración de recursos'!$B$37:$G$39,MATCH($D14,'Calibración de recursos'!$A$37:$A$39,0),MATCH('Calibración de recursos'!B$43,'Calibración de recursos'!$B$36:$G$36,0))=1),1,0) -> 1 | G14: =IF(AND(MATCH($C14,'Calibración de recursos'!$A$31:$A$33,0)>='Calibración de recursos'!C$44,INDEX('Calibración de recursos'!$B$37:$G$39,MATCH($D14,'Calibración de recursos'!$A$37:$A$39,0),MATCH('Calibración de recursos'!C$43,'Calibración de recursos'!$B$36:$G$36,0))=1),1,0) -> 0 | H14: =IF(AND(MATCH($C14,'Calibración de recursos'!$A$31:$A$33,0)>='Calibración de recursos'!D$44,INDEX('Calibración de recursos'!$B$37:$G$39,MATCH($D14,'Calibración de recursos'!$A$37:$A$39,0),MATCH('Calibración de recursos'!D$43,'Calibración de recursos'!$B$36:$G$36,0))=1),1,0) -> 1 | I14: =IF(AND(MATCH($C14,'Calibración de recursos'!$A$31:$A$33,0)>='Calibración de recursos'!E$44,INDEX('Calibración de recursos'!$B$37:$G$39,MATCH($D14,'Calibración de recursos'!$A$37:$A$39,0),MATCH('Calibración de recursos'!E$43,'Calibración de recursos'!$B$36:$G$36,0))=1),1,0) -> 0 | J14: =IF(AND(MATCH($C14,'Calibración de recursos'!$A$31:$A$33,0)>='Calibración de recursos'!F$44,INDEX('Calibración de recursos'!$B$37:$G$39,MATCH($D14,'Calibración de recursos'!$A$37:$A$39,0),MATCH('Calibración de recursos'!F$43,'Calibración de recursos'!$B$36:$G$36,0))=1),1,0) -> 0 | K14: =IF(AND(MATCH($C14,'Calibración de recursos'!$A$31:$A$33,0)>='Calibración de recursos'!G$44,INDEX('Calibración de recursos'!$B$37:$G$39,MATCH($D14,'Calibración de recursos'!$A$37:$A$39,0),MATCH('Calibración de recursos'!G$43,'Calibración de recursos'!$B$36:$G$36,0))=1),1,0) -> 0 | L14: =IF(AND(MATCH($C14,'Calibración de recursos'!$A$31:$A$33,0)>='Calibración de recursos'!H$44,INDEX('Calibración de recursos'!$B$37:$G$39,MATCH($D14,'Calibración de recursos'!$A$37:$A$39,0),MATCH('Calibración de recursos'!H$43,'Calibración de recursos'!$B$36:$G$36,0))=1),1,0) -> 0 | M14: =IF(AND(MATCH($C14,'Calibración de recursos'!$A$31:$A$33,0)>='Calibración de recursos'!I$44,INDEX('Calibración de recursos'!$B$37:$G$39,MATCH($D14,'Calibración de recursos'!$A$37:$A$39,0),MATCH('Calibración de recursos'!I$43,'Calibración de recursos'!$B$36:$G$36,0))=1),1,0) -> 0 | ... Q14: =IF(AND(MATCH($C14,'Calibración de recursos'!$A$31:$A$33,0)>='Calibración de recursos'!M$44,INDEX('Calibración de recursos'!$B$37:$G$39,MATCH($D14,'Calibración de recursos'!$A$37:$A$39,0),MATCH('Calibración de recursos'!M$43,'Calibración de recursos'!$B$36:$G$36,0))=1),1,0) -> 0 | R14: =SUM(F14:Q14) -> 2 | S14: Turno: Tabla 1 de Costigliola et al. (2017). Nivel: S19. Área: S20.
A15: A11 | B15: T3 | C15: sénior | D15: Cromatografía | E15: =INDEX('Calibración de recursos'!$C$31:$C$33,MATCH(C15,'Calibración de recursos'!$A$31:$A$33,0)) -> 0.9 | F15: =IF(AND(MATCH($C15,'Calibración de recursos'!$A$31:$A$33,0)>='Calibración de recursos'!B$44,INDEX('Calibración de recursos'!$B$37:$G$39,MATCH($D15,'Calibración de recursos'!$A$37:$A$39,0),MATCH('Calibración de recursos'!B$43,'Calibración de recursos'!$B$36:$G$36,0))=1),1,0) -> 1 | G15: =IF(AND(MATCH($C15,'Calibración de recursos'!$A$31:$A$33,0)>='Calibración de recursos'!C$44,INDEX('Calibración de recursos'!$B$37:$G$39,MATCH($D15,'Calibración de recursos'!$A$37:$A$39,0),MATCH('Calibración de recursos'!C$43,'Calibración de recursos'!$B$36:$G$36,0))=1),1,0) -> 1 | H15: =IF(AND(MATCH($C15,'Calibración de recursos'!$A$31:$A$33,0)>='Calibración de recursos'!D$44,INDEX('Calibración de recursos'!$B$37:$G$39,MATCH($D15,'Calibración de recursos'!$A$37:$A$39,0),MATCH('Calibración de recursos'!D$43,'Calibración de recursos'!$B$36:$G$36,0))=1),1,0) -> 1 | I15: =IF(AND(MATCH($C15,'Calibración de recursos'!$A$31:$A$33,0)>='Calibración de recursos'!E$44,INDEX('Calibración de recursos'!$B$37:$G$39,MATCH($D15,'Calibración de recursos'!$A$37:$A$39,0),MATCH('Calibración de recursos'!E$43,'Calibración de recursos'!$B$36:$G$36,0))=1),1,0) -> 1 | J15: =IF(AND(MATCH($C15,'Calibración de recursos'!$A$31:$A$33,0)>='Calibración de recursos'!F$44,INDEX('Calibración de recursos'!$B$37:$G$39,MATCH($D15,'Calibración de recursos'!$A$37:$A$39,0),MATCH('Calibración de recursos'!F$43,'Calibración de recursos'!$B$36:$G$36,0))=1),1,0) -> 0 | K15: =IF(AND(MATCH($C15,'Calibración de recursos'!$A$31:$A$33,0)>='Calibración de recursos'!G$44,INDEX('Calibración de recursos'!$B$37:$G$39,MATCH($D15,'Calibración de recursos'!$A$37:$A$39,0),MATCH('Calibración de recursos'!G$43,'Calibración de recursos'!$B$36:$G$36,0))=1),1,0) -> 0 | L15: =IF(AND(MATCH($C15,'Calibración de recursos'!$A$31:$A$33,0)>='Calibración de recursos'!H$44,INDEX('Calibración de recursos'!$B$37:$G$39,MATCH($D15,'Calibración de recursos'!$A$37:$A$39,0),MATCH('Calibración de recursos'!H$43,'Calibración de recursos'!$B$36:$G$36,0))=1),1,0) -> 0 | M15: =IF(AND(MATCH($C15,'Calibración de recursos'!$A$31:$A$33,0)>='Calibración de recursos'!I$44,INDEX('Calibración de recursos'!$B$37:$G$39,MATCH($D15,'Calibración de recursos'!$A$37:$A$39,0),MATCH('Calibración de recursos'!I$43,'Calibración de recursos'!$B$36:$G$36,0))=1),1,0) -> 0 | ... Q15: =IF(AND(MATCH($C15,'Calibración de recursos'!$A$31:$A$33,0)>='Calibración de recursos'!M$44,INDEX('Calibración de recursos'!$B$37:$G$39,MATCH($D15,'Calibración de recursos'!$A$37:$A$39,0),MATCH('Calibración de recursos'!M$43,'Calibración de recursos'!$B$36:$G$36,0))=1),1,0) -> 0 | R15: =SUM(F15:Q15) -> 4 | S15: Turno: Tabla 1 de Costigliola et al. (2017). Nivel: S19. Área: S20.
A16: A12 | B16: T3 | C16: intermedio | D16: Cromatografía | E16: =INDEX('Calibración de recursos'!$C$31:$C$33,MATCH(C16,'Calibración de recursos'!$A$31:$A$33,0)) -> 1 | F16: =IF(AND(MATCH($C16,'Calibración de recursos'!$A$31:$A$33,0)>='Calibración de recursos'!B$44,INDEX('Calibración de recursos'!$B$37:$G$39,MATCH($D16,'Calibración de recursos'!$A$37:$A$39,0),MATCH('Calibración de recursos'!B$43,'Calibración de recursos'!$B$36:$G$36,0))=1),1,0) -> 1 | G16: =IF(AND(MATCH($C16,'Calibración de recursos'!$A$31:$A$33,0)>='Calibración de recursos'!C$44,INDEX('Calibración de recursos'!$B$37:$G$39,MATCH($D16,'Calibración de recursos'!$A$37:$A$39,0),MATCH('Calibración de recursos'!C$43,'Calibración de recursos'!$B$36:$G$36,0))=1),1,0) -> 1 | H16: =IF(AND(MATCH($C16,'Calibración de recursos'!$A$31:$A$33,0)>='Calibración de recursos'!D$44,INDEX('Calibración de recursos'!$B$37:$G$39,MATCH($D16,'Calibración de recursos'!$A$37:$A$39,0),MATCH('Calibración de recursos'!D$43,'Calibración de recursos'!$B$36:$G$36,0))=1),1,0) -> 1 | I16: =IF(AND(MATCH($C16,'Calibración de recursos'!$A$31:$A$33,0)>='Calibración de recursos'!E$44,INDEX('Calibración de recursos'!$B$37:$G$39,MATCH($D16,'Calibración de recursos'!$A$37:$A$39,0),MATCH('Calibración de recursos'!E$43,'Calibración de recursos'!$B$36:$G$36,0))=1),1,0) -> 1 | J16: =IF(AND(MATCH($C16,'Calibración de recursos'!$A$31:$A$33,0)>='Calibración de recursos'!F$44,INDEX('Calibración de recursos'!$B$37:$G$39,MATCH($D16,'Calibración de recursos'!$A$37:$A$39,0),MATCH('Calibración de recursos'!F$43,'Calibración de recursos'!$B$36:$G$36,0))=1),1,0) -> 0 | K16: =IF(AND(MATCH($C16,'Calibración de recursos'!$A$31:$A$33,0)>='Calibración de recursos'!G$44,INDEX('Calibración de recursos'!$B$37:$G$39,MATCH($D16,'Calibración de recursos'!$A$37:$A$39,0),MATCH('Calibración de recursos'!G$43,'Calibración de recursos'!$B$36:$G$36,0))=1),1,0) -> 0 | L16: =IF(AND(MATCH($C16,'Calibración de recursos'!$A$31:$A$33,0)>='Calibración de recursos'!H$44,INDEX('Calibración de recursos'!$B$37:$G$39,MATCH($D16,'Calibración de recursos'!$A$37:$A$39,0),MATCH('Calibración de recursos'!H$43,'Calibración de recursos'!$B$36:$G$36,0))=1),1,0) -> 0 | M16: =IF(AND(MATCH($C16,'Calibración de recursos'!$A$31:$A$33,0)>='Calibración de recursos'!I$44,INDEX('Calibración de recursos'!$B$37:$G$39,MATCH($D16,'Calibración de recursos'!$A$37:$A$39,0),MATCH('Calibración de recursos'!I$43,'Calibración de recursos'!$B$36:$G$36,0))=1),1,0) -> 0 | ... Q16: =IF(AND(MATCH($C16,'Calibración de recursos'!$A$31:$A$33,0)>='Calibración de recursos'!M$44,INDEX('Calibración de recursos'!$B$37:$G$39,MATCH($D16,'Calibración de recursos'!$A$37:$A$39,0),MATCH('Calibración de recursos'!M$43,'Calibración de recursos'!$B$36:$G$36,0))=1),1,0) -> 0 | R16: =SUM(F16:Q16) -> 4 | S16: Turno: Tabla 1 de Costigliola et al. (2017). Nivel: S19. Área: S20.
... A24: A20 | B24: T3 | C24: júnior | D24: Fisicoquímica | E24: =INDEX('Calibración de recursos'!$C$31:$C$33,MATCH(C24,'Calibración de recursos'!$A$31:$A$33,0)) -> 1.15 | F24: =IF(AND(MATCH($C24,'Calibración de recursos'!$A$31:$A$33,0)>='Calibración de recursos'!B$44,INDEX('Calibración de recursos'!$B$37:$G$39,MATCH($D24,'Calibración de recursos'!$A$37:$A$39,0),MATCH('Calibración de recursos'!B$43,'Calibración de recursos'!$B$36:$G$36,0))=1),1,0) -> 0 | G24: =IF(AND(MATCH($C24,'Calibración de recursos'!$A$31:$A$33,0)>='Calibración de recursos'!C$44,INDEX('Calibración de recursos'!$B$37:$G$39,MATCH($D24,'Calibración de recursos'!$A$37:$A$39,0),MATCH('Calibración de recursos'!C$43,'Calibración de recursos'!$B$36:$G$36,0))=1),1,0) -> 0 | H24: =IF(AND(MATCH($C24,'Calibración de recursos'!$A$31:$A$33,0)>='Calibración de recursos'!D$44,INDEX('Calibración de recursos'!$B$37:$G$39,MATCH($D24,'Calibración de recursos'!$A$37:$A$39,0),MATCH('Calibración de recursos'!D$43,'Calibración de recursos'!$B$36:$G$36,0))=1),1,0) -> 0 | I24: =IF(AND(MATCH($C24,'Calibración de recursos'!$A$31:$A$33,0)>='Calibración de recursos'!E$44,INDEX('Calibración de recursos'!$B$37:$G$39,MATCH($D24,'Calibración de recursos'!$A$37:$A$39,0),MATCH('Calibración de recursos'!E$43,'Calibración de recursos'!$B$36:$G$36,0))=1),1,0) -> 0 | J24: =IF(AND(MATCH($C24,'Calibración de recursos'!$A$31:$A$33,0)>='Calibración de recursos'!F$44,INDEX('Calibración de recursos'!$B$37:$G$39,MATCH($D24,'Calibración de recursos'!$A$37:$A$39,0),MATCH('Calibración de recursos'!F$43,'Calibración de recursos'!$B$36:$G$36,0))=1),1,0) -> 1 | K24: =IF(AND(MATCH($C24,'Calibración de recursos'!$A$31:$A$33,0)>='Calibración de recursos'!G$44,INDEX('Calibración de recursos'!$B$37:$G$39,MATCH($D24,'Calibración de recursos'!$A$37:$A$39,0),MATCH('Calibración de recursos'!G$43,'Calibración de recursos'!$B$36:$G$36,0))=1),1,0) -> 0 | L24: =IF(AND(MATCH($C24,'Calibración de recursos'!$A$31:$A$33,0)>='Calibración de recursos'!H$44,INDEX('Calibración de recursos'!$B$37:$G$39,MATCH($D24,'Calibración de recursos'!$A$37:$A$39,0),MATCH('Calibración de recursos'!H$43,'Calibración de recursos'!$B$36:$G$36,0))=1),1,0) -> 0 | M24: =IF(AND(MATCH($C24,'Calibración de recursos'!$A$31:$A$33,0)>='Calibración de recursos'!I$44,INDEX('Calibración de recursos'!$B$37:$G$39,MATCH($D24,'Calibración de recursos'!$A$37:$A$39,0),MATCH('Calibración de recursos'!I$43,'Calibración de recursos'!$B$36:$G$36,0))=1),1,0) -> 0 | ... Q24: =IF(AND(MATCH($C24,'Calibración de recursos'!$A$31:$A$33,0)>='Calibración de recursos'!M$44,INDEX('Calibración de recursos'!$B$37:$G$39,MATCH($D24,'Calibración de recursos'!$A$37:$A$39,0),MATCH('Calibración de recursos'!M$43,'Calibración de recursos'!$B$36:$G$36,0))=1),1,0) -> 0 | R24: =SUM(F24:Q24) -> 2 | S24: Turno: Tabla 1 de Costigliola et al. (2017). Nivel: S19. Área: S20.

Sheet Calibración de recursos
A1: Calibración de equipos y analistas
A2: Horas de equipo por método, datos de la fuente, regla de la matriz de calificación, cobertura de cada método e indicadores. Azul = dato · negro = fórmula · amarillo = supuesto.
A4: A. Horas de equipo por método en el escenario base: ensayos al año × (montaje medio + corrida media) ÷ 60
A5: Método | B5: Técnica | C5: Configuración principal | D5: Participación en la demanda | E5: Ensayos al año | F5: Montaje medio (min) | G5: Corrida media (min) | H5: Horas de equipo al año
A6: M01 | B6: =Catálogo!B5 -> HPLC | C6: HPLC-I | D6: =Catálogo!M5 -> 0.3080569 | E6: =D6*Demanda!$C$11 -> 4720.3558 | F6: =(Duraciones!D6+Duraciones!E6+Duraciones!F6)/3 -> 46.666667 | G6: =Catálogo!T5 -> 62.286797 | H6: =E6*(F6+G6)/60 -> 8571.652
A7: M02 | B7: =Catálogo!B6 -> HPLC | C7: HPLC-G | D7: =Catálogo!M6 -> 0.098943103 | E7: =D7*Demanda!$C$11 -> 1516.1052 | F7: =(Duraciones!D6+Duraciones!E6+Duraciones!F6)/3 -> 46.666667 | G7: =Catálogo!T6 -> 155.71699 | H7: =E7*(F7+G7)/60 -> 5113.9152
A8: M03 | B8: =Catálogo!B7 -> GC | C8: GC-L | D8: =Catálogo!M7 -> 0.07967 | E8: =D8*Demanda!$C$11 -> 1220.7834 | F8: =(Duraciones!D10+Duraciones!E10+Duraciones!F10)/3 -> 12.333333 | G8: =Catálogo!T7 -> 46.096654 | H8: =E8*(F8+G8)/60 -> 1188.8393
A9: M04 | B9: =Catálogo!B8 -> GC | C9: GC-H | D9: =Catálogo!M8 -> 0.17733 | E9: =D9*Demanda!$C$11 -> 2717.2276 | F9: =(Duraciones!D10+Duraciones!E10+Duraciones!F10)/3 -> 12.333333 | G9: =Catálogo!T8 -> 69.144981 | H9: =E9*(F9+G9)/60 -> 3689.9187
A10: M05 | B10: =Catálogo!B9 -> PSA | C10: PSA-S | D10: =Catálogo!M9 -> 0.068044776 | E10: =D10*Demanda!$C$11 -> 1042.6501 | F10: =(Duraciones!D14+Duraciones!F14)/2 -> 16.5 | G10: =Catálogo!T9 -> 9.5484574 | H10: =E10*(F10+G10)/60 -> 452.65711
A11: M06 | B11: =Catálogo!B10 -> PSA | C11: PSA-H | D11: =Catálogo!M10 -> 0.11995522 | E11: =D11*Demanda!$C$11 -> 1838.0739 | F11: =(Duraciones!D14+Duraciones!F14)/2 -> 16.5 | G11: =Catálogo!T10 -> 18.092396 | H11: =E11*(F11+G11)/60 -> 1059.723
A12: M07 | B12: =Catálogo!B11 -> KF | C12: KF-V | D12: =Catálogo!M11 -> 0.045484375 | E12: =D12*Demanda!$C$11 -> 696.95708 | F12: =(Duraciones!D18+Duraciones!E18+Duraciones!F18)/3 -> 9.3333333 | G12: =Catálogo!T11 -> 13.131306 | H12: =E12*(F12+G12)/60 -> 260.94815
A13: M08 | B13: =Catálogo!B12 -> KF | C13: KF-C | D13: =Catálogo!M12 -> 0.025515625 | E13: =D13*Demanda!$C$11 -> 390.97592 | F13: =(Duraciones!D18+Duraciones!E18+Duraciones!F18)/3 -> 9.3333333 | G13: =Catálogo!T12 -> 35.026803 | H13: =E13*(F13+G13)/60 -> 289.06242
A14: M09 | B14: =Catálogo!B13 -> DSC | C14: DSC | D14: =Catálogo!M13 -> 0.0073333333 | E14: =D14*Demanda!$C$11 -> 112.36867 | F14: =(Duraciones!D22+Duraciones!E22+Duraciones!F22)/3 -> 5.3333333 | G14: =Catálogo!T13 -> 27.4 | H14: =E14*(F14+G14)/60 -> 61.30335
A15: M10 | B15: =Catálogo!B14 -> DSC | C15: DSC | D15: =Catálogo!M14 -> 0.032666667 | E15: =D15*Demanda!$C$11 -> 500.55133 | F15: =(Duraciones!D22+Duraciones!E22+Duraciones!F22)/3 -> 5.3333333 | G15: =Catálogo!T14 -> 111.4 | H15: =E15*(F15+G15)/60 -> 973.85043
A16: M11 | B16: =Catálogo!B15 -> XRPD | C16: XRPD | D16: =Catálogo!M15 -> 0.028807143 | E16: =D16*Demanda!$C$11 -> 441.41185 | F16: =(Duraciones!D26+Duraciones!E26+Duraciones!F26)/3 -> 8.6666667 | G16: =Catálogo!T15 -> 61.084039 | H16: =E16*(F16+G16)/60 -> 513.14647
A17: M12 | B17: =Catálogo!B16 -> XRPD | C17: XRPD | D17: =Catálogo!M16 -> 0.0081928571 | E17: =D17*Demanda!$C$11 -> 125.53915 | F17: =(Duraciones!D26+Duraciones!E26+Duraciones!F26)/3 -> 8.6666667 | G17: =Catálogo!T16 -> 145.00558 | H17: =E17*(F17+G17)/60 -> 321.53139
A18: Total | H18: =SUM(H6:H17) -> 22496.548
A19: Montaje medio = media de la distribución de la Tabla 3 de Costigliola et al. (2017) (uniforme en PSA, triangular en las demás). La idoneidad del sistema no se suma: su frecuencia depende de la programación y se mide en la simulación.
A21: B. Datos de la fuente que se usan en los chequeos
A22: Equipos del laboratorio | B22: 70 | C22: Costigliola et al. (2017, p. 9015)
A23: HPLC (mínimo) | B23: 22 | C23: Costigliola et al. (2017, Fig. 5, p. 9018): equipos numerados hasta HPLC22
A24: Analistas | B24: 20 | C24: Costigliola et al. (2017, p. 9015)
A25: Analistas del turno 1 | B25: 6 | C25: Costigliola et al. (2017, Tabla 1 y p. 9015)
A26: Analistas del turno 2 | B26: 4 | C26: Costigliola et al. (2017, Tabla 1 y p. 9015)
A27: Analistas del turno 3 | B27: 10 | C27: Costigliola et al. (2017, Tabla 1 y p. 9015)
A29: C. Niveles de experiencia (supuestos S07 y S19)
A30: Nivel | B30: Rango | C30: Factor de duración | D30: Analistas | E30: Proporción
A31: júnior | B31: 1 | C31: 1.15 | D31: =COUNTIF(Analistas!$C$5:$C$24,A31) -> 6 | E31: =IFERROR(D31/SUM($D$31:$D$33),0) -> 0.3
A32: intermedio | B32: 2 | C32: 1 | D32: =COUNTIF(Analistas!$C$5:$C$24,A32) -> 9 | E32: =IFERROR(D32/SUM($D$31:$D$33),0) -> 0.45
A33: sénior | B33: 3 | C33: 0.9 | D33: =COUNTIF(Analistas!$C$5:$C$24,A33) -> 5 | E33: =IFERROR(D33/SUM($D$31:$D$33),0) -> 0.25
A35: D. Técnicas de cada área de trabajo (supuesto S20): 1 = el área incluye la técnica
A36: Área | B36: HPLC | C36: GC | D36: PSA | E36: KF | F36: DSC | G36: XRPD
A37: Todas | B37: 1 | C37: 1 | D37: 1 | E37: 1 | F37: 1 | G37: 1
A38: Cromatografía | B38: 1 | C38: 1 | D38: 0 | E38: 0 | F38: 0 | G38: 0
A39: Fisicoquímica | B39: 0 | C39: 0 | D39: 1 | E39: 1 | F39: 1 | G39: 1
A41: E. Datos de cada método que usa la regla de calificación
A42: Dato | B42: M01 | C42: M02 | D42: M03 | E42: M04 | F42: M05 | G42: M06 | H42: M07 | I42: M08 | J42: M09 | K42: M10 | L42: M11 | M42: M12
A43: Técnica | B43: =Catálogo!B5 -> HPLC | C43: =Catálogo!B6 -> HPLC | D43: =Catálogo!B7 -> GC | E43: =Catálogo!B8 -> GC | F43: =Catálogo!B9 -> PSA | G43: =Catálogo!B10 -> PSA | H43: =Catálogo!B11 -> KF | I43: =Catálogo!B12 -> KF | J43: =Catálogo!B13 -> DSC | K43: =Catálogo!B14 -> DSC | L43: =Catálogo!B15 -> XRPD | M43: =Catálogo!B16 -> XRPD
A44: Nivel mínimo (1 júnior, 2 intermedio, 3 sénior) | B44: =MATCH(Catálogo!H5,'Calibración del catálogo'!$A$6:$A$8,0) -> 1 | C44: =MATCH(Catálogo!H6,'Calibración del catálogo'!$A$6:$A$8,0) -> 2 | D44: =MATCH(Catálogo!H7,'Calibración del catálogo'!$A$6:$A$8,0) -> 1 | E44: =MATCH(Catálogo!H8,'Calibración del catálogo'!$A$6:$A$8,0) -> 2 | F44: =MATCH(Catálogo!H9,'Calibración del catálogo'!$A$6:$A$8,0) -> 1 | G44: =MATCH(Catálogo!H10,'Calibración del catálogo'!$A$6:$A$8,0) -> 2 | H44: =MATCH(Catálogo!H11,'Calibración del catálogo'!$A$6:$A$8,0) -> 2 | I44: =MATCH(Catálogo!H12,'Calibración del catálogo'!$A$6:$A$8,0) -> 3 | J44: =MATCH(Catálogo!H13,'Calibración del catálogo'!$A$6:$A$8,0) -> 1 | K44: =MATCH(Catálogo!H14,'Calibración del catálogo'!$A$6:$A$8,0) -> 2 | L44: =MATCH(Catálogo!H15,'Calibración del catálogo'!$A$6:$A$8,0) -> 2 | M44: =MATCH(Catálogo!H16,'Calibración del catálogo'!$A$6:$A$8,0) -> 3
A45: Aplica a control en proceso (1 = sí) | B45: =IF(Catálogo!W5="X",1,0) -> 1 | C45: =IF(Catálogo!W6="X",1,0) -> 0 | D45: =IF(Catálogo!W7="X",1,0) -> 0 | E45: =IF(Catálogo!W8="X",1,0) -> 1 | F45: =IF(Catálogo!W9="X",1,0) -> 1 | G45: =IF(Catálogo!W10="X",1,0) -> 0 | H45: =IF(Catálogo!W11="X",1,0) -> 1 | I45: =IF(Catálogo!W12="X",1,0) -> 0 | J45: =IF(Catálogo!W13="X",1,0) -> 1 | K45: =IF(Catálogo!W14="X",1,0) -> 0 | L45: =IF(Catálogo!W15="X",1,0) -> 1 | M45: =IF(Catálogo!W16="X",1,0) -> 0
A47: F. Cobertura de cada método: analistas calificados, equipos compatibles y combinaciones factibles
A48: Indicador | B48: M01 | C48: M02 | D48: M03 | E48: M04 | F48: M05 | G48: M06 | H48: M07 | I48: M08 | J48: M09 | K48: M10 | L48: M11 | M48: M12
A49: Analistas calificados | B49: =SUM(Analistas!F$5:F$24) -> 15 | C49: =SUM(Analistas!G$5:G$24) -> 11 | D49: =SUM(Analistas!H$5:H$24) -> 15 | E49: =SUM(Analistas!I$5:I$24) -> 11 | F49: =SUM(Analistas!J$5:J$24) -> 11 | G49: =SUM(Analistas!K$5:K$24) -> 9 | H49: =SUM(Analistas!L$5:L$24) -> 9 | I49: =SUM(Analistas!M$5:M$24) -> 3 | ... M49: =SUM(Analistas!Q$5:Q$24) -> 3
A50: … del turno 1 | B50: =SUMIF(Analistas!$B$5:$B$24,"T1",Analistas!F$5:F$24) -> 6 | C50: =SUMIF(Analistas!$B$5:$B$24,"T1",Analistas!G$5:G$24) -> 6 | D50: =SUMIF(Analistas!$B$5:$B$24,"T1",Analistas!H$5:H$24) -> 6 | E50: =SUMIF(Analistas!$B$5:$B$24,"T1",Analistas!I$5:I$24) -> 6 | F50: =SUMIF(Analistas!$B$5:$B$24,"T1",Analistas!J$5:J$24) -> 6 | G50: =SUMIF(Analistas!$B$5:$B$24,"T1",Analistas!K$5:K$24) -> 6 | H50: =SUMIF(Analistas!$B$5:$B$24,"T1",Analistas!L$5:L$24) -> 6 | I50: =SUMIF(Analistas!$B$5:$B$24,"T1",Analistas!M$5:M$24) -> 2 | ... M50: =SUMIF(Analistas!$B$5:$B$24,"T1",Analistas!Q$5:Q$24) -> 2
A51: … del turno 2 | B51: =SUMIF(Analistas!$B$5:$B$24,"T2",Analistas!F$5:F$24) -> 3 | C51: =SUMIF(Analistas!$B$5:$B$24,"T2",Analistas!G$5:G$24) -> 2 | D51: =SUMIF(Analistas!$B$5:$B$24,"T2",Analistas!H$5:H$24) -> 3 | E51: =SUMIF(Analistas!$B$5:$B$24,"T2",Analistas!I$5:I$24) -> 2 | F51: =SUMIF(Analistas!$B$5:$B$24,"T2",Analistas!J$5:J$24) -> 1 | G51: =SUMIF(Analistas!$B$5:$B$24,"T2",Analistas!K$5:K$24) -> 1 | H51: =SUMIF(Analistas!$B$5:$B$24,"T2",Analistas!L$5:L$24) -> 1 | I51: =SUMIF(Analistas!$B$5:$B$24,"T2",Analistas!M$5:M$24) -> 0 | ... M51: =SUMIF(Analistas!$B$5:$B$24,"T2",Analistas!Q$5:Q$24) -> 0
A52: … del turno 3 | B52: =SUMIF(Analistas!$B$5:$B$24,"T3",Analistas!F$5:F$24) -> 6 | C52: =SUMIF(Analistas!$B$5:$B$24,"T3",Analistas!G$5:G$24) -> 3 | D52: =SUMIF(Analistas!$B$5:$B$24,"T3",Analistas!H$5:H$24) -> 6 | E52: =SUMIF(Analistas!$B$5:$B$24,"T3",Analistas!I$5:I$24) -> 3 | F52: =SUMIF(Analistas!$B$5:$B$24,"T3",Analistas!J$5:J$24) -> 4 | G52: =SUMIF(Analistas!$B$5:$B$24,"T3",Analistas!K$5:K$24) -> 2 | H52: =SUMIF(Analistas!$B$5:$B$24,"T3",Analistas!L$5:L$24) -> 2 | I52: =SUMIF(Analistas!$B$5:$B$24,"T3",Analistas!M$5:M$24) -> 1 | ... M52: =SUMIF(Analistas!$B$5:$B$24,"T3",Analistas!Q$5:Q$24) -> 1
A53: Equipos compatibles | B53: =SUMIF(Equipos!E$5:E$14,"X",Equipos!$D$5:$D$14) -> 41 | C53: =SUMIF(Equipos!F$5:F$14,"X",Equipos!$D$5:$D$14) -> 15 | D53: =SUMIF(Equipos!G$5:G$14,"X",Equipos!$D$5:$D$14) -> 4 | E53: =SUMIF(Equipos!H$5:H$14,"X",Equipos!$D$5:$D$14) -> 11 | F53: =SUMIF(Equipos!I$5:I$14,"X",Equipos!$D$5:$D$14) -> 2 | G53: =SUMIF(Equipos!J$5:J$14,"X",Equipos!$D$5:$D$14) -> 3 | H53: =SUMIF(Equipos!K$5:K$14,"X",Equipos!$D$5:$D$14) -> 2 | I53: =SUMIF(Equipos!L$5:L$14,"X",Equipos!$D$5:$D$14) -> 2 | ... M53: =SUMIF(Equipos!P$5:P$14,"X",Equipos!$D$5:$D$14) -> 2
A54: Combinaciones analista–equipo | B54: =B49*B53 -> 615 | C54: =C49*C53 -> 165 | D54: =D49*D53 -> 60 | E54: =E49*E53 -> 121 | F54: =F49*F53 -> 22 | G54: =G49*G53 -> 27 | H54: =H49*H53 -> 18 | I54: =I49*I53 -> 6 | ... M54: =M49*M53 -> 6
A55: Chequeo (≥ 2 analistas y ≥ 1 equipo) | B55: =IF(AND(B49>=2,B53>=1),"OK","Revisar") -> OK | C55: =IF(AND(C49>=2,C53>=1),"OK","Revisar") -> OK | D55: =IF(AND(D49>=2,D53>=1),"OK","Revisar") -> OK | E55: =IF(AND(E49>=2,E53>=1),"OK","Revisar") -> OK | F55: =IF(AND(F49>=2,F53>=1),"OK","Revisar") -> OK | G55: =IF(AND(G49>=2,G53>=1),"OK","Revisar") -> OK | H55: =IF(AND(H49>=2,H53>=1),"OK","Revisar") -> OK | I55: =IF(AND(I49>=2,I53>=1),"OK","Revisar") -> OK | ... M55: =IF(AND(M49>=2,M53>=1),"OK","Revisar") -> OK
A56: Turno 1 completo en control en proceso | B56: =IF(B$45=1,IF(B50=COUNTIF(Analistas!$B$5:$B$24,"T1"),"OK","Revisar"),"No aplica") -> OK | C56: =IF(C$45=1,IF(C50=COUNTIF(Analistas!$B$5:$B$24,"T1"),"OK","Revisar"),"No aplica") -> No aplica | D56: =IF(D$45=1,IF(D50=COUNTIF(Analistas!$B$5:$B$24,"T1"),"OK","Revisar"),"No aplica") -> No aplica | E56: =IF(E$45=1,IF(E50=COUNTIF(Analistas!$B$5:$B$24,"T1"),"OK","Revisar"),"No aplica") -> OK | F56: =IF(F$45=1,IF(F50=COUNTIF(Analistas!$B$5:$B$24,"T1"),"OK","Revisar"),"No aplica") -> OK | G56: =IF(G$45=1,IF(G50=COUNTIF(Analistas!$B$5:$B$24,"T1"),"OK","Revisar"),"No aplica") -> No aplica | H56: =IF(H$45=1,IF(H50=COUNTIF(Analistas!$B$5:$B$24,"T1"),"OK","Revisar"),"No aplica") -> OK | I56: =IF(I$45=1,IF(I50=COUNTIF(Analistas!$B$5:$B$24,"T1"),"OK","Revisar"),"No aplica") -> No aplica | ... M56: =IF(M$45=1,IF(M50=COUNTIF(Analistas!$B$5:$B$24,"T1"),"OK","Revisar"),"No aplica") -> No aplica
A58: G. Indicadores y chequeos
A59: Indicador | B59: Valor | C59: Chequeo o referencia
A60: Equipos en total | B60: =SUM(Equipos!D5:D14) -> 70 | C60: =IF(B60=B22,"OK","Revisar") -> OK
A61: HPLC en total | B61: =SUMIF(Equipos!B5:B14,"HPLC",Equipos!D5:D14) -> 41 | C61: =IF(B61>=B23,"OK","Revisar") -> OK
A62: Configuraciones con menos de 2 equipos | B62: =COUNTIF(Equipos!D5:D14,"<2") -> 0 | C62: =IF(B62=0,"OK","Revisar") -> OK
A63: Analistas en total | B63: =COUNTA(Analistas!A5:A24) -> 20 | C63: =IF(B63=B24,"OK","Revisar") -> OK
A64: Analistas por turno (T1, T2, T3) | B64: =COUNTIF(Analistas!B5:B24,"T1")&" · "&COUNTIF(Analistas!B5:B24,"T2")&" · "&COUNTIF(Analistas!B5:B24,"T3") -> 6 · 4 · 10 | C64: =IF(AND(COUNTIF(Analistas!B5:B24,"T1")=B25,COUNTIF(Analistas!B5:B24,"T2")=B26,COUNTIF(Analistas!B5:B24,"T3")=B27),"OK","Revisar") -> OK
A65: Métodos con cobertura completa | B65: =COUNTIF(B55:M55,"OK")&" de 12" -> 12 de 12 | C65: =IF(COUNTIF(B55:M55,"OK")=12,"OK","Revisar") -> OK
A66: Métodos de control en proceso con el turno 1 completo | B66: =COUNTIF(B56:M56,"OK")&" de "&SUM(B45:M45) -> 6 de 6 | C66: =IF(COUNTIF(B56:M56,"OK")=SUM(B45:M45),"OK","Revisar") -> OK
A67: Densidad de la matriz de calificación | B67: =SUM(Analistas!F5:Q24)/(COUNTA(Analistas!A5:A24)*12) -> 0.48333333 | C67: ="Martins et al. (2023, p. 191): flexibilidad f = 0,3 y 0,6" -> Martins et al. (2023, p. 191): flexibilidad f = 0,3 y 0,6
A68: Analistas calificados por método (promedio) | B68: =AVERAGE(B49:M49) -> 9.6666667 | C68: ="TLSP: 6 empleados calificados por trabajo en promedio (Mischek y Musliu, 2021, p. 550)" -> TLSP: 6 empleados calificados por trabajo en promedio (Mischek y Musliu, 2021, p. 550)
A69: Utilización máxima de una configuración (base) | B69: =MAX(Equipos!U5:U14) -> 0.04764143 | C69: ="Sin idoneidad del sistema; Costigliola et al. (2017, p. 9019): los equipos alcanzan aun con +50 % de carga" -> Sin idoneidad del sistema; Costigliola et al. (2017, p. 9019): los equipos alcanzan aun con +50 % de carga
A70: Utilización máxima de una configuración (carga alta) | B70: =MAX(Equipos!V5:V14) -> 0.071462146 | C70: =""

Sheet Turnos
A1: Códigos de turno del laboratorio de referencia
A2: Una fila por código. Horario de Costigliola et al. (2017, Tabla 1, p. 9015); las pausas son el supuesto S24 (amarillo). La hoja Rotación usa estos códigos.
A4: Código | B4: Turno | C4: Descripción | D4: Inicio (h) | E4: Fin (h) | F4: Pausa desde (h) | G4: Pausa hasta (h) | H4: Horas efectivas | I4: Días | J4: Fuente o supuesto
A5: D | B5: T1 | C5: Turno 1, día | D5: 8 | E5: 20 | F5: 0 | G5: 0 | H5: =IF(A5="L",0,IF(E5>D5,E5-D5,E5+24-D5)-(G5-F5)) -> 12 | I5: Todos los días, según la rotación | J5: Horario: Costigliola et al. (2017, Tabla 1). Pausa: S24.
A6: N | B6: T1 | C6: Turno 1, noche (termina al día siguiente) | D6: 20 | E6: 8 | F6: 0 | G6: 0 | H6: =IF(A6="L",0,IF(E6>D6,E6-D6,E6+24-D6)-(G6-F6)) -> 12 | I6: Todos los días, según la rotación | J6: Horario: Costigliola et al. (2017, Tabla 1). Pausa: S24.
A7: M2 | B7: T2 | C7: Turno 2, mañana | D7: 8 | E7: 17 | F7: 12 | G7: 13 | H7: =IF(A7="L",0,IF(E7>D7,E7-D7,E7+24-D7)-(G7-F7)) -> 8 | I7: Lunes a viernes, semanas alternas | J7: Horario: Costigliola et al. (2017, Tabla 1). Pausa: S24.
A8: T2 | B8: T2 | C8: Turno 2, tarde | D8: 17 | E8: 24 | F8: 0 | G8: 0 | H8: =IF(A8="L",0,IF(E8>D8,E8-D8,E8+24-D8)-(G8-F8)) -> 7 | I8: Lunes a viernes, semanas alternas | J8: Horario: Costigliola et al. (2017, Tabla 1). Pausa: S24.
A9: M3a | B9: T3 | C9: Turno 3, almuerzo a las 12:00 | D9: 8 | E9: 17 | F9: 12 | G9: 13 | H9: =IF(A9="L",0,IF(E9>D9,E9-D9,E9+24-D9)-(G9-F9)) -> 8 | I9: Lunes a viernes | J9: Horario: Costigliola et al. (2017, Tabla 1). Pausa: S24.
A10: M3b | B10: T3 | C10: Turno 3, almuerzo a las 13:00 | D10: 8 | E10: 17 | F10: 13 | G10: 14 | H10: =IF(A10="L",0,IF(E10>D10,E10-D10,E10+24-D10)-(G10-F10)) -> 8 | I10: Lunes a viernes | J10: Horario: Costigliola et al. (2017, Tabla 1). Pausa: S24.
A11: L | B11: No aplica | C11: Libre | H11: =IF(A11="L",0,IF(E11>D11,E11-D11,E11+24-D11)-(G11-F11)) -> 0 | I11: No aplica | J11: No aplica

Sheet Rotación
A1: Rotación de los analistas (ciclo de 42 días)
A2: Código de turno de cada analista cada día; el día 1 es lunes y el ciclo se repite. Se calcula con el turno de la hoja Analistas y el desfase y el grupo de almuerzo de la hoja Calibración de turnos.
A3: Códigos: D día y N noche del turno 1 (12 h); M2 mañana y T2 tarde del turno 2; M3a y M3b turno 3 con almuerzo a las 12:00 o a las 13:00; L libre (hoja Turnos).
A4: Día | B4: Día de la semana | C4: A01 | D4: A02 | E4: A03 | F4: A04 | G4: A05 | H4: A06 | I4: A07 | J4: A08 | K4: A09 | L4: A10 | M4: A11 | N4: A12 | O4: A13 | P4: A14 | Q4: A15 | R4: A16 | S4: A17 | T4: A18 | U4: A19 | V4: A20
A5: 1 | B5: =CHOOSE(MOD(A5-1,7)+1,"lunes","martes","miércoles","jueves","viernes","sábado","domingo") -> lunes | C5: =IF('Calibración de turnos'!$B$6="T1",MID("DDNNLL",MOD($A5-1+'Calibración de turnos'!$D$6,6)+1,1),IF('Calibración de turnos'!$B$6="T2",IF(MOD($A5-1,7)+1<=5,IF(MOD(INT(($A5-1)/7)+'Calibración de turnos'!$D$6,2)=0,"M2","T2"),"L"),IF(MOD($A5-1,7)+1<=5,IF('Calibración de turnos'!$E$6=13,"M3b","M3a"),"L"))) -> D | D5: =IF('Calibración de turnos'!$B$7="T1",MID("DDNNLL",MOD($A5-1+'Calibración de turnos'!$D$7,6)+1,1),IF('Calibración de turnos'!$B$7="T2",IF(MOD($A5-1,7)+1<=5,IF(MOD(INT(($A5-1)/7)+'Calibración de turnos'!$D$7,2)=0,"M2","T2"),"L"),IF(MOD($A5-1,7)+1<=5,IF('Calibración de turnos'!$E$7=13,"M3b","M3a"),"L"))) -> N | E5: =IF('Calibración de turnos'!$B$8="T1",MID("DDNNLL",MOD($A5-1+'Calibración de turnos'!$D$8,6)+1,1),IF('Calibración de turnos'!$B$8="T2",IF(MOD($A5-1,7)+1<=5,IF(MOD(INT(($A5-1)/7)+'Calibración de turnos'!$D$8,2)=0,"M2","T2"),"L"),IF(MOD($A5-1,7)+1<=5,IF('Calibración de turnos'!$E$8=13,"M3b","M3a"),"L"))) -> D | F5: =IF('Calibración de turnos'!$B$9="T1",MID("DDNNLL",MOD($A5-1+'Calibración de turnos'!$D$9,6)+1,1),IF('Calibración de turnos'!$B$9="T2",IF(MOD($A5-1,7)+1<=5,IF(MOD(INT(($A5-1)/7)+'Calibración de turnos'!$D$9,2)=0,"M2","T2"),"L"),IF(MOD($A5-1,7)+1<=5,IF('Calibración de turnos'!$E$9=13,"M3b","M3a"),"L"))) -> N | G5: =IF('Calibración de turnos'!$B$10="T1",MID("DDNNLL",MOD($A5-1+'Calibración de turnos'!$D$10,6)+1,1),IF('Calibración de turnos'!$B$10="T2",IF(MOD($A5-1,7)+1<=5,IF(MOD(INT(($A5-1)/7)+'Calibración de turnos'!$D$10,2)=0,"M2","T2"),"L"),IF(MOD($A5-1,7)+1<=5,IF('Calibración de turnos'!$E$10=13,"M3b","M3a"),"L"))) -> L | H5: =IF('Calibración de turnos'!$B$11="T1",MID("DDNNLL",MOD($A5-1+'Calibración de turnos'!$D$11,6)+1,1),IF('Calibración de turnos'!$B$11="T2",IF(MOD($A5-1,7)+1<=5,IF(MOD(INT(($A5-1)/7)+'Calibración de turnos'!$D$11,2)=0,"M2","T2"),"L"),IF(MOD($A5-1,7)+1<=5,IF('Calibración de turnos'!$E$11=13,"M3b","M3a"),"L"))) -> L | I5: =IF('Calibración de turnos'!$B$12="T1",MID("DDNNLL",MOD($A5-1+'Calibración de turnos'!$D$12,6)+1,1),IF('Calibración de turnos'!$B$12="T2",IF(MOD($A5-1,7)+1<=5,IF(MOD(INT(($A5-1)/7)+'Calibración de turnos'!$D$12,2)=0,"M2","T2"),"L"),IF(MOD($A5-1,7)+1<=5,IF('Calibración de turnos'!$E$12=13,"M3b","M3a"),"L"))) -> M2 | J5: =IF('Calibración de turnos'!$B$13="T1",MID("DDNNLL",MOD($A5-1+'Calibración de turnos'!$D$13,6)+1,1),IF('Calibración de turnos'!$B$13="T2",IF(MOD($A5-1,7)+1<=5,IF(MOD(INT(($A5-1)/7)+'Calibración de turnos'!$D$13,2)=0,"M2","T2"),"L"),IF(MOD($A5-1,7)+1<=5,IF('Calibración de turnos'!$E$13=13,"M3b","M3a"),"L"))) -> T2 | K5: =IF('Calibración de turnos'!$B$14="T1",MID("DDNNLL",MOD($A5-1+'Calibración de turnos'!$D$14,6)+1,1),IF('Calibración de turnos'!$B$14="T2",IF(MOD($A5-1,7)+1<=5,IF(MOD(INT(($A5-1)/7)+'Calibración de turnos'!$D$14,2)=0,"M2","T2"),"L"),IF(MOD($A5-1,7)+1<=5,IF('Calibración de turnos'!$E$14=13,"M3b","M3a"),"L"))) -> M2 | L5: =IF('Calibración de turnos'!$B$15="T1",MID("DDNNLL",MOD($A5-1+'Calibración de turnos'!$D$15,6)+1,1),IF('Calibración de turnos'!$B$15="T2",IF(MOD($A5-1,7)+1<=5,IF(MOD(INT(($A5-1)/7)+'Calibración de turnos'!$D$15,2)=0,"M2","T2"),"L"),IF(MOD($A5-1,7)+1<=5,IF('Calibración de turnos'!$E$15=13,"M3b","M3a"),"L"))) -> T2 | M5: =IF('Calibración de turnos'!$B$16="T1",MID("DDNNLL",MOD($A5-1+'Calibración de turnos'!$D$16,6)+1,1),IF('Calibración de turnos'!$B$16="T2",IF(MOD($A5-1,7)+1<=5,IF(MOD(INT(($A5-1)/7)+'Calibración de turnos'!$D$16,2)=0,"M2","T2"),"L"),IF(MOD($A5-1,7)+1<=5,IF('Calibración de turnos'!$E$16=13,"M3b","M3a"),"L"))) -> M3a | N5: =IF('Calibración de turnos'!$B$17="T1",MID("DDNNLL",MOD($A5-1+'Calibración de turnos'!$D$17,6)+1,1),IF('Calibración de turnos'!$B$17="T2",IF(MOD($A5-1,7)+1<=5,IF(MOD(INT(($A5-1)/7)+'Calibración de turnos'!$D$17,2)=0,"M2","T2"),"L"),IF(MOD($A5-1,7)+1<=5,IF('Calibración de turnos'!$E$17=13,"M3b","M3a"),"L"))) -> M3a | O5: =IF('Calibración de turnos'!$B$18="T1",MID("DDNNLL",MOD($A5-1+'Calibración de turnos'!$D$18,6)+1,1),IF('Calibración de turnos'!$B$18="T2",IF(MOD($A5-1,7)+1<=5,IF(MOD(INT(($A5-1)/7)+'Calibración de turnos'!$D$18,2)=0,"M2","T2"),"L"),IF(MOD($A5-1,7)+1<=5,IF('Calibración de turnos'!$E$18=13,"M3b","M3a"),"L"))) -> M3b | P5: =IF('Calibración de turnos'!$B$19="T1",MID("DDNNLL",MOD($A5-1+'Calibración de turnos'!$D$19,6)+1,1),IF('Calibración de turnos'!$B$19="T2",IF(MOD($A5-1,7)+1<=5,IF(MOD(INT(($A5-1)/7)+'Calibración de turnos'!$D$19,2)=0,"M2","T2"),"L"),IF(MOD($A5-1,7)+1<=5,IF('Calibración de turnos'!$E$19=13,"M3b","M3a"),"L"))) -> M3a | Q5: =IF('Calibración de turnos'!$B$20="T1",MID("DDNNLL",MOD($A5-1+'Calibración de turnos'!$D$20,6)+1,1),IF('Calibración de turnos'!$B$20="T2",IF(MOD($A5-1,7)+1<=5,IF(MOD(INT(($A5-1)/7)+'Calibración de turnos'!$D$20,2)=0,"M2","T2"),"L"),IF(MOD($A5-1,7)+1<=5,IF('Calibración de turnos'!$E$20=13,"M3b","M3a"),"L"))) -> M3b | R5: =IF('Calibración de turnos'!$B$21="T1",MID("DDNNLL",MOD($A5-1+'Calibración de turnos'!$D$21,6)+1,1),IF('Calibración de turnos'!$B$21="T2",IF(MOD($A5-1,7)+1<=5,IF(MOD(INT(($A5-1)/7)+'Calibración de turnos'!$D$21,2)=0,"M2","T2"),"L"),IF(MOD($A5-1,7)+1<=5,IF('Calibración de turnos'!$E$21=13,"M3b","M3a"),"L"))) -> M3b | S5: =IF('Calibración de turnos'!$B$22="T1",MID("DDNNLL",MOD($A5-1+'Calibración de turnos'!$D$22,6)+1,1),IF('Calibración de turnos'!$B$22="T2",IF(MOD($A5-1,7)+1<=5,IF(MOD(INT(($A5-1)/7)+'Calibración de turnos'!$D$22,2)=0,"M2","T2"),"L"),IF(MOD($A5-1,7)+1<=5,IF('Calibración de turnos'!$E$22=13,"M3b","M3a"),"L"))) -> M3a | T5: =IF('Calibración de turnos'!$B$23="T1",MID("DDNNLL",MOD($A5-1+'Calibración de turnos'!$D$23,6)+1,1),IF('Calibración de turnos'!$B$23="T2",IF(MOD($A5-1,7)+1<=5,IF(MOD(INT(($A5-1)/7)+'Calibración de turnos'!$D$23,2)=0,"M2","T2"),"L"),IF(MOD($A5-1,7)+1<=5,IF('Calibración de turnos'!$E$23=13,"M3b","M3a"),"L"))) -> M3b | U5: =IF('Calibración de turnos'!$B$24="T1",MID("DDNNLL",MOD($A5-1+'Calibración de turnos'!$D$24,6)+1,1),IF('Calibración de turnos'!$B$24="T2",IF(MOD($A5-1,7)+1<=5,IF(MOD(INT(($A5-1)/7)+'Calibración de turnos'!$D$24,2)=0,"M2","T2"),"L"),IF(MOD($A5-1,7)+1<=5,IF('Calibración de turnos'!$E$24=13,"M3b","M3a"),"L"))) -> M3a | V5: =IF('Calibración de turnos'!$B$25="T1",MID("DDNNLL",MOD($A5-1+'Calibración de turnos'!$D$25,6)+1,1),IF('Calibración de turnos'!$B$25="T2",IF(MOD($A5-1,7)+1<=5,IF(MOD(INT(($A5-1)/7)+'Calibración de turnos'!$D$25,2)=0,"M2","T2"),"L"),IF(MOD($A5-1,7)+1<=5,IF('Calibración de turnos'!$E$25=13,"M3b","M3a"),"L"))) -> M3b
A6: 2 | B6: =CHOOSE(MOD(A6-1,7)+1,"lunes","martes","miércoles","jueves","viernes","sábado","domingo") -> martes | C6: =IF('Calibración de turnos'!$B$6="T1",MID("DDNNLL",MOD($A6-1+'Calibración de turnos'!$D$6,6)+1,1),IF('Calibración de turnos'!$B$6="T2",IF(MOD($A6-1,7)+1<=5,IF(MOD(INT(($A6-1)/7)+'Calibración de turnos'!$D$6,2)=0,"M2","T2"),"L"),IF(MOD($A6-1,7)+1<=5,IF('Calibración de turnos'!$E$6=13,"M3b","M3a"),"L"))) -> D | D6: =IF('Calibración de turnos'!$B$7="T1",MID("DDNNLL",MOD($A6-1+'Calibración de turnos'!$D$7,6)+1,1),IF('Calibración de turnos'!$B$7="T2",IF(MOD($A6-1,7)+1<=5,IF(MOD(INT(($A6-1)/7)+'Calibración de turnos'!$D$7,2)=0,"M2","T2"),"L"),IF(MOD($A6-1,7)+1<=5,IF('Calibración de turnos'!$E$7=13,"M3b","M3a"),"L"))) -> N | E6: =IF('Calibración de turnos'!$B$8="T1",MID("DDNNLL",MOD($A6-1+'Calibración de turnos'!$D$8,6)+1,1),IF('Calibración de turnos'!$B$8="T2",IF(MOD($A6-1,7)+1<=5,IF(MOD(INT(($A6-1)/7)+'Calibración de turnos'!$D$8,2)=0,"M2","T2"),"L"),IF(MOD($A6-1,7)+1<=5,IF('Calibración de turnos'!$E$8=13,"M3b","M3a"),"L"))) -> D | F6: =IF('Calibración de turnos'!$B$9="T1",MID("DDNNLL",MOD($A6-1+'Calibración de turnos'!$D$9,6)+1,1),IF('Calibración de turnos'!$B$9="T2",IF(MOD($A6-1,7)+1<=5,IF(MOD(INT(($A6-1)/7)+'Calibración de turnos'!$D$9,2)=0,"M2","T2"),"L"),IF(MOD($A6-1,7)+1<=5,IF('Calibración de turnos'!$E$9=13,"M3b","M3a"),"L"))) -> N | G6: =IF('Calibración de turnos'!$B$10="T1",MID("DDNNLL",MOD($A6-1+'Calibración de turnos'!$D$10,6)+1,1),IF('Calibración de turnos'!$B$10="T2",IF(MOD($A6-1,7)+1<=5,IF(MOD(INT(($A6-1)/7)+'Calibración de turnos'!$D$10,2)=0,"M2","T2"),"L"),IF(MOD($A6-1,7)+1<=5,IF('Calibración de turnos'!$E$10=13,"M3b","M3a"),"L"))) -> L | H6: =IF('Calibración de turnos'!$B$11="T1",MID("DDNNLL",MOD($A6-1+'Calibración de turnos'!$D$11,6)+1,1),IF('Calibración de turnos'!$B$11="T2",IF(MOD($A6-1,7)+1<=5,IF(MOD(INT(($A6-1)/7)+'Calibración de turnos'!$D$11,2)=0,"M2","T2"),"L"),IF(MOD($A6-1,7)+1<=5,IF('Calibración de turnos'!$E$11=13,"M3b","M3a"),"L"))) -> L | I6: =IF('Calibración de turnos'!$B$12="T1",MID("DDNNLL",MOD($A6-1+'Calibración de turnos'!$D$12,6)+1,1),IF('Calibración de turnos'!$B$12="T2",IF(MOD($A6-1,7)+1<=5,IF(MOD(INT(($A6-1)/7)+'Calibración de turnos'!$D$12,2)=0,"M2","T2"),"L"),IF(MOD($A6-1,7)+1<=5,IF('Calibración de turnos'!$E$12=13,"M3b","M3a"),"L"))) -> M2 | J6: =IF('Calibración de turnos'!$B$13="T1",MID("DDNNLL",MOD($A6-1+'Calibración de turnos'!$D$13,6)+1,1),IF('Calibración de turnos'!$B$13="T2",IF(MOD($A6-1,7)+1<=5,IF(MOD(INT(($A6-1)/7)+'Calibración de turnos'!$D$13,2)=0,"M2","T2"),"L"),IF(MOD($A6-1,7)+1<=5,IF('Calibración de turnos'!$E$13=13,"M3b","M3a"),"L"))) -> T2 | K6: =IF('Calibración de turnos'!$B$14="T1",MID("DDNNLL",MOD($A6-1+'Calibración de turnos'!$D$14,6)+1,1),IF('Calibración de turnos'!$B$14="T2",IF(MOD($A6-1,7)+1<=5,IF(MOD(INT(($A6-1)/7)+'Calibración de turnos'!$D$14,2)=0,"M2","T2"),"L"),IF(MOD($A6-1,7)+1<=5,IF('Calibración de turnos'!$E$14=13,"M3b","M3a"),"L"))) -> M2 | L6: =IF('Calibración de turnos'!$B$15="T1",MID("DDNNLL",MOD($A6-1+'Calibración de turnos'!$D$15,6)+1,1),IF('Calibración de turnos'!$B$15="T2",IF(MOD($A6-1,7)+1<=5,IF(MOD(INT(($A6-1)/7)+'Calibración de turnos'!$D$15,2)=0,"M2","T2"),"L"),IF(MOD($A6-1,7)+1<=5,IF('Calibración de turnos'!$E$15=13,"M3b","M3a"),"L"))) -> T2 | M6: =IF('Calibración de turnos'!$B$16="T1",MID("DDNNLL",MOD($A6-1+'Calibración de turnos'!$D$16,6)+1,1),IF('Calibración de turnos'!$B$16="T2",IF(MOD($A6-1,7)+1<=5,IF(MOD(INT(($A6-1)/7)+'Calibración de turnos'!$D$16,2)=0,"M2","T2"),"L"),IF(MOD($A6-1,7)+1<=5,IF('Calibración de turnos'!$E$16=13,"M3b","M3a"),"L"))) -> M3a | N6: =IF('Calibración de turnos'!$B$17="T1",MID("DDNNLL",MOD($A6-1+'Calibración de turnos'!$D$17,6)+1,1),IF('Calibración de turnos'!$B$17="T2",IF(MOD($A6-1,7)+1<=5,IF(MOD(INT(($A6-1)/7)+'Calibración de turnos'!$D$17,2)=0,"M2","T2"),"L"),IF(MOD($A6-1,7)+1<=5,IF('Calibración de turnos'!$E$17=13,"M3b","M3a"),"L"))) -> M3a | O6: =IF('Calibración de turnos'!$B$18="T1",MID("DDNNLL",MOD($A6-1+'Calibración de turnos'!$D$18,6)+1,1),IF('Calibración de turnos'!$B$18="T2",IF(MOD($A6-1,7)+1<=5,IF(MOD(INT(($A6-1)/7)+'Calibración de turnos'!$D$18,2)=0,"M2","T2"),"L"),IF(MOD($A6-1,7)+1<=5,IF('Calibración de turnos'!$E$18=13,"M3b","M3a"),"L"))) -> M3b | P6: =IF('Calibración de turnos'!$B$19="T1",MID("DDNNLL",MOD($A6-1+'Calibración de turnos'!$D$19,6)+1,1),IF('Calibración de turnos'!$B$19="T2",IF(MOD($A6-1,7)+1<=5,IF(MOD(INT(($A6-1)/7)+'Calibración de turnos'!$D$19,2)=0,"M2","T2"),"L"),IF(MOD($A6-1,7)+1<=5,IF('Calibración de turnos'!$E$19=13,"M3b","M3a"),"L"))) -> M3a | Q6: =IF('Calibración de turnos'!$B$20="T1",MID("DDNNLL",MOD($A6-1+'Calibración de turnos'!$D$20,6)+1,1),IF('Calibración de turnos'!$B$20="T2",IF(MOD($A6-1,7)+1<=5,IF(MOD(INT(($A6-1)/7)+'Calibración de turnos'!$D$20,2)=0,"M2","T2"),"L"),IF(MOD($A6-1,7)+1<=5,IF('Calibración de turnos'!$E$20=13,"M3b","M3a"),"L"))) -> M3b | R6: =IF('Calibración de turnos'!$B$21="T1",MID("DDNNLL",MOD($A6-1+'Calibración de turnos'!$D$21,6)+1,1),IF('Calibración de turnos'!$B$21="T2",IF(MOD($A6-1,7)+1<=5,IF(MOD(INT(($A6-1)/7)+'Calibración de turnos'!$D$21,2)=0,"M2","T2"),"L"),IF(MOD($A6-1,7)+1<=5,IF('Calibración de turnos'!$E$21=13,"M3b","M3a"),"L"))) -> M3b | S6: =IF('Calibración de turnos'!$B$22="T1",MID("DDNNLL",MOD($A6-1+'Calibración de turnos'!$D$22,6)+1,1),IF('Calibración de turnos'!$B$22="T2",IF(MOD($A6-1,7)+1<=5,IF(MOD(INT(($A6-1)/7)+'Calibración de turnos'!$D$22,2)=0,"M2","T2"),"L"),IF(MOD($A6-1,7)+1<=5,IF('Calibración de turnos'!$E$22=13,"M3b","M3a"),"L"))) -> M3a | T6: =IF('Calibración de turnos'!$B$23="T1",MID("DDNNLL",MOD($A6-1+'Calibración de turnos'!$D$23,6)+1,1),IF('Calibración de turnos'!$B$23="T2",IF(MOD($A6-1,7)+1<=5,IF(MOD(INT(($A6-1)/7)+'Calibración de turnos'!$D$23,2)=0,"M2","T2"),"L"),IF(MOD($A6-1,7)+1<=5,IF('Calibración de turnos'!$E$23=13,"M3b","M3a"),"L"))) -> M3b | U6: =IF('Calibración de turnos'!$B$24="T1",MID("DDNNLL",MOD($A6-1+'Calibración de turnos'!$D$24,6)+1,1),IF('Calibración de turnos'!$B$24="T2",IF(MOD($A6-1,7)+1<=5,IF(MOD(INT(($A6-1)/7)+'Calibración de turnos'!$D$24,2)=0,"M2","T2"),"L"),IF(MOD($A6-1,7)+1<=5,IF('Calibración de turnos'!$E$24=13,"M3b","M3a"),"L"))) -> M3a | V6: =IF('Calibración de turnos'!$B$25="T1",MID("DDNNLL",MOD($A6-1+'Calibración de turnos'!$D$25,6)+1,1),IF('Calibración de turnos'!$B$25="T2",IF(MOD($A6-1,7)+1<=5,IF(MOD(INT(($A6-1)/7)+'Calibración de turnos'!$D$25,2)=0,"M2","T2"),"L"),IF(MOD($A6-1,7)+1<=5,IF('Calibración de turnos'!$E$25=13,"M3b","M3a"),"L"))) -> M3b
A7: 3 | B7: =CHOOSE(MOD(A7-1,7)+1,"lunes","martes","miércoles","jueves","viernes","sábado","domingo") -> miércoles | C7: =IF('Calibración de turnos'!$B$6="T1",MID("DDNNLL",MOD($A7-1+'Calibración de turnos'!$D$6,6)+1,1),IF('Calibración de turnos'!$B$6="T2",IF(MOD($A7-1,7)+1<=5,IF(MOD(INT(($A7-1)/7)+'Calibración de turnos'!$D$6,2)=0,"M2","T2"),"L"),IF(MOD($A7-1,7)+1<=5,IF('Calibración de turnos'!$E$6=13,"M3b","M3a"),"L"))) -> N | D7: =IF('Calibración de turnos'!$B$7="T1",MID("DDNNLL",MOD($A7-1+'Calibración de turnos'!$D$7,6)+1,1),IF('Calibración de turnos'!$B$7="T2",IF(MOD($A7-1,7)+1<=5,IF(MOD(INT(($A7-1)/7)+'Calibración de turnos'!$D$7,2)=0,"M2","T2"),"L"),IF(MOD($A7-1,7)+1<=5,IF('Calibración de turnos'!$E$7=13,"M3b","M3a"),"L"))) -> L | E7: =IF('Calibración de turnos'!$B$8="T1",MID("DDNNLL",MOD($A7-1+'Calibración de turnos'!$D$8,6)+1,1),IF('Calibración de turnos'!$B$8="T2",IF(MOD($A7-1,7)+1<=5,IF(MOD(INT(($A7-1)/7)+'Calibración de turnos'!$D$8,2)=0,"M2","T2"),"L"),IF(MOD($A7-1,7)+1<=5,IF('Calibración de turnos'!$E$8=13,"M3b","M3a"),"L"))) -> N | F7: =IF('Calibración de turnos'!$B$9="T1",MID("DDNNLL",MOD($A7-1+'Calibración de turnos'!$D$9,6)+1,1),IF('Calibración de turnos'!$B$9="T2",IF(MOD($A7-1,7)+1<=5,IF(MOD(INT(($A7-1)/7)+'Calibración de turnos'!$D$9,2)=0,"M2","T2"),"L"),IF(MOD($A7-1,7)+1<=5,IF('Calibración de turnos'!$E$9=13,"M3b","M3a"),"L"))) -> L | G7: =IF('Calibración de turnos'!$B$10="T1",MID("DDNNLL",MOD($A7-1+'Calibración de turnos'!$D$10,6)+1,1),IF('Calibración de turnos'!$B$10="T2",IF(MOD($A7-1,7)+1<=5,IF(MOD(INT(($A7-1)/7)+'Calibración de turnos'!$D$10,2)=0,"M2","T2"),"L"),IF(MOD($A7-1,7)+1<=5,IF('Calibración de turnos'!$E$10=13,"M3b","M3a"),"L"))) -> D | H7: =IF('Calibración de turnos'!$B$11="T1",MID("DDNNLL",MOD($A7-1+'Calibración de turnos'!$D$11,6)+1,1),IF('Calibración de turnos'!$B$11="T2",IF(MOD($A7-1,7)+1<=5,IF(MOD(INT(($A7-1)/7)+'Calibración de turnos'!$D$11,2)=0,"M2","T2"),"L"),IF(MOD($A7-1,7)+1<=5,IF('Calibración de turnos'!$E$11=13,"M3b","M3a"),"L"))) -> D | I7: =IF('Calibración de turnos'!$B$12="T1",MID("DDNNLL",MOD($A7-1+'Calibración de turnos'!$D$12,6)+1,1),IF('Calibración de turnos'!$B$12="T2",IF(MOD($A7-1,7)+1<=5,IF(MOD(INT(($A7-1)/7)+'Calibración de turnos'!$D$12,2)=0,"M2","T2"),"L"),IF(MOD($A7-1,7)+1<=5,IF('Calibración de turnos'!$E$12=13,"M3b","M3a"),"L"))) -> M2 | J7: =IF('Calibración de turnos'!$B$13="T1",MID("DDNNLL",MOD($A7-1+'Calibración de turnos'!$D$13,6)+1,1),IF('Calibración de turnos'!$B$13="T2",IF(MOD($A7-1,7)+1<=5,IF(MOD(INT(($A7-1)/7)+'Calibración de turnos'!$D$13,2)=0,"M2","T2"),"L"),IF(MOD($A7-1,7)+1<=5,IF('Calibración de turnos'!$E$13=13,"M3b","M3a"),"L"))) -> T2 | K7: =IF('Calibración de turnos'!$B$14="T1",MID("DDNNLL",MOD($A7-1+'Calibración de turnos'!$D$14,6)+1,1),IF('Calibración de turnos'!$B$14="T2",IF(MOD($A7-1,7)+1<=5,IF(MOD(INT(($A7-1)/7)+'Calibración de turnos'!$D$14,2)=0,"M2","T2"),"L"),IF(MOD($A7-1,7)+1<=5,IF('Calibración de turnos'!$E$14=13,"M3b","M3a"),"L"))) -> M2 | L7: =IF('Calibración de turnos'!$B$15="T1",MID("DDNNLL",MOD($A7-1+'Calibración de turnos'!$D$15,6)+1,1),IF('Calibración de turnos'!$B$15="T2",IF(MOD($A7-1,7)+1<=5,IF(MOD(INT(($A7-1)/7)+'Calibración de turnos'!$D$15,2)=0,"M2","T2"),"L"),IF(MOD($A7-1,7)+1<=5,IF('Calibración de turnos'!$E$15=13,"M3b","M3a"),"L"))) -> T2 | M7: =IF('Calibración de turnos'!$B$16="T1",MID("DDNNLL",MOD($A7-1+'Calibración de turnos'!$D$16,6)+1,1),IF('Calibración de turnos'!$B$16="T2",IF(MOD($A7-1,7)+1<=5,IF(MOD(INT(($A7-1)/7)+'Calibración de turnos'!$D$16,2)=0,"M2","T2"),"L"),IF(MOD($A7-1,7)+1<=5,IF('Calibración de turnos'!$E$16=13,"M3b","M3a"),"L"))) -> M3a | N7: =IF('Calibración de turnos'!$B$17="T1",MID("DDNNLL",MOD($A7-1+'Calibración de turnos'!$D$17,6)+1,1),IF('Calibración de turnos'!$B$17="T2",IF(MOD($A7-1,7)+1<=5,IF(MOD(INT(($A7-1)/7)+'Calibración de turnos'!$D$17,2)=0,"M2","T2"),"L"),IF(MOD($A7-1,7)+1<=5,IF('Calibración de turnos'!$E$17=13,"M3b","M3a"),"L"))) -> M3a | O7: =IF('Calibración de turnos'!$B$18="T1",MID("DDNNLL",MOD($A7-1+'Calibración de turnos'!$D$18,6)+1,1),IF('Calibración de turnos'!$B$18="T2",IF(MOD($A7-1,7)+1<=5,IF(MOD(INT(($A7-1)/7)+'Calibración de turnos'!$D$18,2)=0,"M2","T2"),"L"),IF(MOD($A7-1,7)+1<=5,IF('Calibración de turnos'!$E$18=13,"M3b","M3a"),"L"))) -> M3b | P7: =IF('Calibración de turnos'!$B$19="T1",MID("DDNNLL",MOD($A7-1+'Calibración de turnos'!$D$19,6)+1,1),IF('Calibración de turnos'!$B$19="T2",IF(MOD($A7-1,7)+1<=5,IF(MOD(INT(($A7-1)/7)+'Calibración de turnos'!$D$19,2)=0,"M2","T2"),"L"),IF(MOD($A7-1,7)+1<=5,IF('Calibración de turnos'!$E$19=13,"M3b","M3a"),"L"))) -> M3a | Q7: =IF('Calibración de turnos'!$B$20="T1",MID("DDNNLL",MOD($A7-1+'Calibración de turnos'!$D$20,6)+1,1),IF('Calibración de turnos'!$B$20="T2",IF(MOD($A7-1,7)+1<=5,IF(MOD(INT(($A7-1)/7)+'Calibración de turnos'!$D$20,2)=0,"M2","T2"),"L"),IF(MOD($A7-1,7)+1<=5,IF('Calibración de turnos'!$E$20=13,"M3b","M3a"),"L"))) -> M3b | R7: =IF('Calibración de turnos'!$B$21="T1",MID("DDNNLL",MOD($A7-1+'Calibración de turnos'!$D$21,6)+1,1),IF('Calibración de turnos'!$B$21="T2",IF(MOD($A7-1,7)+1<=5,IF(MOD(INT(($A7-1)/7)+'Calibración de turnos'!$D$21,2)=0,"M2","T2"),"L"),IF(MOD($A7-1,7)+1<=5,IF('Calibración de turnos'!$E$21=13,"M3b","M3a"),"L"))) -> M3b | S7: =IF('Calibración de turnos'!$B$22="T1",MID("DDNNLL",MOD($A7-1+'Calibración de turnos'!$D$22,6)+1,1),IF('Calibración de turnos'!$B$22="T2",IF(MOD($A7-1,7)+1<=5,IF(MOD(INT(($A7-1)/7)+'Calibración de turnos'!$D$22,2)=0,"M2","T2"),"L"),IF(MOD($A7-1,7)+1<=5,IF('Calibración de turnos'!$E$22=13,"M3b","M3a"),"L"))) -> M3a | T7: =IF('Calibración de turnos'!$B$23="T1",MID("DDNNLL",MOD($A7-1+'Calibración de turnos'!$D$23,6)+1,1),IF('Calibración de turnos'!$B$23="T2",IF(MOD($A7-1,7)+1<=5,IF(MOD(INT(($A7-1)/7)+'Calibración de turnos'!$D$23,2)=0,"M2","T2"),"L"),IF(MOD($A7-1,7)+1<=5,IF('Calibración de turnos'!$E$23=13,"M3b","M3a"),"L"))) -> M3b | U7: =IF('Calibración de turnos'!$B$24="T1",MID("DDNNLL",MOD($A7-1+'Calibración de turnos'!$D$24,6)+1,1),IF('Calibración de turnos'!$B$24="T2",IF(MOD($A7-1,7)+1<=5,IF(MOD(INT(($A7-1)/7)+'Calibración de turnos'!$D$24,2)=0,"M2","T2"),"L"),IF(MOD($A7-1,7)+1<=5,IF('Calibración de turnos'!$E$24=13,"M3b","M3a"),"L"))) -> M3a | V7: =IF('Calibración de turnos'!$B$25="T1",MID("DDNNLL",MOD($A7-1+'Calibración de turnos'!$D$25,6)+1,1),IF('Calibración de turnos'!$B$25="T2",IF(MOD($A7-1,7)+1<=5,IF(MOD(INT(($A7-1)/7)+'Calibración de turnos'!$D$25,2)=0,"M2","T2"),"L"),IF(MOD($A7-1,7)+1<=5,IF('Calibración de turnos'!$E$25=13,"M3b","M3a"),"L"))) -> M3b
A8: 4 | B8: =CHOOSE(MOD(A8-1,7)+1,"lunes","martes","miércoles","jueves","viernes","sábado","domingo") -> jueves | C8: =IF('Calibración de turnos'!$B$6="T1",MID("DDNNLL",MOD($A8-1+'Calibración de turnos'!$D$6,6)+1,1),IF('Calibración de turnos'!$B$6="T2",IF(MOD($A8-1,7)+1<=5,IF(MOD(INT(($A8-1)/7)+'Calibración de turnos'!$D$6,2)=0,"M2","T2"),"L"),IF(MOD($A8-1,7)+1<=5,IF('Calibración de turnos'!$E$6=13,"M3b","M3a"),"L"))) -> N | D8: =IF('Calibración de turnos'!$B$7="T1",MID("DDNNLL",MOD($A8-1+'Calibración de turnos'!$D$7,6)+1,1),IF('Calibración de turnos'!$B$7="T2",IF(MOD($A8-1,7)+1<=5,IF(MOD(INT(($A8-1)/7)+'Calibración de turnos'!$D$7,2)=0,"M2","T2"),"L"),IF(MOD($A8-1,7)+1<=5,IF('Calibración de turnos'!$E$7=13,"M3b","M3a"),"L"))) -> L | E8: =IF('Calibración de turnos'!$B$8="T1",MID("DDNNLL",MOD($A8-1+'Calibración de turnos'!$D$8,6)+1,1),IF('Calibración de turnos'!$B$8="T2",IF(MOD($A8-1,7)+1<=5,IF(MOD(INT(($A8-1)/7)+'Calibración de turnos'!$D$8,2)=0,"M2","T2"),"L"),IF(MOD($A8-1,7)+1<=5,IF('Calibración de turnos'!$E$8=13,"M3b","M3a"),"L"))) -> N | F8: =IF('Calibración de turnos'!$B$9="T1",MID("DDNNLL",MOD($A8-1+'Calibración de turnos'!$D$9,6)+1,1),IF('Calibración de turnos'!$B$9="T2",IF(MOD($A8-1,7)+1<=5,IF(MOD(INT(($A8-1)/7)+'Calibración de turnos'!$D$9,2)=0,"M2","T2"),"L"),IF(MOD($A8-1,7)+1<=5,IF('Calibración de turnos'!$E$9=13,"M3b","M3a"),"L"))) -> L | G8: =IF('Calibración de turnos'!$B$10="T1",MID("DDNNLL",MOD($A8-1+'Calibración de turnos'!$D$10,6)+1,1),IF('Calibración de turnos'!$B$10="T2",IF(MOD($A8-1,7)+1<=5,IF(MOD(INT(($A8-1)/7)+'Calibración de turnos'!$D$10,2)=0,"M2","T2"),"L"),IF(MOD($A8-1,7)+1<=5,IF('Calibración de turnos'!$E$10=13,"M3b","M3a"),"L"))) -> D | H8: =IF('Calibración de turnos'!$B$11="T1",MID("DDNNLL",MOD($A8-1+'Calibración de turnos'!$D$11,6)+1,1),IF('Calibración de turnos'!$B$11="T2",IF(MOD($A8-1,7)+1<=5,IF(MOD(INT(($A8-1)/7)+'Calibración de turnos'!$D$11,2)=0,"M2","T2"),"L"),IF(MOD($A8-1,7)+1<=5,IF('Calibración de turnos'!$E$11=13,"M3b","M3a"),"L"))) -> D | I8: =IF('Calibración de turnos'!$B$12="T1",MID("DDNNLL",MOD($A8-1+'Calibración de turnos'!$D$12,6)+1,1),IF('Calibración de turnos'!$B$12="T2",IF(MOD($A8-1,7)+1<=5,IF(MOD(INT(($A8-1)/7)+'Calibración de turnos'!$D$12,2)=0,"M2","T2"),"L"),IF(MOD($A8-1,7)+1<=5,IF('Calibración de turnos'!$E$12=13,"M3b","M3a"),"L"))) -> M2 | J8: =IF('Calibración de turnos'!$B$13="T1",MID("DDNNLL",MOD($A8-1+'Calibración de turnos'!$D$13,6)+1,1),IF('Calibración de turnos'!$B$13="T2",IF(MOD($A8-1,7)+1<=5,IF(MOD(INT(($A8-1)/7)+'Calibración de turnos'!$D$13,2)=0,"M2","T2"),"L"),IF(MOD($A8-1,7)+1<=5,IF('Calibración de turnos'!$E$13=13,"M3b","M3a"),"L"))) -> T2 | K8: =IF('Calibración de turnos'!$B$14="T1",MID("DDNNLL",MOD($A8-1+'Calibración de turnos'!$D$14,6)+1,1),IF('Calibración de turnos'!$B$14="T2",IF(MOD($A8-1,7)+1<=5,IF(MOD(INT(($A8-1)/7)+'Calibración de turnos'!$D$14,2)=0,"M2","T2"),"L"),IF(MOD($A8-1,7)+1<=5,IF('Calibración de turnos'!$E$14=13,"M3b","M3a"),"L"))) -> M2 | L8: =IF('Calibración de turnos'!$B$15="T1",MID("DDNNLL",MOD($A8-1+'Calibración de turnos'!$D$15,6)+1,1),IF('Calibración de turnos'!$B$15="T2",IF(MOD($A8-1,7)+1<=5,IF(MOD(INT(($A8-1)/7)+'Calibración de turnos'!$D$15,2)=0,"M2","T2"),"L"),IF(MOD($A8-1,7)+1<=5,IF('Calibración de turnos'!$E$15=13,"M3b","M3a"),"L"))) -> T2 | M8: =IF('Calibración de turnos'!$B$16="T1",MID("DDNNLL",MOD($A8-1+'Calibración de turnos'!$D$16,6)+1,1),IF('Calibración de turnos'!$B$16="T2",IF(MOD($A8-1,7)+1<=5,IF(MOD(INT(($A8-1)/7)+'Calibración de turnos'!$D$16,2)=0,"M2","T2"),"L"),IF(MOD($A8-1,7)+1<=5,IF('Calibración de turnos'!$E$16=13,"M3b","M3a"),"L"))) -> M3a | N8: =IF('Calibración de turnos'!$B$17="T1",MID("DDNNLL",MOD($A8-1+'Calibración de turnos'!$D$17,6)+1,1),IF('Calibración de turnos'!$B$17="T2",IF(MOD($A8-1,7)+1<=5,IF(MOD(INT(($A8-1)/7)+'Calibración de turnos'!$D$17,2)=0,"M2","T2"),"L"),IF(MOD($A8-1,7)+1<=5,IF('Calibración de turnos'!$E$17=13,"M3b","M3a"),"L"))) -> M3a | O8: =IF('Calibración de turnos'!$B$18="T1",MID("DDNNLL",MOD($A8-1+'Calibración de turnos'!$D$18,6)+1,1),IF('Calibración de turnos'!$B$18="T2",IF(MOD($A8-1,7)+1<=5,IF(MOD(INT(($A8-1)/7)+'Calibración de turnos'!$D$18,2)=0,"M2","T2"),"L"),IF(MOD($A8-1,7)+1<=5,IF('Calibración de turnos'!$E$18=13,"M3b","M3a"),"L"))) -> M3b | P8: =IF('Calibración de turnos'!$B$19="T1",MID("DDNNLL",MOD($A8-1+'Calibración de turnos'!$D$19,6)+1,1),IF('Calibración de turnos'!$B$19="T2",IF(MOD($A8-1,7)+1<=5,IF(MOD(INT(($A8-1)/7)+'Calibración de turnos'!$D$19,2)=0,"M2","T2"),"L"),IF(MOD($A8-1,7)+1<=5,IF('Calibración de turnos'!$E$19=13,"M3b","M3a"),"L"))) -> M3a | Q8: =IF('Calibración de turnos'!$B$20="T1",MID("DDNNLL",MOD($A8-1+'Calibración de turnos'!$D$20,6)+1,1),IF('Calibración de turnos'!$B$20="T2",IF(MOD($A8-1,7)+1<=5,IF(MOD(INT(($A8-1)/7)+'Calibración de turnos'!$D$20,2)=0,"M2","T2"),"L"),IF(MOD($A8-1,7)+1<=5,IF('Calibración de turnos'!$E$20=13,"M3b","M3a"),"L"))) -> M3b | R8: =IF('Calibración de turnos'!$B$21="T1",MID("DDNNLL",MOD($A8-1+'Calibración de turnos'!$D$21,6)+1,1),IF('Calibración de turnos'!$B$21="T2",IF(MOD($A8-1,7)+1<=5,IF(MOD(INT(($A8-1)/7)+'Calibración de turnos'!$D$21,2)=0,"M2","T2"),"L"),IF(MOD($A8-1,7)+1<=5,IF('Calibración de turnos'!$E$21=13,"M3b","M3a"),"L"))) -> M3b | S8: =IF('Calibración de turnos'!$B$22="T1",MID("DDNNLL",MOD($A8-1+'Calibración de turnos'!$D$22,6)+1,1),IF('Calibración de turnos'!$B$22="T2",IF(MOD($A8-1,7)+1<=5,IF(MOD(INT(($A8-1)/7)+'Calibración de turnos'!$D$22,2)=0,"M2","T2"),"L"),IF(MOD($A8-1,7)+1<=5,IF('Calibración de turnos'!$E$22=13,"M3b","M3a"),"L"))) -> M3a | T8: =IF('Calibración de turnos'!$B$23="T1",MID("DDNNLL",MOD($A8-1+'Calibración de turnos'!$D$23,6)+1,1),IF('Calibración de turnos'!$B$23="T2",IF(MOD($A8-1,7)+1<=5,IF(MOD(INT(($A8-1)/7)+'Calibración de turnos'!$D$23,2)=0,"M2","T2"),"L"),IF(MOD($A8-1,7)+1<=5,IF('Calibración de turnos'!$E$23=13,"M3b","M3a"),"L"))) -> M3b | U8: =IF('Calibración de turnos'!$B$24="T1",MID("DDNNLL",MOD($A8-1+'Calibración de turnos'!$D$24,6)+1,1),IF('Calibración de turnos'!$B$24="T2",IF(MOD($A8-1,7)+1<=5,IF(MOD(INT(($A8-1)/7)+'Calibración de turnos'!$D$24,2)=0,"M2","T2"),"L"),IF(MOD($A8-1,7)+1<=5,IF('Calibración de turnos'!$E$24=13,"M3b","M3a"),"L"))) -> M3a | V8: =IF('Calibración de turnos'!$B$25="T1",MID("DDNNLL",MOD($A8-1+'Calibración de turnos'!$D$25,6)+1,1),IF('Calibración de turnos'!$B$25="T2",IF(MOD($A8-1,7)+1<=5,IF(MOD(INT(($A8-1)/7)+'Calibración de turnos'!$D$25,2)=0,"M2","T2"),"L"),IF(MOD($A8-1,7)+1<=5,IF('Calibración de turnos'!$E$25=13,"M3b","M3a"),"L"))) -> M3b
A9: 5 | B9: =CHOOSE(MOD(A9-1,7)+1,"lunes","martes","miércoles","jueves","viernes","sábado","domingo") -> viernes | C9: =IF('Calibración de turnos'!$B$6="T1",MID("DDNNLL",MOD($A9-1+'Calibración de turnos'!$D$6,6)+1,1),IF('Calibración de turnos'!$B$6="T2",IF(MOD($A9-1,7)+1<=5,IF(MOD(INT(($A9-1)/7)+'Calibración de turnos'!$D$6,2)=0,"M2","T2"),"L"),IF(MOD($A9-1,7)+1<=5,IF('Calibración de turnos'!$E$6=13,"M3b","M3a"),"L"))) -> L | D9: =IF('Calibración de turnos'!$B$7="T1",MID("DDNNLL",MOD($A9-1+'Calibración de turnos'!$D$7,6)+1,1),IF('Calibración de turnos'!$B$7="T2",IF(MOD($A9-1,7)+1<=5,IF(MOD(INT(($A9-1)/7)+'Calibración de turnos'!$D$7,2)=0,"M2","T2"),"L"),IF(MOD($A9-1,7)+1<=5,IF('Calibración de turnos'!$E$7=13,"M3b","M3a"),"L"))) -> D | E9: =IF('Calibración de turnos'!$B$8="T1",MID("DDNNLL",MOD($A9-1+'Calibración de turnos'!$D$8,6)+1,1),IF('Calibración de turnos'!$B$8="T2",IF(MOD($A9-1,7)+1<=5,IF(MOD(INT(($A9-1)/7)+'Calibración de turnos'!$D$8,2)=0,"M2","T2"),"L"),IF(MOD($A9-1,7)+1<=5,IF('Calibración de turnos'!$E$8=13,"M3b","M3a"),"L"))) -> L | F9: =IF('Calibración de turnos'!$B$9="T1",MID("DDNNLL",MOD($A9-1+'Calibración de turnos'!$D$9,6)+1,1),IF('Calibración de turnos'!$B$9="T2",IF(MOD($A9-1,7)+1<=5,IF(MOD(INT(($A9-1)/7)+'Calibración de turnos'!$D$9,2)=0,"M2","T2"),"L"),IF(MOD($A9-1,7)+1<=5,IF('Calibración de turnos'!$E$9=13,"M3b","M3a"),"L"))) -> D | G9: =IF('Calibración de turnos'!$B$10="T1",MID("DDNNLL",MOD($A9-1+'Calibración de turnos'!$D$10,6)+1,1),IF('Calibración de turnos'!$B$10="T2",IF(MOD($A9-1,7)+1<=5,IF(MOD(INT(($A9-1)/7)+'Calibración de turnos'!$D$10,2)=0,"M2","T2"),"L"),IF(MOD($A9-1,7)+1<=5,IF('Calibración de turnos'!$E$10=13,"M3b","M3a"),"L"))) -> N | H9: =IF('Calibración de turnos'!$B$11="T1",MID("DDNNLL",MOD($A9-1+'Calibración de turnos'!$D$11,6)+1,1),IF('Calibración de turnos'!$B$11="T2",IF(MOD($A9-1,7)+1<=5,IF(MOD(INT(($A9-1)/7)+'Calibración de turnos'!$D$11,2)=0,"M2","T2"),"L"),IF(MOD($A9-1,7)+1<=5,IF('Calibración de turnos'!$E$11=13,"M3b","M3a"),"L"))) -> N | I9: =IF('Calibración de turnos'!$B$12="T1",MID("DDNNLL",MOD($A9-1+'Calibración de turnos'!$D$12,6)+1,1),IF('Calibración de turnos'!$B$12="T2",IF(MOD($A9-1,7)+1<=5,IF(MOD(INT(($A9-1)/7)+'Calibración de turnos'!$D$12,2)=0,"M2","T2"),"L"),IF(MOD($A9-1,7)+1<=5,IF('Calibración de turnos'!$E$12=13,"M3b","M3a"),"L"))) -> M2 | J9: =IF('Calibración de turnos'!$B$13="T1",MID("DDNNLL",MOD($A9-1+'Calibración de turnos'!$D$13,6)+1,1),IF('Calibración de turnos'!$B$13="T2",IF(MOD($A9-1,7)+1<=5,IF(MOD(INT(($A9-1)/7)+'Calibración de turnos'!$D$13,2)=0,"M2","T2"),"L"),IF(MOD($A9-1,7)+1<=5,IF('Calibración de turnos'!$E$13=13,"M3b","M3a"),"L"))) -> T2 | K9: =IF('Calibración de turnos'!$B$14="T1",MID("DDNNLL",MOD($A9-1+'Calibración de turnos'!$D$14,6)+1,1),IF('Calibración de turnos'!$B$14="T2",IF(MOD($A9-1,7)+1<=5,IF(MOD(INT(($A9-1)/7)+'Calibración de turnos'!$D$14,2)=0,"M2","T2"),"L"),IF(MOD($A9-1,7)+1<=5,IF('Calibración de turnos'!$E$14=13,"M3b","M3a"),"L"))) -> M2 | L9: =IF('Calibración de turnos'!$B$15="T1",MID("DDNNLL",MOD($A9-1+'Calibración de turnos'!$D$15,6)+1,1),IF('Calibración de turnos'!$B$15="T2",IF(MOD($A9-1,7)+1<=5,IF(MOD(INT(($A9-1)/7)+'Calibración de turnos'!$D$15,2)=0,"M2","T2"),"L"),IF(MOD($A9-1,7)+1<=5,IF('Calibración de turnos'!$E$15=13,"M3b","M3a"),"L"))) -> T2 | M9: =IF('Calibración de turnos'!$B$16="T1",MID("DDNNLL",MOD($A9-1+'Calibración de turnos'!$D$16,6)+1,1),IF('Calibración de turnos'!$B$16="T2",IF(MOD($A9-1,7)+1<=5,IF(MOD(INT(($A9-1)/7)+'Calibración de turnos'!$D$16,2)=0,"M2","T2"),"L"),IF(MOD($A9-1,7)+1<=5,IF('Calibración de turnos'!$E$16=13,"M3b","M3a"),"L"))) -> M3a | N9: =IF('Calibración de turnos'!$B$17="T1",MID("DDNNLL",MOD($A9-1+'Calibración de turnos'!$D$17,6)+1,1),IF('Calibración de turnos'!$B$17="T2",IF(MOD($A9-1,7)+1<=5,IF(MOD(INT(($A9-1)/7)+'Calibración de turnos'!$D$17,2)=0,"M2","T2"),"L"),IF(MOD($A9-1,7)+1<=5,IF('Calibración de turnos'!$E$17=13,"M3b","M3a"),"L"))) -> M3a | O9: =IF('Calibración de turnos'!$B$18="T1",MID("DDNNLL",MOD($A9-1+'Calibración de turnos'!$D$18,6)+1,1),IF('Calibración de turnos'!$B$18="T2",IF(MOD($A9-1,7)+1<=5,IF(MOD(INT(($A9-1)/7)+'Calibración de turnos'!$D$18,2)=0,"M2","T2"),"L"),IF(MOD($A9-1,7)+1<=5,IF('Calibración de turnos'!$E$18=13,"M3b","M3a"),"L"))) -> M3b | P9: =IF('Calibración de turnos'!$B$19="T1",MID("DDNNLL",MOD($A9-1+'Calibración de turnos'!$D$19,6)+1,1),IF('Calibración de turnos'!$B$19="T2",IF(MOD($A9-1,7)+1<=5,IF(MOD(INT(($A9-1)/7)+'Calibración de turnos'!$D$19,2)=0,"M2","T2"),"L"),IF(MOD($A9-1,7)+1<=5,IF('Calibración de turnos'!$E$19=13,"M3b","M3a"),"L"))) -> M3a | Q9: =IF('Calibración de turnos'!$B$20="T1",MID("DDNNLL",MOD($A9-1+'Calibración de turnos'!$D$20,6)+1,1),IF('Calibración de turnos'!$B$20="T2",IF(MOD($A9-1,7)+1<=5,IF(MOD(INT(($A9-1)/7)+'Calibración de turnos'!$D$20,2)=0,"M2","T2"),"L"),IF(MOD($A9-1,7)+1<=5,IF('Calibración de turnos'!$E$20=13,"M3b","M3a"),"L"))) -> M3b | R9: =IF('Calibración de turnos'!$B$21="T1",MID("DDNNLL",MOD($A9-1+'Calibración de turnos'!$D$21,6)+1,1),IF('Calibración de turnos'!$B$21="T2",IF(MOD($A9-1,7)+1<=5,IF(MOD(INT(($A9-1)/7)+'Calibración de turnos'!$D$21,2)=0,"M2","T2"),"L"),IF(MOD($A9-1,7)+1<=5,IF('Calibración de turnos'!$E$21=13,"M3b","M3a"),"L"))) -> M3b | S9: =IF('Calibración de turnos'!$B$22="T1",MID("DDNNLL",MOD($A9-1+'Calibración de turnos'!$D$22,6)+1,1),IF('Calibración de turnos'!$B$22="T2",IF(MOD($A9-1,7)+1<=5,IF(MOD(INT(($A9-1)/7)+'Calibración de turnos'!$D$22,2)=0,"M2","T2"),"L"),IF(MOD($A9-1,7)+1<=5,IF('Calibración de turnos'!$E$22=13,"M3b","M3a"),"L"))) -> M3a | T9: =IF('Calibración de turnos'!$B$23="T1",MID("DDNNLL",MOD($A9-1+'Calibración de turnos'!$D$23,6)+1,1),IF('Calibración de turnos'!$B$23="T2",IF(MOD($A9-1,7)+1<=5,IF(MOD(INT(($A9-1)/7)+'Calibración de turnos'!$D$23,2)=0,"M2","T2"),"L"),IF(MOD($A9-1,7)+1<=5,IF('Calibración de turnos'!$E$23=13,"M3b","M3a"),"L"))) -> M3b | U9: =IF('Calibración de turnos'!$B$24="T1",MID("DDNNLL",MOD($A9-1+'Calibración de turnos'!$D$24,6)+1,1),IF('Calibración de turnos'!$B$24="T2",IF(MOD($A9-1,7)+1<=5,IF(MOD(INT(($A9-1)/7)+'Calibración de turnos'!$D$24,2)=0,"M2","T2"),"L"),IF(MOD($A9-1,7)+1<=5,IF('Calibración de turnos'!$E$24=13,"M3b","M3a"),"L"))) -> M3a | V9: =IF('Calibración de turnos'!$B$25="T1",MID("DDNNLL",MOD($A9-1+'Calibración de turnos'!$D$25,6)+1,1),IF('Calibración de turnos'!$B$25="T2",IF(MOD($A9-1,7)+1<=5,IF(MOD(INT(($A9-1)/7)+'Calibración de turnos'!$D$25,2)=0,"M2","T2"),"L"),IF(MOD($A9-1,7)+1<=5,IF('Calibración de turnos'!$E$25=13,"M3b","M3a"),"L"))) -> M3b
